Workbook

Sheet README
A2: The present Excel file implements simulations of the effect of a minimum wealth tax on the progressivity of the tax system and on fiscal revenues, for different countries.
A4: DATA SOURCES
A6: The file contains one sheet per data sources, containing the data which is used as input to the simulations. Specifically, we use the following studies on income distribution and tax prgressivity in different countries:
A8: Laurent Bach, Antoine Bozio, Arthur Guillouzouic, Clément Malgouyres (2025). Do Billionaires Pay Taxes?
A9: Insee (2026). Comptes nationaux distribués 2023, base 2020. CND.101 - Comptes nationaux distribués selon les vingtièmes de niveau de vie usuel
A10: Thomas Piketty, Emmanuel Saez, Gabriel Zucman (2018). Distributional National Accounts: Methods and Estimates for the United States.
A11: Akcan S. Balkir, Emmanuel Saez, Danny Yagan, Gabriel Zucman (2025). How Much Tax Do US Billionaires Pay? Evidence From Administrative Data.
A12: Theo Palomo, Davi Bhering, Thiago Scot, Pierre Bachas, Luciana Barcarolo, Celso Campos, Javier Feinmann, Leonardo Moreira, Gabriel Zucman (2025). Tax Progressivity and Inequality in Brazil: Evidence from Integrated Administrative Data.
A13: Arjan Bruil, Céline van Essen, Wouter Leenders, Arjan Lejour, Jan Möhlmann, Simon Rabaté (2025). Inequality and Redistribution in the Netherlands
A14: Demetrio Guzzardi, Elisa Palagi, Andrea Roventini, Alessandro Santoro (2024). Reconstructing Income Inequality in Italy: New Evidence and Tax System Implications from Distributional National Accounts.
A16: METHOD AND ASSUMPTIONS
A18: The simulations of tax rates and tax revenues rely on:
B20: (i) Some data tabulations describing the distribution of pre-tax income and tax rate by pre-tax income group.
B21: See Data sources. All the articles follow the same methodology and provide country-specific results in a standardized way.
B23: (ii) Some assumptions regarding the link between wealth distribution and income distribution. Specifically, we make assumptions about:
C25: (a) The income to wealth ratio within each group.
C26: Income to wealth ratio is assumed uniform over each income group.
C27: In all countries, it is taken equal to 13.0% for P99-P99.9, 10.8% for for P99.9-P99.99, 8.3% for for P99.99-P99.999, and 7.4% for P99.999-Billionaires.
C28: For billionaires, we use country specific assumptions based on the US benchmark (4,9%), that we adjust according to average wealth reported in Bilionnaires lists.
C30: See 'Income to wealth ratios' sheet.
C31: This assumption is necessary for computing the wealth tax liabilities from the income data.
C32: The only country for which there exist reliable estimates of income to wealth ratios at the very top of the income distribution is the US.
C33: US DINA files (PSZ 2018) for year 2024 show a ratio of 13,0% for P99-P99.9, 10,8% for for P99.9-P99.99, 8,3% for for P99.99-P99.999, and 7,4% for P99.999-P99.9998. See 'Income to wealth ratios' sheet.
C34: For the purpose of the simulations, we extrapolate these ratios to the other countries.
C35: Balkir et al (2025) find an income to wealth ratio of 4.9% for the top 400 billionnaires (after excluding pure realized capital gains) for years 2018-2020.
C36: For other countries, we adjust this benchmark based on some calibrations made from the average wealth per billionaire recorded in the Forbes list.
C38: (b) The distribution of wealth/income within each income group.
... C40: This assumption allows a flexible choice of wealth threshold for the simulated wealth tax.
B42: (iii) Some assumptions on the nominal income growth rate by income group.
B43: We use nominal income growth rates by income group and by country from the World Inequality Database.
B45: See 'WID' sheet and wid.world.
B46: This assumption is necessary for ageing the values of income by group from the year they are based on to 2025, in order to compute fiscal revenues for year 2025.
B47: We choose not to directly use the income distribution from the WID because the income distribution provided in each country-specific study is more granular (up to the top 0,0001% income group)
B48: than the WID data (which only goes up to the top 0,001% income group). We however apply distinct growth rates to the average income and to the income threshold of each group, based on the observed
B49: growth rates of these two variables in WID data, for each group and each country. This allows to account for changes in the income distribution that are captured by WID data.
A51: See the country-specific sheets for details of the simulation method applied from these data and assumptions. The method is the same for all the countries.
A53: ONLINE SIMULATIONS
A55: The online simulator exactly replicates the simulation method implemented in this Excel file.
A56: For each country and each income group, the 'Data' and 'Assumptions' values are provided as input to the simulations.
A57: The website then replicates the calculations implemented in the 'Simulations' columns, depending on the reform parameters chosen by the user.
A59: CONTACT INFORMATION
A61: For any comment or suggestion, please contact Léonard Mouillet (International Tax Observatory) : leonard.mouillet@psemail.eu

Sheet FRA
B2: Data (2016) | H2: Assumptions | L2: Simulations (2025)
A3: Group | B3: Number of units | C3: Income share | D3: Average income | E3: Income threshold | F3: Total tax rate | G3: Individual tax rate | H3: Income / Wealth Ratio | I3: Nominal growth rate (average) | J3: Nominal growth rate (threshold) | K3: Population growth | L3: Current wealth tax rate | M3: Average income | N3: Income threshold | O3: Wealth threshold | P3: Patero coefficient alpha | Q3: Corrected alpha | R3: Share of wealth exposed | S3: Number of units exposed | T3: Current tax rate | U3: Tax rate under reform | V3: Extra fiscal revenues
A4: P0-P10 | B4: ='Bach et al. (2025)'!C4-'Bach et al. (2025)'!C5 -> 3783411 | C4: =('Bach et al. (2025)'!F4-'Bach et al. (2025)'!F5)/100 -> 0.0015 | F4: ='Insee (2026)'!C91 -> 0.58519002
A5: P10-P20 | B5: ='Bach et al. (2025)'!C5-'Bach et al. (2025)'!C6 -> 3783612 | C5: =('Bach et al. (2025)'!F5-'Bach et al. (2025)'!F6)/100 -> 0.021 | F5: ='Insee (2026)'!E91 -> 0.44220761 | T5: =F5 -> 0.44220761 | U5: =T5 -> 0.44220761
A6: P20-P30 | B6: ='Bach et al. (2025)'!C6-'Bach et al. (2025)'!C7 -> 3783029 | C6: =('Bach et al. (2025)'!F6-'Bach et al. (2025)'!F7)/100 -> 0.0371 | F6: ='Insee (2026)'!G91 -> 0.44212399 | T6: =F6 -> 0.44212399 | U6: =T6 -> 0.44212399
A7: P30-P40 | B7: ='Bach et al. (2025)'!C7-'Bach et al. (2025)'!C8 -> 3783555 | C7: =('Bach et al. (2025)'!F7-'Bach et al. (2025)'!F8)/100 -> 0.0486 | F7: ='Insee (2026)'!I91 -> 0.46266399 | T7: =F7 -> 0.46266399 | U7: =T7 -> 0.46266399
A8: P40-P50 | B8: ='Bach et al. (2025)'!C8-'Bach et al. (2025)'!C9 -> 3783954 | C8: =('Bach et al. (2025)'!F8-'Bach et al. (2025)'!F9)/100 -> 0.062 | F8: ='Insee (2026)'!K91 -> 0.48163197 | T8: =F8 -> 0.48163197 | U8: =T8 -> 0.48163197
A9: P50-P60 | B9: ='Bach et al. (2025)'!C9-'Bach et al. (2025)'!C10 -> 3782935 | C9: =('Bach et al. (2025)'!F9-'Bach et al. (2025)'!F10)/100 -> 0.0736 | F9: ='Insee (2026)'!M91 -> 0.49227262 | T9: =F9 -> 0.49227262 | U9: =T9 -> 0.49227262
A10: P60-P70 | B10: ='Bach et al. (2025)'!C10-'Bach et al. (2025)'!C11 -> 3783286 | C10: =('Bach et al. (2025)'!F10-'Bach et al. (2025)'!F11)/100 -> 0.0915 | F10: ='Insee (2026)'!O91 -> 0.51497106 | T10: =F10 -> 0.51497106 | U10: =T10 -> 0.51497106
A11: P70-P80 | B11: ='Bach et al. (2025)'!C11-'Bach et al. (2025)'!C12 -> 3783032 | C11: =('Bach et al. (2025)'!F11-'Bach et al. (2025)'!F12)/100 -> 0.117 | F11: ='Insee (2026)'!Q91 -> 0.53154438 | T11: =F11 -> 0.53154438 | U11: =T11 -> 0.53154438
A12: P80-P90 | B12: ='Bach et al. (2025)'!C12-'Bach et al. (2025)'!C13 -> 3783370 | C12: =('Bach et al. (2025)'!F12-'Bach et al. (2025)'!F13)/100 -> 0.1586 | F12: ='Insee (2026)'!S91 -> 0.55033213 | T12: =F12 -> 0.55033213 | U12: =T12 -> 0.55033213
A13: P90-P99 | B13: ='Bach et al. (2025)'!C13-'Bach et al. (2025)'!C15 -> 3404985 | C13: =('Bach et al. (2025)'!F13-'Bach et al. (2025)'!F15)/100 -> 0.2508 | F13: =SUMPRODUCT('Bach et al. (2025)'!AA4:AA12,'Bach et al. (2025)'!I4:I12)/SUM('Bach et al. (2025)'!I4:I12)*1 + 'Insee (2026)'!U91*0 -> 0.54308957 | T13: =F13 -> 0.54308957 | U13: =T13 -> 0.54308957
A14: P99-P99.9 | B14: ='Bach et al. (2025)'!C15 - 'Bach et al. (2025)'!C16 -> 340500 | C14: =('Bach et al. (2025)'!F15-'Bach et al. (2025)'!F16)/100 -> 0.0764 | D14: =('Bach et al. (2025)'!C15*'Bach et al. (2025)'!E15 - 'Bach et al. (2025)'!E16*'Bach et al. (2025)'!C16)/('Bach et al. (2025)'!C15-'Bach et al. (2025)'!C16) -> 279445.99 | E14: ='Bach et al. (2025)'!D15 -> 180000 | F14: =SUMPRODUCT('Bach et al. (2025)'!AA13:AA21,'Bach et al. (2025)'!I13:I21)/SUM('Bach et al. (2025)'!I13:I21) -> 0.56201136 | G14: =(SUMPRODUCT('Bach et al. (2025)'!K13:K21,'Bach et al. (2025)'!I13:I21) + SUMPRODUCT('Bach et al. (2025)'!L13:L21,'Bach et al. (2025)'!I13:I21) + SUMPRODUCT('Bach et al. (2025)'!N13:N21,'Bach et al. (2025)'!I13:I21) + SUMPRODUCT('Bach et al. (2025)'!X13:X21,'Bach et al. (2025)'!I13:I21))/SUM('Bach et al. (2025)'!I13:I21) -> 0.24326656 | H14: 0.13 | I14: =WID!O5 -> 0.031988821 | J14: =WID!O36 -> 0.023686218 | K14: =WID!O$66 -> 0.0054522348 | L14: =H14*G14 -> 0.031624653 | M14: =D14*(1+I14)^9 -> 370999.07 | N14: =E14*(1+J14)^9 -> 222215.43 | O14: =(N14/H14)/1000000 -> 1.7093495 | P14: =M14/(M14-N14) -> 2.4935475 | Q14: =P14*(1-(N14/N15)^(P14-1)) -> 2.2288297 | R14: =MIN(1,MAX((M$22^(-Q14+1)-O15^(-Q14+1))/(O14^(-Q14+1)-O15^(-Q14+1)),0)) -> 0 | S14: =MIN(1,MAX((M$22^(-Q14)-O15^(-Q14))/(O14^(-Q14)-O15^(-Q14)),0))*B14*(1+K14)^9 -> 0 | T14: =F14 -> 0.56201136 | U14: =F14+MAX(0,M$23/H14-G14)*R14 -> 0.56201136 | V14: =(U14-T14)*M14*B14*(1+K14)^9/1000000 -> 0
A15: P99.9-P99.99 | B15: ='Bach et al. (2025)'!C16 - 'Bach et al. (2025)'!C17 -> 34050 | C15: =('Bach et al. (2025)'!F16-'Bach et al. (2025)'!F17)/100 -> 0.0288 | D15: =('Bach et al. (2025)'!C16*'Bach et al. (2025)'!E16 - 'Bach et al. (2025)'!E17*'Bach et al. (2025)'!C17)/('Bach et al. (2025)'!C16-'Bach et al. (2025)'!C17) -> 1052864.3 | E15: ='Bach et al. (2025)'!D16 -> 626000 | F15: =SUMPRODUCT('Bach et al. (2025)'!AA22:AA30, 'Bach et al. (2025)'!I22:I30)/ SUM('Bach et al. (2025)'!I22:I30) -> 0.53664254 | G15: =(SUMPRODUCT('Bach et al. (2025)'!K22:K30,'Bach et al. (2025)'!I22:I30) + SUMPRODUCT('Bach et al. (2025)'!L22:L30,'Bach et al. (2025)'!I22:I30) + SUMPRODUCT('Bach et al. (2025)'!N22:N30,'Bach et al. (2025)'!I22:I30) + SUMPRODUCT('Bach et al. (2025)'!X22:X30,'Bach et al. (2025)'!I22:I30) )/SUM('Bach et al. (2025)'!I22:I30) -> 0.23590774 | H15: 0.108 | I15: =WID!O6 -> 0.051621534 | J15: =WID!O37 -> 0.053136389 | K15: =WID!O$66 -> 0.0054522348 | L15: =H15*G15 -> 0.025478036 | M15: =D15*(1+I15)^9 -> 1656180.4 | N15: =E15*(1+J15)^9 -> 997552.83 | O15: =(N15/H15)/1000000 -> 9.2366003 | P15: =M15/(M15-N15) -> 2.5145932 | Q15: =P15*(1-(N15/N16)^(P15-1)) -> 2.2606245 | R15: =MIN(1,MAX((M$22^(-Q15+1)-O16^(-Q15+1))/(O15^(-Q15+1)-O16^(-Q15+1)),0)) -> 0 | S15: =MIN(1,MAX((M$22^(-Q15)-O16^(-Q15))/(O15^(-Q15)-O16^(-Q15)),0))*B15*(1+K15)^9 -> 0 | T15: =F15 -> 0.53664254 | U15: =F15+MAX(0,M$23/H15-G15)*R15 -> 0.53664254 | V15: =(U15-T15)*M15*B15*(1+K15)^9/1000000 -> 0
A16: P99.99-P99.999 | B16: ='Bach et al. (2025)'!C17 - 'Bach et al. (2025)'!C18 -> 3405 | C16: =('Bach et al. (2025)'!F17-'Bach et al. (2025)'!F18)/100 -> 0.0134 | D16: =('Bach et al. (2025)'!C17*'Bach et al. (2025)'!E17 - 'Bach et al. (2025)'!E18*'Bach et al. (2025)'!C18)/('Bach et al. (2025)'!C17-'Bach et al. (2025)'!C18) -> 4892164.8 | E16: ='Bach et al. (2025)'!D17 -> 2592000 | F16: =SUMPRODUCT('Bach et al. (2025)'!AA31:AA39,'Bach et al. (2025)'!I31:I39)/SUM('Bach et al. (2025)'!I31:I39) -> 0.45859222 | G16: =(SUMPRODUCT('Bach et al. (2025)'!K31:K39,'Bach et al. (2025)'!I31:I39) +SUMPRODUCT('Bach et al. (2025)'!L31:L39,'Bach et al. (2025)'!I31:I39) + SUMPRODUCT('Bach et al. (2025)'!N31:N39,'Bach et al. (2025)'!I31:I39) + + SUMPRODUCT('Bach et al. (2025)'!X31:X39,'Bach et al. (2025)'!I31:I39))/SUM('Bach et al. (2025)'!I31:I39) -> 0.16326935 | H16: 0.083 | I16: =WID!O7 -> 0.067228319 | J16: =WID!O38 -> 0.064060531 | K16: =WID!O$66 -> 0.0054522348 | L16: =H16*G16 -> 0.013551356 | M16: =D16*(1+I16)^9 -> 8786524.8 | N16: =E16*(1+J16)^9 -> 4532439.4 | O16: =(N16/H16)/1000000 -> 54.607704 | P16: =M16/(M16-N16) -> 2.0654321 | Q16: =P16*(1-(N16/N17)^(P16-1)) -> 1.8302845 | R16: =MIN(1,MAX((M$22^(-Q16+1)-O17^(-Q16+1))/(O16^(-Q16+1)-O17^(-Q16+1)),0)) -> 0.52585226 | S16: =MIN(1,MAX((M$22^(-Q16)-O17^(-Q16))/(O16^(-Q16)-O17^(-Q16)),0))*B16*(1+K16)^9 -> 1134.2492 | T16: =F16 -> 0.45859222 | U16: =F16+MAX(0,M$23/H16-G16)*R16 -> 0.49944806 | V16: =(U16-T16)*M16*B16*(1+K16)^9/1000000 -> 1283.6342
A17: P99.999-Billionaires | B17: ='Bach et al. (2025)'!C18 - 'Bach et al. (2025)'!C19 -> 303 | C17: =('Bach et al. (2025)'!F18-'Bach et al. (2025)'!F19)/100 -> 0.0066 | D17: =('Bach et al. (2025)'!C18*'Bach et al. (2025)'!E18 - 'Bach et al. (2025)'!E19*'Bach et al. (2025)'!C19)/('Bach et al. (2025)'!C18-'Bach et al. (2025)'!C19) -> 27015277 | E17: ='Bach et al. (2025)'!D18 -> 14876000 | F17: =AVERAGE('Bach et al. (2025)'!AA40:AA44) -> 0.32722839 | G17: =AVERAGE('Bach et al. (2025)'!K40:K44) + AVERAGE('Bach et al. (2025)'!L40:L44) + AVERAGE('Bach et al. (2025)'!N40:N44) + + AVERAGE('Bach et al. (2025)'!X40:X44) -> 0.073443388 | H17: 0.074 | I17: =WID!O8 -> 0.10834128 | J17: =WID!O39 -> 0.099163812 | K17: =WID!O$66 -> 0.0054522348 | L17: =H17*G17 -> 0.0054348107 | M17: =D17*(1+I17)^9 -> 68182200 | N17: =E17*(1+J17)^9 -> 34837579 | O17: =(N17/H17)/1000000 -> 470.77809 | P17: =M17/(M17-N17) -> 2.0447736 | Q17: =P17*(1-(N17/N18)^(P17-1)) -> 1.5809388 | R17: =MIN(1,MAX((M$22^(-Q17+1)-O18^(-Q17+1))/(O17^(-Q17+1)-O18^(-Q17+1)),0)) -> 1 | S17: =MIN(1,MAX((M$22^(-Q17)-O18^(-Q17))/(O17^(-Q17)-O18^(-Q17)),0))*B17*(1+K17)^9 -> 318.19666 | T17: =F17 -> 0.32722839 | U17: =F17+MAX(0,M$23/H17-G17)*R17 -> 0.52405527 | V17: =(U17-T17)*M17*B17*(1+K17)^9/1000000 -> 4270.2278
A18: Billionaires | B18: ='Bach et al. (2025)'!C19 -> 75 | C18: ='Bach et al. (2025)'!F19/100 -> 0.0131 | D18: ='Bach et al. (2025)'!E19 -> 217289000 | E18: ='Bach et al. (2025)'!D19 -> 61540000 | F18: ='Bach et al. (2025)'!AA45 -> 0.25752107 | G18: ='Bach et al. (2025)'!K45 + 'Bach et al. (2025)'!L45 + 'Bach et al. (2025)'!N45 + 'Bach et al. (2025)'!X45 -> 0.021091068 | H18: 0.07 | I18: =WID!O8 -> 0.10834128 | J18: =WID!O39 -> 0.099163812 | K18: =WID!O$66 -> 0.0054522348 | L18: =H18*G18 -> 0.0014763747 | M18: =D18*(1+I18)^9 -> 5.4840237e+08 | N18: =E18*(1+J18)^9 -> 1.4411835e+08 | O18: =(N18/H18)/1000000 -> 2058.8336 | P18: =M18/(M18-N18) -> 1.356478 | R18: =IF(M$22<=O18, 1, (O18/M$22)^(P18-1)) -> 1 | S18: =IF(M$22<=O18, 1, (O18/M$22)^P18)*B18*(1+K18)^9 -> 78.76155 | T18: 0.26 | U18: =T18+MAX(0,M$23/H18-G18)*R18 -> 0.52462322 | V18: =(U18-T18)*M18*B18*(1+K18)^9/1000000 -> 11429.876
S19: =SUM(S14:S18) -> 1531.2074 | V19: =SUM(V14:V18) -> 16983.738
B20: Sources: INSEE (2024) and Bach et al. (2025). See formulas.
B21: Note: Tax rates from Bach et al. (2025) are corrected for incorporating indirect taxes and contributive SSCs. | L21: Reform Parameters | T21: Summary of revenu estimates
B22: See 'Bach et al. (2025)' sheet. | L22: Threshold | M22: 100 | T22: =+V19 -> 16983.738 | U22: 0.02 | V22: 0.03
L23: Rate | M23: 0.02 | T23: 100 | U23: 16983.738 | V23: 28076.523
T24: 1000 | U24: 13070.687 | V24: 20367.647

Sheet NDL
B2: Data (2016) | H2: Assumptions | L2: Simulations (2025)
A3: Group | B3: Number of units | C3: Income share | D3: Average income | E3: Income threshold | F3: Total tax rate | G3: Individual tax rate | H3: Income / Wealth Ratio | I3: Nominal growth rate (average) | J3: Nominal growth rate (threshold) | K3: Population growth | L3: Current wealth tax rate | M3: Average income | N3: Income threshold | O3: Wealth threshold | P3: Patero coefficient alpha | Q3: Corrected alpha | R3: Share of wealth exposed | S3: Number of units exposed | T3: Current tax rate | U3: Tax rate under reform | V3: Extra fiscal revenues
A4: P0-P10 | B4: ='Bruil et al. (2025)'!J5/5 -> 1333236.8 | C4: ='Bruil et al. (2025)'!$M$5*('Bach et al. (2025)'!F4-'Bach et al. (2025)'!F5)/('Bach et al. (2025)'!$F$4-'Bach et al. (2025)'!$F$9) -> 0.0018948296
A5: P10-P20 | B5: ='Bruil et al. (2025)'!J5/5 -> 1333236.8 | C5: ='Bruil et al. (2025)'!$M$5*('Bach et al. (2025)'!F5-'Bach et al. (2025)'!F6)/('Bach et al. (2025)'!$F$4-'Bach et al. (2025)'!$F$9) -> 0.026527615 | F5: ='Bruil et al. (2025)'!G4 -> 0.50664804 | T5: =F5 -> 0.50664804 | U5: =T5 -> 0.50664804
A6: P20-P30 | B6: ='Bruil et al. (2025)'!J5/5 -> 1333236.8 | C6: ='Bruil et al. (2025)'!$M$5*('Bach et al. (2025)'!F6-'Bach et al. (2025)'!F7)/('Bach et al. (2025)'!$F$4-'Bach et al. (2025)'!$F$9) -> 0.046865452 | F6: ='Bruil et al. (2025)'!G5 -> 0.45769899 | T6: =F6 -> 0.45769899 | U6: =T6 -> 0.45769899
A7: P30-P40 | B7: ='Bruil et al. (2025)'!J5/5 -> 1333236.8 | C7: ='Bruil et al. (2025)'!$M$5*('Bach et al. (2025)'!F7-'Bach et al. (2025)'!F8)/('Bach et al. (2025)'!$F$4-'Bach et al. (2025)'!$F$9) -> 0.061392479 | F7: ='Bruil et al. (2025)'!G6 -> 0.45706849 | T7: =F7 -> 0.45706849 | U7: =T7 -> 0.45706849
A8: P40-P50 | B8: ='Bruil et al. (2025)'!J5/5 -> 1333236.8 | C8: ='Bruil et al. (2025)'!$M$5*('Bach et al. (2025)'!F8-'Bach et al. (2025)'!F9)/('Bach et al. (2025)'!$F$4-'Bach et al. (2025)'!$F$9) -> 0.078319624 | F8: ='Bruil et al. (2025)'!G7 -> 0.46145334 | T8: =F8 -> 0.46145334 | U8: =T8 -> 0.46145334
A9: P50-P60 | B9: ='Bruil et al. (2025)'!J6/4 -> 1333236.8 | C9: ='Bruil et al. (2025)'!$M$6*('Bach et al. (2025)'!F9-'Bach et al. (2025)'!F10)/('Bach et al. (2025)'!$F$9-'Bach et al. (2025)'!$F$13) -> 0.072314046 | F9: ='Bruil et al. (2025)'!G8 -> 0.46669341 | T9: =F9 -> 0.46669341 | U9: =T9 -> 0.46669341
A10: P60-P70 | B10: ='Bruil et al. (2025)'!J6/4 -> 1333236.8 | C10: ='Bruil et al. (2025)'!$M$6*('Bach et al. (2025)'!F10-'Bach et al. (2025)'!F11)/('Bach et al. (2025)'!$F$9-'Bach et al. (2025)'!$F$13) -> 0.089901293 | F10: ='Bruil et al. (2025)'!G9 -> 0.47420146 | T10: =F10 -> 0.47420146 | U10: =T10 -> 0.47420146
A11: P70-P80 | B11: ='Bruil et al. (2025)'!J6/4 -> 1333236.8 | C11: ='Bruil et al. (2025)'!$M$6*('Bach et al. (2025)'!F11-'Bach et al. (2025)'!F12)/('Bach et al. (2025)'!$F$9-'Bach et al. (2025)'!$F$13) -> 0.11495575 | F11: ='Bruil et al. (2025)'!G10 -> 0.48305826 | T11: =F11 -> 0.48305826 | U11: =T11 -> 0.48305826
A12: P80-P90 | B12: ='Bruil et al. (2025)'!J6/4 -> 1333236.8 | C12: ='Bruil et al. (2025)'!$M$6*('Bach et al. (2025)'!F12-'Bach et al. (2025)'!F13)/('Bach et al. (2025)'!$F$9-'Bach et al. (2025)'!$F$13) -> 0.15582891 | F12: ='Bruil et al. (2025)'!G11 -> 0.4862709 | T12: =F12 -> 0.4862709 | U12: =T12 -> 0.4862709
A13: P90-P99 | B13: ='Bruil et al. (2025)'!J7-'Bruil et al. (2025)'!J8 -> 1199913 | C13: ='Bruil et al. (2025)'!M7-'Bruil et al. (2025)'!M8 -> 0.212 | F13: ='Bruil et al. (2025)'!G12 -> 0.43747519 | T13: =F13 -> 0.43747519 | U13: =T13 -> 0.43747519
A14: P99-P99.9 | B14: ='Bruil et al. (2025)'!J8-'Bruil et al. (2025)'!J9 -> 119991 | C14: ='Bruil et al. (2025)'!M8-'Bruil et al. (2025)'!M9 -> 0.08 | D14: =('Bruil et al. (2025)'!L8*'Bruil et al. (2025)'!J8-'Bruil et al. (2025)'!L9*'Bruil et al. (2025)'!J9)/('Bruil et al. (2025)'!J8-'Bruil et al. (2025)'!J9) -> 395560.73 | E14: ='Bruil et al. (2025)'!K8 -> 226162 | F14: ='Bruil et al. (2025)'!G13 -> 0.27181551 | G14: ='Bruil et al. (2025)'!C13 -> 0.11227558 | H14: 0.13 | I14: =WID!O15 -> 0.052374181 | J14: =WID!O46 -> 0.052430928 | K14: =WID!O$68 -> 0.010294291 | L14: =H14*G14 -> 0.014595825 | M14: =D14*(1+I14)^9 -> 626245.8 | N14: =E14*(1+J14)^9 -> 358230.08 | O14: =(N14/H14)/1000000 -> 2.755616 | P14: =M14/(M14-N14) -> 2.336601 | Q14: =P14*(1-(N14/N15)^(P14-1)) -> 1.9986133 | R14: =MIN(1,MAX((M$22^(-Q14+1)-O15^(-Q14+1))/(O14^(-Q14+1)-O15^(-Q14+1)),0)) -> 0 | S14: =MIN(1,MAX((M$22^(-Q14)-O15^(-Q14))/(O14^(-Q14)-O15^(-Q14)),0))*B14*(1+K14)^9 -> 0 | T14: =F14 -> 0.27181551 | U14: =F14+MAX(0,M$23/H14-G14)*R14 -> 0.27181551 | V14: =(U14-T14)*M14*B14*(1+K14)^9/1000000 -> 0
A15: P99.9-P99.99 | B15: ='Bruil et al. (2025)'!J9-'Bruil et al. (2025)'!J10 -> 11999 | C15: ='Bruil et al. (2025)'!M9-'Bruil et al. (2025)'!M10 -> 0.036 | D15: =('Bruil et al. (2025)'!L9*'Bruil et al. (2025)'!J9-'Bruil et al. (2025)'!L10*'Bruil et al. (2025)'!J10)/('Bruil et al. (2025)'!J9-'Bruil et al. (2025)'!J10) -> 1780094.1 | E15: ='Bruil et al. (2025)'!K9 -> 1023879 | F15: ='Bruil et al. (2025)'!G14 -> 0.21413333 | G15: ='Bruil et al. (2025)'!C14 -> 0.061872382 | H15: 0.108 | I15: =WID!O16 -> 0.044324266 | J15: =WID!O47 -> 0.045024033 | K15: =WID!O$68 -> 0.010294291 | L15: =H15*G15 -> 0.0066822173 | M15: =D15*(1+I15)^9 -> 2630033.5 | N15: =E15*(1+J15)^9 -> 1521896.6 | O15: =(N15/H15)/1000000 -> 14.091635 | P15: =M15/(M15-N15) -> 2.3733831 | Q15: =P15*(1-(N15/N16)^(P15-1)) -> 2.0478618 | R15: =MIN(1,MAX((M$22^(-Q15+1)-O16^(-Q15+1))/(O15^(-Q15+1)-O16^(-Q15+1)),0)) -> 0 | S15: =MIN(1,MAX((M$22^(-Q15)-O16^(-Q15))/(O15^(-Q15)-O16^(-Q15)),0))*B15*(1+K15)^9 -> 0 | T15: =F15 -> 0.21413333 | U15: =F15+MAX(0,M$23/H15-G15)*R15 -> 0.21413333 | V15: =(U15-T15)*M15*B15*(1+K15)^9/1000000 -> 0
A16: P99.99-P99.999 | B16: ='Bruil et al. (2025)'!J10-'Bruil et al. (2025)'!J11 -> 1200 | C16: ='Bruil et al. (2025)'!M10-'Bruil et al. (2025)'!M11 -> 0.016 | D16: =('Bruil et al. (2025)'!L10*'Bruil et al. (2025)'!J10-'Bruil et al. (2025)'!L11*'Bruil et al. (2025)'!J11)/('Bruil et al. (2025)'!J10-'Bruil et al. (2025)'!J11) -> 7606596 | E16: ='Bruil et al. (2025)'!K10 -> 4372218 | F16: ='Bruil et al. (2025)'!G15 -> 0.19061302 | G16: ='Bruil et al. (2025)'!C15 -> 0.044620932 | H16: 0.083 | I16: =WID!O17 -> 0.046466517 | J16: =WID!O48 -> 0.044427469 | K16: =WID!O$68 -> 0.010294291 | L16: =H16*G16 -> 0.0037035373 | M16: =D16*(1+I16)^9 -> 11447704 | N16: =E16*(1+J16)^9 -> 6465563.5 | O16: =(N16/H16)/1000000 -> 77.898355 | P16: =M16/(M16-N16) -> 2.2977481 | Q16: =P16*(1-(N16/N17)^(P16-1)) -> 1.9307494 | R16: =MIN(1,MAX((M$22^(-Q16+1)-O17^(-Q16+1))/(O16^(-Q16+1)-O17^(-Q16+1)),0)) -> 0.72666454 | S16: =MIN(1,MAX((M$22^(-Q16)-O17^(-Q16))/(O16^(-Q16)-O17^(-Q16)),0))*B16*(1+K16)^9 -> 784.63366 | T16: =F16 -> 0.19061302 | U16: =F16+MAX(0,M$23/H16-G16)*R16 -> 0.33328846 | V16: =(U16-T16)*M16*B16*(1+K16)^9/1000000 -> 2149.2154
A17: P99.999-Billionaires | B17: ='Bruil et al. (2025)'!J11-'Bruil et al. (2025)'!J12 -> 120 | C17: ='Bruil et al. (2025)'!M11-'Bruil et al. (2025)'!M12 -> 0.006 | D17: =('Bruil et al. (2025)'!L11*'Bruil et al. (2025)'!J11-'Bruil et al. (2025)'!L12*'Bruil et al. (2025)'!J12)/('Bruil et al. (2025)'!J11-'Bruil et al. (2025)'!J12) -> 32324145 | E17: ='Bruil et al. (2025)'!K11 -> 18828918 | F17: ='Bruil et al. (2025)'!G16 -> 0.18179299 | G17: ='Bruil et al. (2025)'!C16 -> 0.02212867 | H17: 0.074 | I17: =WID!O18 -> 0.036261402 | J17: =WID!O49 -> 0.03902733 | K17: =WID!O$68 -> 0.010294291 | L17: =H17*G17 -> 0.0016375216 | M17: =D17*(1+I17)^9 -> 44540074 | N17: =E17*(1+J17)^9 -> 26574684 | O17: =(N17/H17)/1000000 -> 359.11735 | P17: =M17/(M17-N17) -> 2.4792155 | Q17: =P17*(1-(N17/N18)^(P17-1)) -> 2.233169 | R17: =MIN(1,MAX((M$22^(-Q17+1)-O18^(-Q17+1))/(O17^(-Q17+1)-O18^(-Q17+1)),0)) -> 1 | S17: =MIN(1,MAX((M$22^(-Q17)-O18^(-Q17))/(O17^(-Q17)-O18^(-Q17)),0))*B17*(1+K17)^9 -> 131.5868 | T17: =F17 -> 0.18179299 | U17: =F17+MAX(0,M$23/H17-G17)*R17 -> 0.42993459 | V17: =(U17-T17)*M17*B17*(1+K17)^9/1000000 -> 1454.3296
A18: Billionaires | B18: ='Bruil et al. (2025)'!J12 -> 14 | C18: ='Bruil et al. (2025)'!M12 -> 0.003 | D18: ='Bruil et al. (2025)'!L12 -> 111562388 | E18: ='Bruil et al. (2025)'!K12 -> 89761129 | F18: ='Bruil et al. (2025)'!G17 -> 0.16443377 | G18: ='Bruil et al. (2025)'!C17 -> 0.0023009031 | H18: 0.07 | I18: =WID!O18 -> 0.036261402 | J18: =WID!O49 -> 0.03902733 | K18: =WID!O$68 -> 0.010294291 | L18: =H18*G18 -> 0.00016106322 | M18: =D18*(1+I18)^9 -> 1.5372401e+08 | N18: =E18*(1+J18)^9 -> 1.2668671e+08 | O18: =(N18/H18)/1000000 -> 1809.8101 | P18: =M18/(M18-N18) -> 5.685627 | R18: =IF(M$22<=O18, 1, (O18/M$22)^(P18-1)) -> 1 | S18: =IF(M$22<=O18, 1, (O18/M$22)^P18)*B18*(1+K18)^9 -> 15.351794 | T18: 0.26 | U18: =T18+MAX(0,M$23/H18-G18)*R18 -> 0.54341338 | V18: =(U18-T18)*M18*B18*(1+K18)^9/1000000 -> 668.83837
S19: =SUM(S14:S18) -> 931.57226 | V19: =SUM(V14:V18) -> 4272.3834
B20: Source: Bruil et al (2025). See formulas.
B21: Note: For dissagregating income shares within the bottom 50% and the middle 40%, we use the shares observed in France. | L21: Reform Parameters | T21: Summary of revenu estimates
L22: Threshold | M22: 100 | T22: =+V19 -> 4272.3834 | U22: 0.02 | V22: 0.03
L23: Rate | M23: 0.02 | T23: 100 | U23: 4272.3834 | V23: 6720.3525
T24: 1000 | U24: 915.87086 | V24: 1387.5362

Sheet USA
B2: Data (2024) | H2: Assumptions | L2: Simulations (2025)
A3: Group | B3: Number of units | C3: Income share | D3: Average income | E3: Income threshold | F3: Total tax rate | G3: Individual tax rate | H3: Income / Wealth Ratio | I3: Nominal growth rate (average) | J3: Nominal growth rate (threshold) | K3: Population growth | L3: Current wealth tax rate | M3: Average income | N3: Income threshold | O3: Wealth threshold | P3: Patero coefficient alpha | Q3: Corrected alpha | R3: Share of wealth exposed | S3: Number of units exposed | T3: Current tax rate | U3: Tax rate under reform | V3: Extra fiscal revenues
A4: P0-P10 | B4: =SUM('Piketty, Saez, Zucman (2018)'!C4:C13) -> 18271113 | C4: =SUM('Piketty, Saez, Zucman (2018)'!E4:E13) -> 0.0046 | F4: =SUMPRODUCT('Piketty, Saez, Zucman (2018)'!H4:H13, 'Piketty, Saez, Zucman (2018)'!$F4:$F13)/SUM('Piketty, Saez, Zucman (2018)'!$F4:$F13) + R21*SUMPRODUCT('Piketty, Saez, Zucman (2018)'!O4:O13, 'Piketty, Saez, Zucman (2018)'!$F4:$F13)/SUM('Piketty, Saez, Zucman (2018)'!$F4:$F13) -> 0.39046205
A5: P10-P20 | B5: =SUM('Piketty, Saez, Zucman (2018)'!C14:C23) -> 18273171 | C5: =SUM('Piketty, Saez, Zucman (2018)'!E14:E23) -> 0.01312 | F5: =SUMPRODUCT('Piketty, Saez, Zucman (2018)'!H14:H23, 'Piketty, Saez, Zucman (2018)'!$F14:$F23)/SUM('Piketty, Saez, Zucman (2018)'!$F14:$F23) + R21*SUMPRODUCT('Piketty, Saez, Zucman (2018)'!O14:O23, 'Piketty, Saez, Zucman (2018)'!$F14:$F23)/SUM('Piketty, Saez, Zucman (2018)'!$F14:$F23) -> 0.25941116 | T5: =F5 -> 0.25941116 | U5: =T5 -> 0.25941116
A6: P20-P30 | B6: =SUM('Piketty, Saez, Zucman (2018)'!C24:C33) -> 18272267 | C6: =SUM('Piketty, Saez, Zucman (2018)'!E24:E33) -> 0.02089 | F6: =SUMPRODUCT('Piketty, Saez, Zucman (2018)'!H24:H33, 'Piketty, Saez, Zucman (2018)'!$F24:$F33)/SUM('Piketty, Saez, Zucman (2018)'!$F24:$F33) + R21*SUMPRODUCT('Piketty, Saez, Zucman (2018)'!O24:O33, 'Piketty, Saez, Zucman (2018)'!$F24:$F33)/SUM('Piketty, Saez, Zucman (2018)'!$F24:$F33) -> 0.24822442 | T6: =F6 -> 0.24822442 | U6: =T6 -> 0.24822442
A7: P30-P40 | B7: =SUM('Piketty, Saez, Zucman (2018)'!C34:C43) -> 18271128 | C7: =SUM('Piketty, Saez, Zucman (2018)'!E34:E43) -> 0.02933 | F7: =SUMPRODUCT('Piketty, Saez, Zucman (2018)'!H34:H43, 'Piketty, Saez, Zucman (2018)'!$F34:$F43)/SUM('Piketty, Saez, Zucman (2018)'!$F34:$F43) + R21*SUMPRODUCT('Piketty, Saez, Zucman (2018)'!O34:O43, 'Piketty, Saez, Zucman (2018)'!$F34:$F43)/SUM('Piketty, Saez, Zucman (2018)'!$F34:$F43) -> 0.26313325 | T7: =F7 -> 0.26313325 | U7: =T7 -> 0.26313325
A8: P40-P50 | B8: =SUM('Piketty, Saez, Zucman (2018)'!C44:C53) -> 18272260 | C8: =SUM('Piketty, Saez, Zucman (2018)'!E44:E53) -> 0.03921 | F8: =SUMPRODUCT('Piketty, Saez, Zucman (2018)'!H44:H53, 'Piketty, Saez, Zucman (2018)'!$F44:$F53)/SUM('Piketty, Saez, Zucman (2018)'!$F44:$F53) + R21*SUMPRODUCT('Piketty, Saez, Zucman (2018)'!O44:O53, 'Piketty, Saez, Zucman (2018)'!$F44:$F53)/SUM('Piketty, Saez, Zucman (2018)'!$F44:$F53) -> 0.26624154 | T8: =F8 -> 0.26624154 | U8: =T8 -> 0.26624154
A9: P50-P60 | B9: =SUM('Piketty, Saez, Zucman (2018)'!C54:C63) -> 18271308 | C9: =SUM('Piketty, Saez, Zucman (2018)'!E54:E63) -> 0.051059999 | F9: =SUMPRODUCT('Piketty, Saez, Zucman (2018)'!H54:H63, 'Piketty, Saez, Zucman (2018)'!$F54:$F63)/SUM('Piketty, Saez, Zucman (2018)'!$F54:$F63) + R21*SUMPRODUCT('Piketty, Saez, Zucman (2018)'!O54:O63, 'Piketty, Saez, Zucman (2018)'!$F54:$F63)/SUM('Piketty, Saez, Zucman (2018)'!$F54:$F63) -> 0.28002967 | T9: =F9 -> 0.28002967 | U9: =T9 -> 0.28002967
A10: P60-P70 | B10: =SUM('Piketty, Saez, Zucman (2018)'!C64:C73) -> 18273673 | C10: =SUM('Piketty, Saez, Zucman (2018)'!E64:E73) -> 0.07135 | F10: =SUMPRODUCT('Piketty, Saez, Zucman (2018)'!H64:H73, 'Piketty, Saez, Zucman (2018)'!$F64:$F73)/SUM('Piketty, Saez, Zucman (2018)'!$F64:$F73) + R21*SUMPRODUCT('Piketty, Saez, Zucman (2018)'!O64:O73, 'Piketty, Saez, Zucman (2018)'!$F64:$F73)/SUM('Piketty, Saez, Zucman (2018)'!$F64:$F73) -> 0.29269838 | T10: =F10 -> 0.29269838 | U10: =T10 -> 0.29269838
A11: P70-P80 | B11: =SUM('Piketty, Saez, Zucman (2018)'!C74:C83) -> 18271441 | C11: =SUM('Piketty, Saez, Zucman (2018)'!E74:E83) -> 0.10444 | F11: =SUMPRODUCT('Piketty, Saez, Zucman (2018)'!H74:H83, 'Piketty, Saez, Zucman (2018)'!$F74:$F83)/SUM('Piketty, Saez, Zucman (2018)'!$F74:$F83) + R21*SUMPRODUCT('Piketty, Saez, Zucman (2018)'!O74:O83, 'Piketty, Saez, Zucman (2018)'!$F74:$F83)/SUM('Piketty, Saez, Zucman (2018)'!$F74:$F83) -> 0.29686721 | T11: =F11 -> 0.29686721 | U11: =T11 -> 0.29686721
A12: P80-P90 | B12: =SUM('Piketty, Saez, Zucman (2018)'!C84:C93) -> 18272475 | C12: =SUM('Piketty, Saez, Zucman (2018)'!E84:E93) -> 0.15636 | F12: =SUMPRODUCT('Piketty, Saez, Zucman (2018)'!H84:H93, 'Piketty, Saez, Zucman (2018)'!$F84:$F93)/SUM('Piketty, Saez, Zucman (2018)'!$F84:$F93) + R21*SUMPRODUCT('Piketty, Saez, Zucman (2018)'!O84:O93, 'Piketty, Saez, Zucman (2018)'!$F84:$F93)/SUM('Piketty, Saez, Zucman (2018)'!$F84:$F93) -> 0.29981626 | T12: =F12 -> 0.29981626 | U12: =T12 -> 0.29981626
A13: P90-P99 | B13: =SUM('Piketty, Saez, Zucman (2018)'!C94:C102) -> 16445819 | C13: =SUM('Piketty, Saez, Zucman (2018)'!E94:E102) -> 0.28881 | F13: =SUMPRODUCT('Piketty, Saez, Zucman (2018)'!H94:H102, 'Piketty, Saez, Zucman (2018)'!$F94:$F102)/SUM('Piketty, Saez, Zucman (2018)'!$F94:$F102) + R21*SUMPRODUCT('Piketty, Saez, Zucman (2018)'!O94:O102, 'Piketty, Saez, Zucman (2018)'!$F94:$F102)/SUM('Piketty, Saez, Zucman (2018)'!$F94:$F102) -> 0.31978189 | T13: =F13 -> 0.31978189 | U13: =T13 -> 0.31978189
A14: P99-P99.9 | B14: =SUM('Piketty, Saez, Zucman (2018)'!C103:C111) -> 1644714 | C14: =SUM('Piketty, Saez, Zucman (2018)'!E103:E111) -> 0.11222 | D14: =AVERAGE('Piketty, Saez, Zucman (2018)'!$F103:$F111) -> 1652421.3 | E14: ='Piketty, Saez, Zucman (2018)'!D103 -> 979000 | F14: =SUMPRODUCT('Piketty, Saez, Zucman (2018)'!H103:H111, 'Piketty, Saez, Zucman (2018)'!$F103:$F111)/SUM('Piketty, Saez, Zucman (2018)'!$F103:$F111) + R21*SUMPRODUCT('Piketty, Saez, Zucman (2018)'!O103:O111, 'Piketty, Saez, Zucman (2018)'!$F103:$F111)/SUM('Piketty, Saez, Zucman (2018)'!$F103:$F111) -> 0.33559856 | G14: =SUMPRODUCT('Piketty, Saez, Zucman (2018)'!L103:L111, 'Piketty, Saez, Zucman (2018)'!$F103:$F111)/SUM('Piketty, Saez, Zucman (2018)'!$F103:$F111) -> 0.20279507 | H14: 0.13 | I14: =WID!O10 -> 0.053230665 | J14: =WID!O10 -> 0.053230665 | K14: =WID!O$67 -> 0.0092025446 | L14: =H14*G14 -> 0.026363359 | M14: =D14*(1+I14)^1 -> 1740380.8 | N14: =E14*(1+J14) -> 1031112.8 | O14: =(N14/H14)/1000000 -> 7.9316371 | P14: =M14/(M14-N14) -> 2.4537704 | Q14: =P14*(1-(N14/N15)^(P14-1)) -> 2.1727892 | R14: =MIN(1,MAX((M$22^(-Q14+1)-O15^(-Q14+1))/(O14^(-Q14+1)-O15^(-Q14+1)),0)) -> 0 | S14: =MIN(1,MAX((M$22^(-Q14)-O15^(-Q14))/(O14^(-Q14)-O15^(-Q14)),0))*B14*(1+K14)^1 -> 0 | T14: =F14 -> 0.33559856 | U14: =F14+MAX(0,M$23/H14-G14)*R14 -> 0.33559856 | V14: =(U14-T14)*M14*B14*(1+K14)/1000000 -> 0
A15: P99.9-P99.99 | B15: =SUM('Piketty, Saez, Zucman (2018)'!C112:C120) -> 164455 | C15: =SUM('Piketty, Saez, Zucman (2018)'!E112:E120) -> 0.053910001 | D15: =AVERAGE('Piketty, Saez, Zucman (2018)'!$F112:$F120) -> 7936218.6 | E15: ='Piketty, Saez, Zucman (2018)'!D112 -> 4280000 | F15: =SUMPRODUCT('Piketty, Saez, Zucman (2018)'!H112:H120, 'Piketty, Saez, Zucman (2018)'!$F112:$F120)/SUM('Piketty, Saez, Zucman (2018)'!$F112:$F120) + R21*SUMPRODUCT('Piketty, Saez, Zucman (2018)'!O112:O120, 'Piketty, Saez, Zucman (2018)'!$F112:$F120)/SUM('Piketty, Saez, Zucman (2018)'!$F112:$F120) -> 0.37579076 | G15: =SUMPRODUCT('Piketty, Saez, Zucman (2018)'!L112:L120, 'Piketty, Saez, Zucman (2018)'!$F112:$F120)/SUM('Piketty, Saez, Zucman (2018)'!$F112:$F120) -> 0.23315599 | H15: 0.108 | I15: =WID!O11 -> 0.069676856 | J15: =WID!O11 -> 0.069676856 | K15: =WID!O$67 -> 0.0092025446 | L15: =H15*G15 -> 0.025180847 | M15: =D15*(1+I15)^1 -> 8489189.3 | N15: =E15*(1+J15) -> 4578216.9 | O15: =(N15/H15)/1000000 -> 42.390898 | P15: =M15/(M15-N15) -> 2.1706084 | Q15: =P15*(1-(N15/N16)^(P15-1)) -> 1.8692501 | R15: =MIN(1,MAX((M$22^(-Q15+1)-O16^(-Q15+1))/(O15^(-Q15+1)-O16^(-Q15+1)),0)) -> 0.35601799 | S15: =MIN(1,MAX((M$22^(-Q15)-O16^(-Q15))/(O15^(-Q15)-O16^(-Q15)),0))*B15*(1+K15)^1 -> 29809.439 | T15: =F15 -> 0.37579076 | U15: =F15+MAX(0,M$23/H15-G15)*R15 -> 0.37579076 | V15: =(U15-T15)*M15*B15*(1+K15)/1000000 -> 0
A16: P99.99-P99.999 | B16: =SUM('Piketty, Saez, Zucman (2018)'!C121:C129) -> 16442 | C16: =SUM('Piketty, Saez, Zucman (2018)'!E121:E129) -> 0.02879 | D16: =AVERAGE('Piketty, Saez, Zucman (2018)'!$F121:$F129) -> 42405660 | E16: ='Piketty, Saez, Zucman (2018)'!D121 -> 22800000 | F16: =SUMPRODUCT('Piketty, Saez, Zucman (2018)'!H121:H129, 'Piketty, Saez, Zucman (2018)'!$F121:$F129)/SUM('Piketty, Saez, Zucman (2018)'!$F121:$F129) + R21*SUMPRODUCT('Piketty, Saez, Zucman (2018)'!O121:O129, 'Piketty, Saez, Zucman (2018)'!$F121:$F129)/SUM('Piketty, Saez, Zucman (2018)'!$F121:$F129) -> 0.35651367 | G16: =SUMPRODUCT('Piketty, Saez, Zucman (2018)'!L121:L129, 'Piketty, Saez, Zucman (2018)'!$F121:$F129)/SUM('Piketty, Saez, Zucman (2018)'!$F121:$F129) -> 0.20636722 | H16: 0.083 | I16: =WID!O12 -> 0.084639076 | J16: =WID!O12 -> 0.084639076 | K16: =WID!O$67 -> 0.0092025446 | L16: =H16*G16 -> 0.017128479 | M16: =D16*(1+I16)^1 -> 45994835 | N16: =E16*(1+J16) -> 24729771 | O16: =(N16/H16)/1000000 -> 297.94905 | P16: =M16/(M16-N16) -> 2.1629295 | Q16: =P16*(1-(N16/N17)^(P16-1)) -> 1.8546145 | R16: =MIN(1,MAX((M$22^(-Q16+1)-O17^(-Q16+1))/(O16^(-Q16+1)-O17^(-Q16+1)),0)) -> 1 | S16: =MIN(1,MAX((M$22^(-Q16)-O17^(-Q16))/(O16^(-Q16)-O17^(-Q16)),0))*B16*(1+K16)^1 -> 16593.308 | T16: =F16 -> 0.35651367 | U16: =F16+MAX(0,M$23/H16-G16)*R16 -> 0.39111031 | V16: =(U16-T16)*M16*B16*(1+K16)/1000000 -> 26404.378
A17: P99.999-Billionaires | B17: ='Piketty, Saez, Zucman (2018)'!C130 -> 1431 | C17: ='Piketty, Saez, Zucman (2018)'!E130 -> 0.00985 | D17: ='Piketty, Saez, Zucman (2018)'!F130 -> 166643920 | E17: ='Piketty, Saez, Zucman (2018)'!D130 -> 119000000 | F17: ='Piketty, Saez, Zucman (2018)'!H130 + R21*'Piketty, Saez, Zucman (2018)'!O130 -> 0.29605398 | G17: ='Piketty, Saez, Zucman (2018)'!L130 -> 0.13085756 | H17: 0.074 | I17: =WID!O13 -> 0.10965318 | J17: =WID!O13 -> 0.10965318 | K17: =WID!O$67 -> 0.0092025446 | L17: =H17*G17 -> 0.0096834592 | M17: =D17*(1+I17)^1 -> 1.8491696e+08 | N17: =E17*(1+J17) -> 1.3204873e+08 | O17: =(N17/H17)/1000000 -> 1784.4423 | P17: =M17/(M17-N17) -> 3.4976954 | Q17: =P17*(1-(N17/N18)^(P17-1)) -> -0.30326201 | R17: =MIN(1,MAX((M$22^(-Q17+1)-O18^(-Q17+1))/(O17^(-Q17+1)-O18^(-Q17+1)),0)) -> 1 | S17: =MIN(1,MAX((M$22^(-Q17)-O18^(-Q17))/(O17^(-Q17)-O18^(-Q17)),0))*B17*(1+K17)^1 -> 1444.1688 | T17: =F17 -> 0.29605398 | U17: =F17+MAX(0,M$23/H17-G17)*R17 -> 0.43546669 | V17: =(U17-T17)*M17*B17*(1+K17)/1000000 -> 37230.347
A18: Billionaires | B18: ='Piketty, Saez, Zucman (2018)'!C131 -> 411 | C18: =D18*B18/(D14*B14/C14) -> 0.0067196797 | D18: ='Balkir et al. (2025)'!D10 -> 3.9595668e+08 | E18: =D18/3.44 -> 1.1510368e+08 | F18: ='Balkir et al. (2025)'!F10 -> 0.27186661 | G18: ='Balkir et al. (2025)'!G10*('Piketty, Saez, Zucman (2018)'!L130)/('Piketty, Saez, Zucman (2018)'!L130+'Piketty, Saez, Zucman (2018)'!K130) -> 0.12347621 | H18: 0.049 | I18: =WID!O13 -> 0.10965318 | J18: =WID!O13 -> 0.10965318 | K18: =WID!O$67 -> 0.0092025446 | L18: =H18*G18 -> 0.0060503341 | M18: =D18*(1+I18)^1 -> 4.3937459e+08 | N18: =E18*(1+J18) -> 1.2772517e+08 | O18: =(N18/H18)/1000000 -> 2606.6361 | P18: =M18/(M18-N18) -> 1.4098361 | R18: =IF(M$22<=O18, 1, (O18/M$22)^(P18-1)) -> 1 | S18: =IF(M$22<=O18, 1, (O18/M$22)^P18)*B18*(1+K18)^1 -> 414.78225 | T18: 0.26 | U18: =T18+MAX(0,M$23/H18-G18)*R18 -> 0.54468706 | V18: =(U18-T18)*M18*B18*(1+K18)/1000000 -> 51882.73
S19: =SUM(S14:S18) -> 48261.698 | V19: =SUM(V14:V18) -> 115517.45
B20: Sources: US DINA files for 2024 (PSZ, 2018) and Balkir et al. (2025). See formulas.
B21: Note: For computing income threshold for the billionnaires group, we apply the Pareto coefficient b = 3,44 from Saez & Zucman (2020). | L21: Reform Parameters | O21: Include health premiums in total taxes | R21: 0 | T21: Summary of revenu estimates
B22: See SaezZucman2020JEPData.xlsx, sheet DataF1(Forbes). | L22: Threshold | M22: 100 | T22: =+V19 -> 115517.45 | U22: 0.02 | V22: 0.03
L23: Rate | M23: 0.02 | T23: 100 | U23: 115517.45 | V23: 303133.47
T24: 1000 | U24: 93787.937 | V24: 183348.85

Sheet BRA
B2: Data (2019) | H2: Assumptions | L2: Simulations (2025)
A3: Group | B3: Number of units | C3: Income share | D3: Average income | E3: Income threshold | F3: Total tax rate | G3: Individual tax rate | H3: Income / Wealth Ratio | I3: Nominal growth rate (average) | J3: Nominal growth rate (threshold) | K3: Population growth | L3: Current wealth tax rate | M3: Average income | N3: Income threshold | O3: Wealth threshold | P3: Patero coefficient alpha | Q3: Corrected alpha | R3: Share of wealth exposed | S3: Number of units exposed | T3: Current tax rate | U3: Tax rate under reform | V3: Extra fiscal revenues
A4: P0-P10 | B4: ='Palomo et al. (2025)'!L6-'Palomo et al. (2025)'!L7 -> 15175032 | C4: ='Palomo et al. (2025)'!Q4-'Palomo et al. (2025)'!Q5 -> 0.0015
A5: P10-P20 | B5: ='Palomo et al. (2025)'!L6-'Palomo et al. (2025)'!L7 -> 15175032 | C5: =('Palomo et al. (2025)'!Q5-'Palomo et al. (2025)'!Q6)*('Bach et al. (2025)'!F5-'Bach et al. (2025)'!F6)/('Bach et al. (2025)'!F5-'Bach et al. (2025)'!F7) -> 0.012525374 | F5: ='Palomo et al. (2025)'!C5 -> 0.48921796 | T5: =F5 -> 0.48921796 | U5: =T5 -> 0.48921796
A6: P20-P30 | B6: ='Palomo et al. (2025)'!L6-'Palomo et al. (2025)'!L7 -> 15175032 | C6: =('Palomo et al. (2025)'!Q5-'Palomo et al. (2025)'!Q6)*('Bach et al. (2025)'!F6-'Bach et al. (2025)'!F7)/('Bach et al. (2025)'!F5-'Bach et al. (2025)'!F7) -> 0.02212816 | F6: ='Palomo et al. (2025)'!C5 -> 0.48921796 | T6: =F6 -> 0.48921796 | U6: =T6 -> 0.48921796
A7: P30-P40 | B7: ='Palomo et al. (2025)'!L6-'Palomo et al. (2025)'!L7 -> 15175032 | C7: ='Palomo et al. (2025)'!Q6-'Palomo et al. (2025)'!Q7 -> 0.034106318 | F7: ='Palomo et al. (2025)'!C6 -> 0.4809789 | T7: =F7 -> 0.4809789 | U7: =T7 -> 0.4809789
A8: P40-P50 | B8: ='Palomo et al. (2025)'!L7-'Palomo et al. (2025)'!L8 -> 15175032 | C8: ='Palomo et al. (2025)'!Q7-'Palomo et al. (2025)'!Q8 -> 0.041189 | F8: ='Palomo et al. (2025)'!C7 -> 0.44749116 | T8: =F8 -> 0.44749116 | U8: =T8 -> 0.44749116
A9: P50-P60 | B9: ='Palomo et al. (2025)'!L8-'Palomo et al. (2025)'!L9 -> 15175032 | C9: ='Palomo et al. (2025)'!Q8-'Palomo et al. (2025)'!Q9 -> 0.049900362 | F9: ='Palomo et al. (2025)'!C8 -> 0.46344125 | T9: =F9 -> 0.46344125 | U9: =T9 -> 0.46344125
A10: P60-P70 | B10: ='Palomo et al. (2025)'!L9-'Palomo et al. (2025)'!L10 -> 15175032 | C10: ='Palomo et al. (2025)'!Q9-'Palomo et al. (2025)'!Q10 -> 0.062538191 | F10: ='Palomo et al. (2025)'!C9 -> 0.46875623 | T10: =F10 -> 0.46875623 | U10: =T10 -> 0.46875623
A11: P70-P80 | B11: ='Palomo et al. (2025)'!L10-'Palomo et al. (2025)'!L11 -> 15687814 | C11: ='Palomo et al. (2025)'!Q10-'Palomo et al. (2025)'!Q11 -> 0.056502347 | F11: ='Palomo et al. (2025)'!C10 -> 0.4378783 | T11: =F11 -> 0.4378783 | U11: =T11 -> 0.4378783
A12: P80-P90 | B12: ='Palomo et al. (2025)'!L11-'Palomo et al. (2025)'!L12 -> 14918641 | C12: ='Palomo et al. (2025)'!Q11-'Palomo et al. (2025)'!Q12 -> 0.13112195 | F12: ='Palomo et al. (2025)'!C11 -> 0.49957817 | T12: =F12 -> 0.49957817 | U12: =T12 -> 0.49957817
A13: P90-P99 | B13: ='Palomo et al. (2025)'!L12-'Palomo et al. (2025)'!L14 -> 13426770 | C13: ='Palomo et al. (2025)'!Q12-'Palomo et al. (2025)'!Q14 -> 0.33229163 | F13: =('Palomo et al. (2025)'!C12*('Palomo et al. (2025)'!Q12-'Palomo et al. (2025)'!Q13)+'Palomo et al. (2025)'!C13*('Palomo et al. (2025)'!Q13-'Palomo et al. (2025)'!Q14))/('Palomo et al. (2025)'!Q12-'Palomo et al. (2025)'!Q14) -> 0.4539918 | T13: =F13 -> 0.4539918 | U13: =T13 -> 0.4539918
A14: P99-P99.9 | B14: ='Palomo et al. (2025)'!L14-'Palomo et al. (2025)'!L15 -> 1342683 | C14: ='Palomo et al. (2025)'!Q14-'Palomo et al. (2025)'!Q15 -> 0.13925629 | D14: =('Palomo et al. (2025)'!L14*'Palomo et al. (2025)'!P14-'Palomo et al. (2025)'!L15*'Palomo et al. (2025)'!P15)/('Palomo et al. (2025)'!L14-'Palomo et al. (2025)'!L15) -> 150587.81 | E14: ='Palomo et al. (2025)'!O14 -> 92934.491 | F14: ='Palomo et al. (2025)'!C14 -> 0.30034455 | G14: ='Palomo et al. (2025)'!F14 + 'Palomo et al. (2025)'!H14 -> 0.0954156 | H14: 0.13 | I14: =WID!O20 -> 0.1131934 | J14: =WID!O51 -> 0.10086835 | K14: =WID!O$69 -> 0.010179449 | L14: =H14*G14 -> 0.012404028 | M14: =D14*(1+I14)^6 -> 286558.67 | N14: =E14*(1+J14)^6 -> 165420.46 | O14: =(N14/H14)/1000000 -> 1.2724651 | P14: =M14/(M14-N14) -> 2.3655515 | Q14: =P14*(1-(N14/N15)^(P14-1)) -> 1.9824501 | R14: =MIN(1,MAX((M$22^(-Q14+1)-O15^(-Q14+1))/(O14^(-Q14+1)-O15^(-Q14+1)),0)) -> 0 | S14: =MIN(1,MAX((M$22^(-Q14)-O15^(-Q14))/(O14^(-Q14)-O15^(-Q14)),0))*B14*(1+K14)^6 -> 0 | T14: =F14 -> 0.30034455 | U14: =F14+MAX(0,M$23/H14-G14)*R14 -> 0.30034455 | V14: =(U14-T14)*M14*B14*(1+K14)^6/1000000 -> 0
A15: P99.9-P99.99 | B15: ='Palomo et al. (2025)'!L15-'Palomo et al. (2025)'!L16 -> 134265 | C15: ='Palomo et al. (2025)'!Q15-'Palomo et al. (2025)'!Q16 -> 0.058412486 | D15: =('Palomo et al. (2025)'!L15*'Palomo et al. (2025)'!P15-'Palomo et al. (2025)'!L16*'Palomo et al. (2025)'!P16)/('Palomo et al. (2025)'!L15-'Palomo et al. (2025)'!L16) -> 631671.64 | E15: ='Palomo et al. (2025)'!O15 -> 352926.3 | F15: ='Palomo et al. (2025)'!C15 -> 0.22436049 | G15: ='Palomo et al. (2025)'!F15 + 'Palomo et al. (2025)'!H15 -> 0.04854842 | H15: 0.108 | I15: =WID!O21 -> 0.071989851 | J15: =WID!O52 -> 0.10064308 | K15: =WID!O$69 -> 0.010179449 | L15: =H15*G15 -> 0.0052432294 | M15: =D15*(1+I15)^6 -> 958595.58 | N15: =E15*(1+J15)^6 -> 627426.82 | O15: =(N15/H15)/1000000 -> 5.8095076 | P15: =M15/(M15-N15) -> 2.8945833 | Q15: =P15*(1-(N15/N16)^(P15-1)) -> 2.6814926 | R15: =MIN(1,MAX((M$22^(-Q15+1)-O16^(-Q15+1))/(O15^(-Q15+1)-O16^(-Q15+1)),0)) -> 0 | S15: =MIN(1,MAX((M$22^(-Q15)-O16^(-Q15))/(O15^(-Q15)-O16^(-Q15)),0))*B15*(1+K15)^6 -> 0 | T15: =F15 -> 0.22436049 | U15: =F15+MAX(0,M$23/H15-G15)*R15 -> 0.22436049 | V15: =(U15-T15)*M15*B15*(1+K15)^6/1000000 -> 0
A16: P99.99-P99.999 | B16: ='Palomo et al. (2025)'!L16-'Palomo et al. (2025)'!L17 -> 13430 | C16: ='Palomo et al. (2025)'!Q16-'Palomo et al. (2025)'!Q17 -> 0.030000273 | D16: =('Palomo et al. (2025)'!L16*'Palomo et al. (2025)'!P16-'Palomo et al. (2025)'!L17*'Palomo et al. (2025)'!P17)/('Palomo et al. (2025)'!L16-'Palomo et al. (2025)'!L17) -> 3243379 | E16: ='Palomo et al. (2025)'!O16 -> 1737934.2 | F16: ='Palomo et al. (2025)'!C16 -> 0.21458076 | G16: ='Palomo et al. (2025)'!F16 + 'Palomo et al. (2025)'!H16 -> 0.03369216 | H16: 0.083 | I16: =WID!O22 -> 0.054629983 | J16: =WID!O53 -> 0.061517047 | K16: =WID!O$69 -> 0.010179449 | L16: =H16*G16 -> 0.0027964493 | M16: =D16*(1+I16)^6 -> 4462707.1 | N16: =E16*(1+J16)^6 -> 2486538.4 | O16: =(N16/H16)/1000000 -> 29.958295 | P16: =M16/(M16-N16) -> 2.2582623 | Q16: =P16*(1-(N16/N17)^(P16-1)) -> 1.960451 | R16: =MIN(1,MAX((M$22^(-Q16+1)-O17^(-Q16+1))/(O16^(-Q16+1)-O17^(-Q16+1)),0)) -> 0 | S16: =MIN(1,MAX((M$22^(-Q16)-O17^(-Q16))/(O16^(-Q16)-O17^(-Q16)),0))*B16*(1+K16)^6 -> 0 | T16: =F16 -> 0.21458076 | U16: =F16+MAX(0,M$23/H16-G16)*R16 -> 0.21458076 | V16: =(U16-T16)*M16*B16*(1+K16)^6/1000000 -> 0
A17: P99.999-Billionaires | B17: ='Palomo et al. (2025)'!L17-'Palomo et al. (2025)'!L18 -> 1340 | C17: ='Palomo et al. (2025)'!Q17-'Palomo et al. (2025)'!Q18 -> 0.015756808 | D17: =('Palomo et al. (2025)'!L17*'Palomo et al. (2025)'!P17-'Palomo et al. (2025)'!L18*'Palomo et al. (2025)'!P18)/('Palomo et al. (2025)'!L17-'Palomo et al. (2025)'!L18) -> 17073083 | E17: ='Palomo et al. (2025)'!O17 -> 9018191.6 | F17: ='Palomo et al. (2025)'!C17 -> 0.19708729 | G17: ='Palomo et al. (2025)'!F17 + 'Palomo et al. (2025)'!H17 -> 0.0204606 | H17: 0.074 | I17: =WID!O23 -> 0.055413566 | J17: =WID!O54 -> 0.055083278 | K17: =WID!O$69 -> 0.010179449 | L17: =H17*G17 -> 0.0015140844 | M17: =D17*(1+I17)^6 -> 23596521 | N17: =E17*(1+J17)^6 -> 12440559 | O17: =(N17/H17)/1000000 -> 168.11566 | P17: =M17/(M17-N17) -> 2.1151489 | Q17: =P17*(1-(N17/N18)^(P17-1)) -> 1.7987791 | R17: =MIN(1,MAX((M$22^(-Q17+1)-O18^(-Q17+1))/(O17^(-Q17+1)-O18^(-Q17+1)),0)) -> 0 | S17: =MIN(1,MAX((M$22^(-Q17)-O18^(-Q17))/(O17^(-Q17)-O18^(-Q17)),0))*B17*(1+K17)^6 -> 0 | T17: =F17 -> 0.19708729 | U17: =F17+MAX(0,M$23/H17-G17)*R17 -> 0.19708729 | V17: =(U17-T17)*M17*B17*(1+K17)^6/1000000 -> 0
A18: Billionaires | B18: ='Palomo et al. (2025)'!L18 -> 152 | C18: ='Palomo et al. (2025)'!Q18 -> 0.012770815 | D18: ='Palomo et al. (2025)'!P18 -> 1.219898e+08 | E18: ='Palomo et al. (2025)'!O18 -> 49552064 | F18: ='Palomo et al. (2025)'!C17 -> 0.19708729 | G18: ='Palomo et al. (2025)'!F17 + 'Palomo et al. (2025)'!H17 -> 0.0204606 | H18: 0.08 | I18: =WID!O23 -> 0.055413566 | J18: =WID!O54 -> 0.055083278 | K18: =WID!O$69 -> 0.010179449 | L18: =H18*G18 -> 0.001636848 | M18: =D18*(1+I18)^6 -> 1.6860078e+08 | N18: =E18*(1+J18)^6 -> 68356873 | O18: =(N18/H18)/1000000 -> 854.46091 | P18: =M18/(M18-N18) -> 1.6819055 | R18: =IF(M$22<=O18, 1, (O18/M$22)^(P18-1)) -> 0.8982982 | S18: =IF(M$22<=O18, 1, (O18/M$22)^P18)*B18*(1+K18)^6 -> 123.97882 | T18: 0.26 | U18: =T18+MAX(0,M$23/H18-G18)*R18 -> 0.46619483 | V18: =(U18-T18)*M18*B18*(1+K18)^6/1000000 -> 5615.2889
S19: =SUM(S14:S18) -> 123.97882 | V19: =SUM(V14:V18) -> 5615.2889
B20: Source: Palomo et al. (2025). See formulas.
L21: Reform Parameters | T21: Summary of revenu estimates
L22: Threshold | M22: 1000 | T22: =V19 -> 5615.2889 | U22: 0.02 | V22: 0.03
L23: Rate | M23: 0.02 | T23: 100 | U23: 16658.255 | V23: 25773.375
T24: 1000 | U24: 5615.2889 | V24: 8673.2001

Sheet ITA
B2: Data (2015) | H2: Assumptions | L2: Simulations (2025)
A3: Group | B3: Number of units | C3: Income share | D3: Average income | E3: Income threshold | F3: Total tax rate | G3: Individual tax rate | H3: Income / Wealth Ratio | I3: Nominal growth rate (average) | J3: Nominal growth rate (threshold) | K3: Population growth | L3: Current wealth tax rate | M3: Average income | N3: Income threshold | O3: Wealth threshold | P3: Patero coefficient alpha | Q3: Corrected alpha | R3: Share of wealth exposed | S3: Number of units exposed | T3: Current tax rate | U3: Tax rate under reform | V3: Extra fiscal revenues
A4: P0-P10 | B4: ='Guzzardi et al. (2024)'!C23 -> 5069945 | C4: =('Guzzardi et al. (2024)'!F$21+'Guzzardi et al. (2024)'!F$22)*('Bach et al. (2025)'!F4-'Bach et al. (2025)'!F5)/('Bach et al. (2025)'!F$4-'Bach et al. (2025)'!F$9) -> 0.0014365452
A5: P10-P20 | B5: ='Guzzardi et al. (2024)'!C23 -> 5069945 | C5: =('Guzzardi et al. (2024)'!F$21+'Guzzardi et al. (2024)'!F$22)*('Bach et al. (2025)'!F5-'Bach et al. (2025)'!F6)/('Bach et al. (2025)'!F$4-'Bach et al. (2025)'!F$9) -> 0.020111633 | F5: ='Guzzardi et al. (2024)'!C4 -> 0.42 | T5: =F5 -> 0.42 | U5: =T5 -> 0.42
A6: P20-P30 | B6: ='Guzzardi et al. (2024)'!C23 -> 5069945 | C6: =('Guzzardi et al. (2024)'!F$21+'Guzzardi et al. (2024)'!F$22)*('Bach et al. (2025)'!F6-'Bach et al. (2025)'!F7)/('Bach et al. (2025)'!F$4-'Bach et al. (2025)'!F$9) -> 0.035530552 | F6: ='Guzzardi et al. (2024)'!C4 -> 0.42 | T6: =F6 -> 0.42 | U6: =T6 -> 0.42
A7: P30-P40 | B7: ='Guzzardi et al. (2024)'!C23 -> 5069945 | C7: =('Guzzardi et al. (2024)'!F$21+'Guzzardi et al. (2024)'!F$22)*('Bach et al. (2025)'!F7-'Bach et al. (2025)'!F8)/('Bach et al. (2025)'!F$4-'Bach et al. (2025)'!F$9) -> 0.046544066 | F7: ='Guzzardi et al. (2024)'!C4 -> 0.42 | T7: =F7 -> 0.42 | U7: =T7 -> 0.42
A8: P40-P50 | B8: ='Guzzardi et al. (2024)'!C23 -> 5069945 | C8: =('Guzzardi et al. (2024)'!F$21+'Guzzardi et al. (2024)'!F$22)*('Bach et al. (2025)'!F8-'Bach et al. (2025)'!F9)/('Bach et al. (2025)'!F$4-'Bach et al. (2025)'!F$9) -> 0.059377203 | F8: ='Guzzardi et al. (2024)'!C4 -> 0.42 | T8: =F8 -> 0.42 | U8: =T8 -> 0.42
A9: P50-P60 | B9: ='Guzzardi et al. (2024)'!C23 -> 5069945 | C9: ='Guzzardi et al. (2024)'!F23 -> 0.086 | F9: ='Guzzardi et al. (2024)'!C5 -> 0.43 | T9: =F9 -> 0.43 | U9: =T9 -> 0.43
A10: P60-P70 | B10: ='Guzzardi et al. (2024)'!C23 -> 5069945 | C10: ='Guzzardi et al. (2024)'!F24 -> 0.105 | F10: ='Guzzardi et al. (2024)'!C6 -> 0.45 | T10: =F10 -> 0.45 | U10: =T10 -> 0.45
A11: P70-P80 | B11: ='Guzzardi et al. (2024)'!C23 -> 5069945 | C11: ='Guzzardi et al. (2024)'!F25 -> 0.129 | F11: ='Guzzardi et al. (2024)'!C7 -> 0.47 | T11: =F11 -> 0.47 | U11: =T11 -> 0.47
A12: P80-P90 | B12: ='Guzzardi et al. (2024)'!C23 -> 5069945 | C12: ='Guzzardi et al. (2024)'!F26 -> 0.164 | F12: ='Guzzardi et al. (2024)'!C8 -> 0.49 | T12: =F12 -> 0.49 | U12: =T12 -> 0.49
A13: P90-P99 | B13: ='Guzzardi et al. (2024)'!C27-'Guzzardi et al. (2024)'!C29 -> 4562951 | C13: ='Guzzardi et al. (2024)'!F27 -'Guzzardi et al. (2024)'!F29 -> 0.252 | F13: ='Guzzardi et al. (2024)'!C9 -> 0.5 | T13: =F13 -> 0.5 | U13: =T13 -> 0.5
A14: P99-P99.9 | B14: ='Guzzardi et al. (2024)'!C29-'Guzzardi et al. (2024)'!C30 -> 456295 | C14: ='Guzzardi et al. (2024)'!F29 -'Guzzardi et al. (2024)'!F30 -> 0.073 | D14: =('Guzzardi et al. (2024)'!C29*'Guzzardi et al. (2024)'!E29-'Guzzardi et al. (2024)'!C30*'Guzzardi et al. (2024)'!E30)/('Guzzardi et al. (2024)'!C29-'Guzzardi et al. (2024)'!C30) -> 212338.53 | E14: ='Guzzardi et al. (2024)'!D29 -> 147733 | F14: ='Guzzardi et al. (2024)'!C10 -> 0.43 | G14: ='Guzzardi et al. (2024)'!D10 -> 0.25 | H14: 0.13 | I14: =WID!O25 -> 0.039529547 | J14: =WID!O56 -> 0.035268475 | K14: =WID!O$70 -> -8.4327136e-05 | L14: =H14*G14 -> 0.0325 | M14: =D14*(1+I14)^10 -> 312893.96 | N14: =E14*(1+J14)^10 -> 208933.18 | O14: =(N14/H14)/1000000 -> 1.6071783 | P14: =M14/(M14-N14) -> 3.0097307 | Q14: =P14*(1-(N14/N15)^(P14-1)) -> 2.6588892 | R14: =MIN(1,MAX((M$22^(-Q14+1)-O15^(-Q14+1))/(O14^(-Q14+1)-O15^(-Q14+1)),0)) -> 0 | S14: =MIN(1,MAX((M$22^(-Q14)-O15^(-Q14))/(O14^(-Q14)-O15^(-Q14)),0))*B14*(1+K14)^6 -> 0 | T14: =F14 -> 0.43 | U14: =F14+MAX(0,M$23/H14-G14)*R14 -> 0.43 | V14: =(U14-T14)*M14*B14*(1+K14)^10/1000000 -> 0
A15: P99.9-P99.99 | B15: ='Guzzardi et al. (2024)'!C30*0.9 -> 45629.1 | C15: =(B15*D15)/(D$14*B$14/C$14) -> 0.028490774 | D15: =('Guzzardi et al. (2024)'!E30*SUM(B15:B18)-B16*D16-B17*D17-B18*D18)/B15 -> 828731.79 | E15: =D15/'Guzzardi et al. (2024)'!G$30 -> 351780.3 | F15: ='Guzzardi et al. (2024)'!C11 -> 0.36 | G15: ='Guzzardi et al. (2024)'!D11 -> 0.15 | H15: 0.108 | I15: =WID!O26 -> 0.060947379 | J15: =WID!O57 -> 0.056375828 | K15: =WID!O$70 -> -8.4327136e-05 | L15: =H15*G15 -> 0.0162 | M15: =D15*(1+I15)^10 -> 1497450.4 | N15: =E15*(1+J15)^10 -> 608773.95 | O15: =(N15/H15)/1000000 -> 5.6367959 | P15: =M15/(M15-N15) -> 1.6850344 | Q15: =P15*(1-(N15/N16)^(P15-1)) -> 1.0456869 | R15: =MIN(1,MAX((M$22^(-Q15+1)-O16^(-Q15+1))/(O15^(-Q15+1)-O16^(-Q15+1)),0)) -> 0 | S15: =MIN(1,MAX((M$22^(-Q15)-O16^(-Q15))/(O15^(-Q15)-O16^(-Q15)),0))*B15*(1+K15)^6 -> 0 | T15: =F15 -> 0.36 | U15: =F15+MAX(0,M$23/H15-G15)*R15 -> 0.36 | V15: =(U15-T15)*M15*B15*(1+K15)^10/1000000 -> 0
A16: P99.99-P99.999 | B16: ='Guzzardi et al. (2024)'!C30*0.09 -> 4562.91 | C16: =(B16*D16)/(D$14*B$14/C$14) -> 0.010738936 | D16: =(('Guzzardi et al. (2024)'!E30*(SUM(B15:B18)/SUM(B16:B18))^(('Guzzardi et al. (2024)'!G30-1)/'Guzzardi et al. (2024)'!G30))*SUM(B16:B18)-B17*D17-B18*D18)/B16 -> 3123712.2 | E16: =D16/'Guzzardi et al. (2024)'!G$30 -> 1325954.2 | F16: ='Guzzardi et al. (2024)'!C11 - (1/3)*('Guzzardi et al. (2024)'!C11 - 'Guzzardi et al. (2024)'!C12) -> 0.3 | G16: =F16*('Guzzardi et al. (2024)'!D$11/'Guzzardi et al. (2024)'!C$11) -> 0.125 | H16: 0.083 | I16: =WID!O27 -> 0.068384531 | J16: =WID!O58 -> 0.065689781 | K16: =WID!O$70 -> -8.4327136e-05 | L16: =H16*G16 -> 0.010375 | M16: =D16*(1+I16)^10 -> 6052669 | N16: =E16*(1+J16)^10 -> 2505166.2 | O16: =(N16/H16)/1000000 -> 30.182725 | P16: =M16/(M16-N16) -> 1.7061773 | Q16: =P16*(1-(N16/N17)^(P16-1)) -> 1.099074 | R16: =MIN(1,MAX((M$22^(-Q16+1)-O17^(-Q16+1))/(O16^(-Q16+1)-O17^(-Q16+1)),0)) -> 0 | S16: =MIN(1,MAX((M$22^(-Q16)-O17^(-Q16))/(O16^(-Q16)-O17^(-Q16)),0))*B16*(1+K16)^6 -> 0 | T16: =F16 -> 0.3 | U16: =F16+MAX(0,M$23/H16-G16)*R16 -> 0.3 | V16: =(U16-T16)*M16*B16*(1+K16)^10/1000000 -> 0
A17: P99.999-Billionaires | B17: ='Guzzardi et al. (2024)'!C30*0.009 -> 456.291 | C17: =(B17*D17)/(D$14*B$14/C$14) -> 0.0041122132 | D17: =(('Guzzardi et al. (2024)'!E30*(SUM(B15:B18)/SUM(B17:B18))^(('Guzzardi et al. (2024)'!G30-1)/'Guzzardi et al. (2024)'!G30))*(B17+B18)-B18*D18)/B17 -> 11961492 | E17: =D17/'Guzzardi et al. (2024)'!G$30 -> 5077417.6 | F17: ='Guzzardi et al. (2024)'!C11 - (2/3)*('Guzzardi et al. (2024)'!C11 - 'Guzzardi et al. (2024)'!C12) -> 0.24 | G17: =F17*('Guzzardi et al. (2024)'!D$11/'Guzzardi et al. (2024)'!C$11) -> 0.1 | H17: 0.074 | I17: =WID!O28 -> 0.081211274 | J17: =WID!O59 -> 0.078617252 | K17: =WID!O$70 -> -8.4327136e-05 | L17: =H17*G17 -> 0.0074 | M17: =D17*(1+I17)^10 -> 26115060 | N17: =E17*(1+J17)^10 -> 10822224 | O17: =(N17/H17)/1000000 -> 146.24627 | P17: =M17/(M17-N17) -> 1.7076662 | Q17: =P17*(1-(N17/N18)^(P17-1)) -> 1.2067747 | R17: =MIN(1,MAX((M$22^(-Q17+1)-O18^(-Q17+1))/(O17^(-Q17+1)-O18^(-Q17+1)),0)) -> 0.14725955 | S17: =MIN(1,MAX((M$22^(-Q17)-O18^(-Q17))/(O17^(-Q17)-O18^(-Q17)),0))*B17*(1+K17)^6 -> 19.136171 | T17: =F17 -> 0.24 | U17: =F17+MAX(0,M$23/H17-G17)*R17 -> 0.26507392 | V17: =(U17-T17)*M17*B17*(1+K17)^10/1000000 -> 298.53069
A18: Billionaires | B18: ='Guzzardi et al. (2024)'!C30*0.0009 -> 45.6291 | C18: =(B18*D18)/(D$14*B$14/C$14) -> 0.0023268806 | D18: ='Guzzardi et al. (2024)'!E30*(SUM(B15:B18)/B18)^(('Guzzardi et al. (2024)'!G30-1)/'Guzzardi et al. (2024)'!G30) -> 67683662 | E18: =D18/'Guzzardi et al. (2024)'!G$30 -> 28730379 | F18: ='Guzzardi et al. (2024)'!C12 -> 0.18 | G18: =F18*('Guzzardi et al. (2024)'!D$11/'Guzzardi et al. (2024)'!C$11) -> 0.075 | H18: 0.04 | I18: =WID!O28 -> 0.081211274 | J18: =WID!O59 -> 0.078617252 | K18: =WID!O$70 -> -8.4327136e-05 | L18: =H18*G18 -> 0.003 | M18: =D18*(1+I18)^10 -> 1.477711e+08 | N18: =E18*(1+J18)^10 -> 61237152 | O18: =(N18/H18)/1000000 -> 1530.9288 | P18: =M18/(M18-N18) -> 1.7076662 | R18: =IF(M$22<=O18, 1, (O18/M$22)^(P18-1)) -> 1 | S18: =IF(M$22<=O18, 1, (O18/M$22)^P18)*B18*(1+K18)^6 -> 45.606018 | T18: 0.26 | U18: =T18+MAX(0,M$23/H18-G18)*R18 -> 0.685 | V18: =(U18-T18)*M18*B18*(1+K18)^10/1000000 -> 2863.2158
S19: =SUM(S14:S18) -> 64.742189 | V19: =SUM(V14:V18) -> 3161.7465
B20: Sources: Guzzardi et al. (2024). See formulas.
B21: Notes: The tax rate estimate for billionaires comes from one single observation (Silvio Berlusconi in 2020) | L21: Reform Parameters | T21: Summary of revenu estimates
B22: Tax rate estimates for P99.99-P99.999 and for P99.999-Billionnaires are linearly interpolated. | L22: Threshold | M22: 1000 | T22: =V19 -> 3161.7465 | U22: 0.02 | V22: 0.03
B23: Tax rates for groups P10-P20 and P20-P30 are taken equal to the tax rate estimate for P25-P50. | L23: Rate | M23: 0.02 | T23: 100 | U23: 5616.1741 | V23: 9663.332
B24: Individual tax rates for the top three income groups are calculated by extrapolating the individual tax rate to total tax rate ratio observed for P99.99-P100. | T24: 1000 | U24: 3161.7465 | V24: 5082.9203
B25: For dissagregating income values within the top 0.1%, we assume a Pareto distribution.
B26: For dissagregating income shares within the bottom 50%, we apply the incomes shares observed in France (Bach et al., 2025).

Sheet Summary
B2: Revenue estimates (above) for different wealth tax scenarios, and comparison with previous estimates (below)
C3: 2% rate | E3: 3% rate | H3: Comments
C4: Centi-millionaires | D4: Billionaires | E4: Centi-millionaires | F4: Billionaires
B5: United States | C5: =USA!U23/1000 -> 115.51745 | D5: =USA!U24/1000 -> 93.787937 | E5: =USA!V23/1000 -> 303.13347 | F5: =USA!V24/1000 -> 183.34885 | H5: Non-billionaires already face effective personal wealth tax rate larger than 2%, so they are only taxed in the 3% scenario and generate few revenues.
C6: 145.6 | D6: 94 | E6: 288.3 | F6: 161.1
B7: France | C7: =FRA!U23/1000 -> 16.983738 | D7: =FRA!U24/1000 -> 13.070687 | E7: =FRA!V23/1000 -> 28.076523 | F7: =FRA!V24/1000 -> 20.367647 | H7: Billionaires estimates coincide very well.
C8: 19.4 | D8: 12.5 | E8: 34.8 | F8: 19.5
B9: Netherlands | C9: =NDL!U23/1000 -> 4.2723834 | D9: =NDL!U24/1000 -> 0.91587086 | E9: =NDL!V23/1000 -> 6.7203525 | F9: =NDL!V24/1000 -> 1.3875362 | H9: Current wealth tax rate (0,03% for the top income group) lower than the 0,2% hypothesis used in previous estimates. Significant centimilionnaires estimate discrepancy because current simulation capture numerous centimillionaires with low effective tax rates.
C10: 1 | D10: 0.6 | E10: 1.7 | F10: 1
B11: Italy | C11: =ITA!U23/1000 -> 5.6161741 | D11: =ITA!U24/1000 -> 3.1617465 | E11: =ITA!V23/1000 -> 9.663332 | F11: =ITA!V24/1000 -> 5.0829203 | H11: High billionaire wealth in Forbes compared to income concentration in income data. Reconcilied with higher income to wealth ratio assumption than Forbes calibration.
C12: 8.3 | D12: 5.4 | E12: 15 | F12: 8.4
B13: Brazil | C13: =BRA!U23/1000 -> 16.658255 | D13: =BRA!U24/1000 -> 5.6152889 | E13: =BRA!V23/1000 -> 25.773375 | F13: =BRA!V24/1000 -> 8.6732001 | H13: Low billionaire wealth in Forbes compared to income concentration in income data. Reconcilied with lower income to wealth ratio assumption than Forbes calibration.
C14: 5.5 | D14: 3.5 | E14: 9.8 | F14: 5.5
B16: Notes: Amounts are €B for France, Netherlands, Italy, and $B for US and Brazil.
B17: Previous estimates use Real-Time Billionaire data from Forbes (retrieved on March 3, 2025).
B18: They assume a current effective tax rate of billionaires equal to 0.2% (0,6% for the US) of their wealth,
B19: and use a simple multiplicative factors of 1.55 (for 2% rate) and 1.79 (for 3% rate) when moving from revenue for billionaires to revenue for centi-millionaires.
B20: Current estimates start from country specific estimates of income distribution and tax progressivity for year 2025.
B21: They apply decreasing income to wealth ratio at the top of the distribution.
B23: The 1,55 multiplication rule from previous estimates is contradicted by simulations based on country-specific income distributions. This explains the estimation discrepancies for centi-millionaires scenarios.
B25: When the chosen income to wealth ratio is closed to the Forbes calibrated one, billionnaires estimates are very close to previous estimates.
B26: When the chosen income to wealth ratio is larger (smaller) than the Forbes calibrated one, billionnaires estimates are lower (higher) than previous estimates.
B27: There is therefore a trade-off between the confidence we can place in the Forbes data (timely and based on observed wealth, but uncertain coverage and limited granularity)
B28: and the information conveyed by income distributions (no direct wealth data, but broad coverage, well-defined granularity, and direct connection to tax rate estimates).

Sheet Data Sources
A2: LIST OF DATA SOURCES
A4: Laurent Bach, Antoine Bozio, Arthur Guillouzouic, Clément Malgouyres (2025). Do Billionaires Pay Taxes?
A5: Insee (2024). Comptes nationaux distribués 2022, base 2020. CND.101 - Comptes nationaux distribués selon les vingtièmes de niveau de vie usuel
A6: Thomas Piketty, Emmanuel Saez, Gabriel Zucman (2018). Distributional National Accounts: Methods and Estimates for the United States.
A7: Akcan S. Balkir, Emmanuel Saez, Danny Yagan, Gabriel Zucman (2025). How Much Tax Do US Billionaires Pay? Evidence From Administrative Data.
A8: Theo Palomo, Davi Bhering, Thiago Scot, Pierre Bachas, Luciana Barcarolo, Celso Campos, Javier Feinmann, Leonardo Moreira, Gabriel Zucman (2025). Tax Progressivity and Inequality in Brazil: Evidence from Integrated Administrative Data.
A9: Arjan Bruil, Céline van Essen, Wouter Leenders, Arjan Lejour, Jan Möhlmann, Simon Rabaté (2025). Inequality and Redistribution in the Netherlands
A10: Demetrio Guzzardi, Elisa Palagi, Andrea Roventini, Alessandro Santoro (2024). Reconstructing Income Inequality in Italy: New Evidence and Tax System Implications from Distributional National Accounts.

Sheet Income to wealth ratios
B2: Billionaires income to wealth ratio estimations from income distributions and wealth recorded in Billionaire Lists | P2: Observed ratios in US joint distribution of income and wealth
C3: Billionaires List | H3: Top income group | P3: Gperc | R3: 2018 | W3: 2021 | AB3: 2024
B4: Country | C4: Number of units (N) | D4: Total wealth ($B) | E4: Total wealth (€B) | F4: Average wealth ($B) | G4: Average wealth (€B) | H4: Number of units | I4: Average income | J4: Pareto coefficient b | K4: Average income of N top units | L4: Estimated ratio | M4: Household multiplier | R4: N | S4: Average income | T4: Average wealth | U4: Income to wealth ratio | W4: N | X4: Average income | Y4: Average wealth | Z4: Income to wealth ratio | AB4: N | AC4: Average income | AD4: Average wealth | AE4: Income to wealth ratio
B5: France | C5: 147 | D5: 730 | E5: 695.2 | F5: =D5/$C5 -> 4.9659864 | G5: =E5/$C5 -> 4.7292517 | H5: =FRA!B18*(1+FRA!K18)^9 -> 78.76155 | I5: =FRA!M18 -> 5.4840237e+08 | J5: =FRA!D18/FRA!E18 -> 3.530858 | K5: =I5*(C5/H5)^((1-J5)/J5) -> 3.5062994e+08 | L5: =K5/(E5*1000000000/C5) -> 0.074140681 | P5: 99 | Q5: P99-P99.9 | R5: 162004 | S5: 807940 | T5: 4988455 | U5: 0.16196197 | V5: =SUMPRODUCT(S5:S13,U5:U13)/SUM(S5:S13) -> 0.14215643 | W5: 166548 | X5: 868228 | Y5: 6239397 | Z5: 0.13915256 | AA5: =SUMPRODUCT(X5:X13,Z5:Z13)/SUM(X5:X13) -> 0.12033611 | AB5: 171380 | AC5: 1051200 | AD5: 7210150 | AE5: 0.14579447 | AF5: =SUMPRODUCT(AC5:AC13,AE5:AE13)/SUM(AC5:AC13) -> 0.12953578
B6: US | C6: 936 | D6: 7927.6094 | E6: =D6*0.95 -> 7531.2289 | F6: =D6/$C6 -> 8.4696681 | G6: =E6/$C6 -> 8.0461847 | H6: =USA!B18*(1+USA!K18)^9 -> 446.32052 | I6: =USA!M18 -> 4.3937459e+08 | J6: =USA!D18/USA!E18 -> 3.44 | K6: =I6*(C6/H6)^((1-J6)/J6) -> 2.5983804e+08 | L6: =K6/(D6*1000000000/C6) -> 0.030678657 | P6: 99.099998 | R6: 161841 | S6: 865779 | T6: 5737162 | U6: 0.15090719 | W6: 166738 | X6: 931737 | Y6: 7142127 | Z6: 0.13045652 | AB6: 171269 | AC6: 1125298 | AD6: 8114548 | AE6: 0.13867661
B7: Netherlands | C7: 13 | D7: 49.210542 | E7: =D7*0.95 -> 46.750015 | F7: =D7/$C7 -> 3.7854263 | G7: =E7/$C7 -> 3.596155 | H7: =NDL!B18/M7*(1+NDL!K18)^9 -> 8.5287743 | I7: =M7*NDL!M18 -> 2.7670321e+08 | J7: =NDL!D18/NDL!E18 -> 1.2428808 | K7: =I7*(C7/H7)^((1-J7)/J7) -> 2.548248e+08 | L7: =K7/(E7*1000000000/C7) -> 0.070860349 | M7: 1.8 | P7: 99.199997 | R7: 162014 | S7: 938270 | T7: 5993560 | U7: 0.15654635 | W7: 166630 | X7: 1008746 | Y7: 7993723 | Z7: 0.12619226 | AB7: 171482 | AC7: 1202668 | AD7: 8723809 | AE7: 0.13786042
B8: Brazil | C8: 66 | D8: 252.69514 | E8: =D8*0.95 -> 240.06038 | F8: =D8/$C8 -> 3.8287142 | G8: =E8/$C8 -> 3.6372785 | H8: =BRA!B18/M8*(1+BRA!K18)^9 -> 92.503431 | I8: =M8*BRA!M18 -> 3.034814e+08 | J8: =BRA!D18/BRA!E18 -> 2.4618511 | K8: =I8*(C8/H8)^((1-J8)/J8) -> 3.7084433e+08 | L8: =K8/(D8*1000000000/C8) -> 0.096858713 | M8: 1.8 | P8: 99.300003 | R8: 161832 | S8: 1022692 | T8: 6954512 | U8: 0.14705446 | W8: 166586 | X8: 1097815 | Y8: 8829116 | Z8: 0.12434031 | AB8: 171444 | AC8: 1292233 | AD8: 8816158 | AE8: 0.14657553
B9: Italy | C9: 79 | D9: 360.74274 | E9: =D9*0.95 -> 342.7056 | F9: =D9/$C9 -> 4.5663638 | G9: =E9/$C9 -> 4.3380456 | H9: =ITA!B18/M9*(1+ITA!K18)^9 -> 25.330268 | I9: =M9*ITA!M18 -> 2.6598798e+08 | J9: =ITA!D18/ITA!E18 -> 2.3558221 | K9: =I9*(C9/H9)^((1-J9)/J9) -> 1.3821735e+08 | L9: =K9/(E9*1000000000/C9) -> 0.031861664 | M9: 1.8 | P9: 99.400002 | R9: 161990 | S9: 1134165 | T9: 8127751 | U9: 0.1395423 | W9: 166672 | X9: 1215719 | Y9: 9750950 | Z9: 0.12467698 | AB9: 171359 | AC9: 1426810 | AD9: 10138369 | AE9: 0.14073369
P10: 99.5 | R10: 161927 | S10: 1283456 | T10: 8818007 | U10: 0.14554945 | W10: 166651 | X10: 1389801 | Y10: 11548602 | Z10: 0.12034366 | AB10: 169929 | AC10: 1625806 | AD10: 13188411 | AE10: 0.12327535
B11: Sources: Real-Time Billionaire data from Forbes, retrieved on December 1, 2025. Billionnaire data for France comes from the 2024 ranking by Challenges. | P11: 99.599998 | R11: 161798 | S11: 1494369 | T11: 10670818 | U11: 0.14004259 | W11: 166618 | X11: 1645271 | Y11: 13915416 | Z11: 0.11823369 | AB11: 172832 | AC11: 1895211 | AD11: 15644008 | AE11: 0.12114613
B12: Income data comes from the country specific studies (see formulas). | P12: 99.699997 | R12: 162024 | S12: 1855783 | T12: 14152106 | U12: 0.13113123 | W12: 166657 | X12: 2087103 | Y12: 18331928 | Z12: 0.11385071 | AB12: 171423 | AC12: 2391677 | AD12: 19260828 | AE12: 0.12417311
P13: 99.800003 | R13: 161951 | S13: 2631270 | T13: 19547508 | U13: 0.13460897 | W13: 166646 | X13: 3036983 | Y13: 27040090 | Z13: 0.11231408 | AB13: 171381 | AC13: 3473833 | AD13: 29183538 | AE13: 0.11903399
B14: Notes: Since the number of units differ between Forbes lists and the top income group from the studies, we cannot immediately divide average income by average income from both sides. | P14: 99.900002 | Q14: P99.9-P99.99 | R14: 16182 | S14: 3481986 | T14: 26789418 | U14: 0.12997617 | V14: =SUMPRODUCT(S14:S22,U14:U22)/SUM(S14:S22) -> 0.12515864 | W14: 16667 | X14: 4034694 | Y14: 37426896 | Z14: 0.107802 | AA14: =SUMPRODUCT(X14:X22,Z14:Z22)/SUM(X14:X22) -> 0.10607795 | AB14: 17149 | AC14: 4661727 | AD14: 40464820 | AE14: 0.11520444 | AF14: =SUMPRODUCT(AC14:AC22,AE14:AE22)/SUM(AC14:AC22) -> 0.10808657
B15: We therefore use a calibrated Pareto coefficient in order to correct the average income of the top group and to make it coincide with the average income of the top N units, | P15: 99.910004 | R15: 16183 | S15: 3748265 | T15: 30270880 | U15: 0.12382412 | W15: 16653 | X15: 4350199 | Y15: 40341984 | Z15: 0.10783304 | AB15: 17132 | AC15: 5050220 | AD15: 42112216 | AE15: 0.11992292
B16: where N is the number of units in the Forbes list. | P16: 99.919998 | R16: 16202 | S16: 4066345 | T16: 32604216 | U16: 0.12471838 | W16: 16666 | X16: 4738359 | Y16: 42557872 | Z16: 0.11133919 | AB16: 17145 | AC16: 5541752 | AD16: 46789212 | AE16: 0.11844081
B17: We assume that units in the Forbes list are equivalent to households, in the sense of either couples or single individuals. This is already the unit of observation used for France and the US. | P17: 99.93 | R17: 16192 | S17: 4470736 | T17: 35218080 | U17: 0.12694435 | W17: 16662 | X17: 5245137 | Y17: 49611700 | Z17: 0.10572379 | AB17: 17132 | AC17: 6115450 | AD17: 53461336 | AE17: 0.11439014
B18: We apply a household multiplier to Netherlands, Brazil and Italy income data, so as to make the unit of observation somehow coincide with the Forbes list. | P18: 99.940002 | R18: 16187 | S18: 5000077 | T18: 39197084 | U18: 0.12756248 | W18: 16665 | X18: 5896624 | Y18: 54337444 | Z18: 0.10851862 | AB18: 17138 | AC18: 6793617 | AD18: 59339600 | AE18: 0.11448707
P19: 99.949997 | R19: 16186 | S19: 5708433 | T19: 41818264 | U19: 0.13650574 | W19: 16661 | X19: 6732156 | Y19: 60172976 | Z19: 0.11188006 | AB19: 17145 | AC19: 7744908 | AD19: 68521032 | AE19: 0.11302964
B20: This method closely reproduces the reference estimate of 4,9% for the US. | P20: 99.959999 | R20: 16201 | S20: 6774401 | T20: 52490428 | U20: 0.12905975 | W20: 16678 | X20: 7975584 | Y20: 70838056 | Z20: 0.11258897 | AB20: 17143 | AC20: 9249725 | AD20: 85266784 | AE20: 0.10847981
B21: Based on this table and on the initial benchmark of 4,9% (US estimate), we retain the following assumptions for the simulations : | P21: 99.970001 | R21: 16197 | S21: 8474492 | T21: 68255272 | U21: 0.12415879 | W21: 16661 | X21: 10168683 | Y21: 97280936 | Z21: 0.10452904 | AB21: 17129 | AC21: 11750994 | AD21: 109137944 | AE21: 0.10767102
P22: 99.980003 | R22: 16190 | S22: 12002910 | T22: 103680632 | U22: 0.1157681 | W22: 16655 | X22: 14978737 | Y22: 153502720 | Z22: 0.097579621 | AB22: 17138 | AC22: 17893180 | AD22: 192337488 | AE22: 0.093030125
B23: France | C23: 0.07 | P23: 99.989998 | Q23: P99.99-P99.999 | R23: 1605 | S23: 15680434 | T23: 138991760 | U23: 0.11281557 | V23: =SUMPRODUCT(S23:S31,U23:U31)/SUM(S23:S31) -> 0.10343253 | W23: 1661 | X23: 20616632 | Y23: 213389152 | Z23: 0.09661518 | AA23: =SUMPRODUCT(X23:X31,Z23:Z31)/SUM(X23:X31) -> 0.086468116 | AB23: 1708 | AC23: 24521532 | AD23: 288376672 | AE23: 0.085032992 | AF23: =SUMPRODUCT(AC23:AC31,AE23:AE31)/SUM(AC23:AC31) -> 0.082793159
B24: US | C24: 0.049 | P24: 99.990997 | R24: 1624 | S24: 16784578 | T24: 140861664 | U24: 0.11915646 | W24: 1663 | X24: 22252180 | Y24: 224822480 | Z24: 0.098976672 | AB24: 1723 | AC24: 26594596 | AD24: 305491776 | AE24: 0.087055027
B25: Netherlands | C25: 0.07 | P25: 99.991997 | R25: 1624 | S25: 18233358 | T25: 160058704 | U25: 0.1139167 | W25: 1675 | X25: 24054592 | Y25: 257008272 | Z25: 0.093594618 | AB25: 1707 | AC25: 29064876 | AD25: 336537440 | AE25: 0.086364463
B26: Brazil | C26: 0.08 | P26: 99.992996 | R26: 1621 | S26: 19935524 | T26: 195389392 | U26: 0.10202972 | W26: 1679 | X26: 26248784 | Y26: 302508000 | Z26: 0.086770542 | AB26: 1732 | AC26: 31744942 | AD26: 352722304 | AE26: 0.089999817
B27: Italy | C27: 0.04 | P27: 99.994003 | R27: 1615 | S27: 22336292 | T27: 227705696 | U27: 0.098092809 | W27: 1653 | X27: 29331146 | Y27: 343963776 | Z27: 0.085273936 | AB27: 1701 | AC27: 35470352 | AD27: 403969120 | AE27: 0.087804615
P28: 99.995003 | R28: 1614 | S28: 25600892 | T28: 247328480 | U28: 0.10350968 | W28: 1673 | X28: 33550620 | Y28: 400685344 | Z28: 0.083733082 | AB28: 1714 | AC28: 41257112 | AD28: 475012864 | AE28: 0.086854726
P29: 99.996002 | R29: 1625 | S29: 30248796 | T29: 291615648 | U29: 0.1037283 | W29: 1678 | X29: 39623324 | Y29: 448552896 | Z29: 0.088335901 | AB29: 1716 | AC29: 50087968 | AD29: 635568384 | AE29: 0.078808151
P30: 99.997002 | R30: 1618 | S30: 38651340 | T30: 388485120 | U30: 0.09949246 | W30: 1656 | X30: 50894552 | Y30: 611225536 | Z30: 0.0832664 | AB30: 1710 | AC30: 65383580 | AD30: 809232256 | AE30: 0.080797054
P31: 99.998001 | R31: 1435 | S31: 57079656 | T31: 582812416 | U31: 0.097938299 | W31: 1491 | X31: 75082264 | Y31: 933173504 | Z31: 0.080459058 | AB31: 1709 | AC31: 95165672 | AD31: 1230000000 | AE31: 0.077370465
P32: 99.999001 | Q32: P99.999-P100 | R32: 1412 | S32: 91344960 | T32: 987265088 | U32: 0.092523232 | V32: =SUMPRODUCT(R32:R33,S32:S33,U32:U33)/SUMPRODUCT(R32:R33,S32:S33) -> 0.0826826 | W32: 1450 | X32: 120061824 | Y32: 1570000000 | Z32: 0.076472498 | AA32: =SUMPRODUCT(W32:W33,X32:X33,Z32:Z33)/SUMPRODUCT(W32:W33,X32:X33) -> 0.06532876 | AB32: 1325 | AC32: 170138960 | AD32: 2310000128 | AE32: 0.073653229 | AF32: =SUMPRODUCT(AB32:AB33,AC32:AC33,AE32:AE33)/SUMPRODUCT(AB32:AB33,AC32:AC33) -> 0.072269995
P33: 400 | R33: 400 | S33: 556576384 | T33: 7230000128 | U33: 0.076981515 | W33: 400 | X33: 654475776 | Y33: 11299999744 | Z33: 0.057918213 | AB33: 411 | AC33: 950575488 | AD33: 13299999744 | AE33: 0.07147184
Q35: Sources: Joint distribution of income and wealth is from US DINA files (PSZ 2018, https://gabriel-zucman.eu/usdina/)
Q36: Notes: Unit of observation is taxunit. Income variable is 'peinc'.

Sheet Insee (2026)
A1: Nature des revenus et transferts | B1: Ensemble | C1: V1 | D1: V2 | E1: V3 | F1: V4 | G1: V5 | H1: V6 | I1: V7 | J1: V8 | K1: V9 | L1: V10 | M1: V11 | N1: V12 | O1: V13 | P1: V14 | Q1: V15 | R1: V16 | S1: V17 | T1: V18 | U1: V19 | V1: V20
A2: Revenus primaires des ménages (=A) : | B2: 1901.5 | C2: 10.2 | D2: 16.3 | E2: 24.8 | F2: 31.7 | G2: 39.3 | H2: 45.4 | I2: 53 | J2: 61.1 | K2: 65.9 | L2: 71.3 | M2: 77.4 | N2: 82.3 | O2: 94.3 | P2: 99.1 | Q2: 112.3 | R2: 124.2 | S2: 138.4 | T2: 161.2 | U2: 200.7 | V2: 392.6
A3: Revenus salariaux nets | B3: 937.9 | C3: 3.4 | D3: 7.1 | E3: 12.5 | F3: 16.6 | G3: 20.7 | H3: 24 | I3: 28.8 | J3: 33.7 | K3: 36 | L3: 39.2 | M3: 42.9 | N3: 44.2 | O3: 50.9 | P3: 53.1 | Q3: 59.2 | R3: 64.9 | S3: 70.1 | T3: 81 | U3: 96.3 | V3: 153.3
A4: Cotisations sociales (salariés et employeurs) | B4: 542.9 | C4: 2.2 | D4: 3.8 | E4: 6.4 | F4: 8.5 | G4: 10.5 | H4: 11.8 | I4: 14.2 | J4: 16.8 | K4: 18.7 | L4: 20.5 | M4: 22 | N4: 23.3 | O4: 28 | P4: 29.2 | Q4: 33.4 | R4: 37.7 | S4: 41.6 | T4: 50.4 | U4: 61.7 | V4: 102.4
A5: Revenus mixtes des indépendants | B5: 119.9 | C5: 0.3 | D5: 1 | E5: 1.5 | F5: 1.6 | G5: 1.8 | H5: 2 | I5: 2.1 | J5: 2.4 | K5: 2.3 | L5: 2.4 | M5: 2.4 | N5: 3.1 | O5: 3.4 | P5: 3.1 | Q5: 4.8 | R5: 5.4 | S5: 7.7 | T5: 7.2 | U5: 12.1 | V5: 53.2
A6: Revenus nets de la propriété (intérêts, dividendes, etc.) | B6: 133.9 | C6: 1 | D6: 0.9 | E6: 1 | F6: 1.1 | G6: 1.3 | H6: 1.7 | I6: 1.9 | J6: 1.9 | K6: 2.2 | L6: 2.1 | M6: 2.6 | N6: 3.3 | O6: 3.4 | P6: 4.1 | Q6: 4.9 | R6: 5.6 | S6: 7.4 | T6: 9.6 | U6: 15.6 | V6: 62.3
A7: Loyers réels et imputés aux propriétaires | B7: 166.9 | C7: 3.3 | D7: 3.6 | E7: 3.4 | F7: 3.9 | G7: 5 | H7: 5.8 | I7: 6.1 | J7: 6.2 | K7: 6.8 | L7: 7.1 | M7: 7.6 | N7: 8.4 | O7: 8.7 | P7: 9.6 | Q7: 9.9 | R7: 10.6 | S7: 11.6 | T7: 12.9 | U7: 14.9 | V7: 21.4
A8: Profits des entreprises non distribués aux ménages (=B) | B8: 123.1 | C8: 0.7 | D8: 0.4 | E8: 0.4 | F8: 0.5 | G8: 0.5 | H8: 0.8 | I8: 0.5 | J8: 0.6 | K8: 0.7 | L8: 0.6 | M8: 1 | N8: 1.3 | O8: 1.2 | P8: 1.2 | Q8: 1.9 | R8: 2.7 | S8: 3.1 | T8: 4.1 | U8: 10.5 | V8: 90.4
A9: Revenus primaires des APU (aux prix de base) et des ISBLSM (=C) | B9: 58.5 | C9: -0.4 | D9: -0.2 | E9: 0.1 | F9: 0.3 | G9: 0.7 | H9: 0.9 | I9: 1.1 | J9: 1.5 | K9: 1.7 | L9: 1.9 | M9: 2.1 | N9: 2.3 | O9: 2.8 | P9: 2.9 | Q9: 3.5 | R9: 3.9 | S9: 4.5 | T9: 5.2 | U9: 6.9 | V9: 16.8
A10: Tirés des impôts nets des subventions sur la production | B10: 89.9 | C10: 0.5 | D10: 0.7 | E10: 1.1 | F10: 1.4 | G10: 1.8 | H10: 2 | I10: 2.4 | J10: 2.7 | K10: 3 | L10: 3.2 | M10: 3.5 | N10: 3.7 | O10: 4.2 | P10: 4.5 | Q10: 5.1 | R10: 5.6 | S10: 6.3 | T10: 7.3 | U10: 9.4 | V10: 21.4
A11: Revenus de la propriété (reçus - versés) et ENE des APU et des ISBLSM | B11: -31.3 | C11: -0.9 | D11: -0.9 | E11: -1 | F11: -1.1 | G11: -1.1 | H11: -1.2 | I11: -1.2 | J11: -1.3 | K11: -1.3 | L11: -1.3 | M11: -1.3 | N11: -1.4 | O11: -1.5 | P11: -1.5 | Q11: -1.6 | R11: -1.7 | S11: -1.8 | T11: -2.1 | U11: -2.5 | V11: -4.6
A12: Revenu primaire élargi (D=A+B+C) | B12: 2083.1 | C12: 10.4 | D12: 16.6 | E12: 25.3 | F12: 32.4 | G12: 40.5 | H12: 47 | I12: 54.7 | J12: 63.1 | K12: 68.3 | L12: 73.7 | M12: 80.6 | N12: 85.9 | O12: 98.3 | P12: 103.2 | Q12: 117.7 | R12: 130.8 | S12: 146 | T12: 170.5 | U12: 218.2 | V12: 499.9
A13: Revenus des APU tirés des impôts nets sur les produits (E) | B13: 286.7 | C13: 1.5 | D13: 2.4 | E13: 3.6 | F13: 4.6 | G13: 5.6 | H13: 6.5 | I13: 7.6 | J13: 8.7 | K13: 9.4 | L13: 10.2 | M13: 11.1 | N13: 11.8 | O13: 13.5 | P13: 14.2 | Q13: 16.2 | R13: 18 | S13: 20 | T13: 23.4 | U13: 29.9 | V13: 68.4
... A56: Nombre d'individus (en millions) | B56: 68.4 | C56: 3.4 | D56: 3.4 | E56: 3.4 | F56: 3.4 | G56: 3.4 | H56: 3.4 | I56: 3.4 | J56: 3.4 | K56: 3.4 | L56: 3.4 | M56: 3.4 | N56: 3.4 | O56: 3.4 | P56: 3.4 | Q56: 3.4 | R56: 3.4 | S56: 3.4 | T56: 3.4 | U56: 3.4 | V56: 3.4
A58: Source : Insee (2024), Comptes nationaux distribués 2023, base 2020. CND.101 - Comptes nationaux distribués selon les vingtièmes de niveau de vie usuel. See https://www.insee.fr/fr/statistiques/8194104
A59: Notes: Amounts are in € billion.
A60: Individuals are ranked by their "niveau de vie usuel", which is equal to usual disposable income by consumption unit within the household. In our simulations, and in standard tax progressivity analysis, individuals are ranked by their pretax income.
A61: We ignore this inconsistency and we take these tax rate estimate by disposable income group as an approximation of tax rates for the corresponding pretax income groups.
A64: Income concepts | B64: Total | C64: V1 | D64: V2 | E64: V3 | F64: V4 | G64: V5 | H64: V6 | I64: V7 | J64: V8 | K64: V9 | L64: V10 | M64: V11 | N64: V12 | O64: V13 | P64: V14 | Q64: V15 | R64: V16 | S64: V17 | T64: V18 | U64: V19 | V64: V20
A65: DINA Pretax factor income | B65: =B14 -> 2369.9 | C65: =C14 -> 11.9 | D65: =D14 -> 18.8 | E65: =E14 -> 28.8 | F65: =F14 -> 36.9 | G65: =G14 -> 46 | H65: =H14 -> 53.5 | I65: =I14 -> 62.2 | ... V65: =V14 -> 568.7
A66: DINA Pretax income (narrow) | B66: =(B14+B24+B29)*$B14/($B14+$B24+$B29) -> 2369.9 | C66: =(C14+C24+C29)*$B14/($B14+$B24+$B29) -> 12.53504 | D66: =(D14+D24+D29)*$B14/($B14+$B24+$B29) -> 23.80686 | E66: =(E14+E24+E29)*$B14/($B14+$B24+$B29) -> 34.10697 | F66: =(F14+F24+F29)*$B14/($B14+$B24+$B29) -> 42.269322 | G66: =(G14+G24+G29)*$B14/($B14+$B24+$B29) -> 52.860946 | H66: =(H14+H24+H29)*$B14/($B14+$B24+$B29) -> 62.772373 | I66: =(I14+I24+I29)*$B14/($B14+$B24+$B29) -> 69.477162 | ... V66: =(V14+V24+V29)*$B14/($B14+$B24+$B29) -> 532.30195
A67: Benefits - Contributions | B67: =B24+B29 -> 69 | C67: =C24+C29 -> 1 | D67: =D24+D29 -> 5.7 | E67: =E24+E29 -> 6.3 | F67: =F24+F29 -> 6.6 | G67: =G24+G29 -> 8.4 | H67: =H24+H29 -> 11.1 | I67: =I24+I29 -> 9.3 | ... V67: =V24+V29 -> -20.9
A68: Attributed deficit | B68: =- (B14+B24+B29)*(1-$B14/($B14+$B24+$B29)) -> -69 | C68: =- (C14+C24+C29)*(1-$B14/($B14+$B24+$B29)) -> -0.36495961 | D68: =- (D14+D24+D29)*(1-$B14/($B14+$B24+$B29)) -> -0.69314035 | E68: =- (E14+E24+E29)*(1-$B14/($B14+$B24+$B29)) -> -0.99302964 | F68: =- (F14+F24+F29)*(1-$B14/($B14+$B24+$B29)) -> -1.2306778 | G68: =- (G14+G24+G29)*(1-$B14/($B14+$B24+$B29)) -> -1.5390545 | H68: =- (H14+H24+H29)*(1-$B14/($B14+$B24+$B29)) -> -1.8276272 | I68: =- (I14+I24+I29)*(1-$B14/($B14+$B24+$B29)) -> -2.0228382 | ... V68: =- (V14+V24+V29)*(1-$B14/($B14+$B24+$B29)) -> -15.498052
A69: DINA Pretax income (broad) | B69: =(B14+B24+B25+B29+B30+B31-($B31/$B27)*B27)*$B14/($B14+$B24+$B25+$B29+$B30) -> 2369.9 | C69: =(C14+C24+C25+C29+C30+C31-($B31/$B27)*C27)*$B14/($B14+$B24+$B25+$B29+$B30) -> 14.853629 | D69: =(D14+D24+D25+D29+D30+D31-($B31/$B27)*D27)*$B14/($B14+$B24+$B25+$B29+$B30) -> 26.858913 | E69: =(E14+E24+E25+E29+E30+E31-($B31/$B27)*E27)*$B14/($B14+$B24+$B25+$B29+$B30) -> 36.589583 | F69: =(F14+F24+F25+F29+F30+F31-($B31/$B27)*F27)*$B14/($B14+$B24+$B25+$B29+$B30) -> 44.509443 | G69: =(G14+G24+G25+G29+G30+G31-($B31/$B27)*G27)*$B14/($B14+$B24+$B25+$B29+$B30) -> 55.039112 | H69: =(H14+H24+H25+H29+H30+H31-($B31/$B27)*H27)*$B14/($B14+$B24+$B25+$B29+$B30) -> 64.144608 | I69: =(I14+I24+I25+I29+I30+I31-($B31/$B27)*I27)*$B14/($B14+$B24+$B25+$B29+$B30) -> 71.097872 | ... V69: =(V14+V24+V25+V29+V30+V31-($B31/$B27)*V27)*$B14/($B14+$B24+$B25+$B29+$B30) -> 524.57624
A70: Benefits - Contributions | B70: =B24+B25+B29+B30+B31-($B31/$B27)*B27 -> 81.9 | C70: =C24+C25+C29+C30+C31-($B31/$B27)*C27 -> 3.4669468 | D70: =D24+D25+D29+D30+D31-($B31/$B27)*D27 -> 8.9871148 | E70: =E24+E25+E29+E30+E31-($B31/$B27)*E27 -> 9.0540616 | F70: =F24+F25+F29+F30+F31-($B31/$B27)*F27 -> 9.147619 | G70: =G24+G25+G29+G30+G31-($B31/$B27)*G27 -> 10.941176 | H70: =H24+H25+H29+H30+H31-($B31/$B27)*H27 -> 12.861345 | I70: =I24+I25+I29+I30+I31-($B31/$B27)*I27 -> 11.354902 | ... V70: =V24+V25+V29+V30+V31-($B31/$B27)*V27 -> -25.995238
A71: Attributed deficit | B71: =-(B14+B24+B25+B29+B30+B31-($B31/$B27)*B27)*(1-$B14/($B14+$B24+$B25+$B29+$B30)) -> -81.9 | C71: =-(C14+C24+C25+C29+C30+C31-($B31/$B27)*C27)*(1-$B14/($B14+$B24+$B25+$B29+$B30)) -> -0.51331795 | D71: =-(D14+D24+D25+D29+D30+D31-($B31/$B27)*D27)*(1-$B14/($B14+$B24+$B25+$B29+$B30)) -> -0.92820161 | E71: =-(E14+E24+E25+E29+E30+E31-($B31/$B27)*E27)*(1-$B14/($B14+$B24+$B25+$B29+$B30)) -> -1.2644782 | F71: =-(F14+F24+F25+F29+F30+F31-($B31/$B27)*F27)*(1-$B14/($B14+$B24+$B25+$B29+$B30)) -> -1.538176 | G71: =-(G14+G24+G25+G29+G30+G31-($B31/$B27)*G27)*(1-$B14/($B14+$B24+$B25+$B29+$B30)) -> -1.9020647 | H71: =-(H14+H24+H25+H29+H30+H31-($B31/$B27)*H27)*(1-$B14/($B14+$B24+$B25+$B29+$B30)) -> -2.2167363 | I71: =-(I14+I24+I25+I29+I30+I31-($B31/$B27)*I27)*(1-$B14/($B14+$B24+$B25+$B29+$B30)) -> -2.4570301 | ... V71: =-(V14+V24+V25+V29+V30+V31-($B31/$B27)*V27)*(1-$B14/($B14+$B24+$B25+$B29+$B30)) -> -18.128526
A72: IPP Economic income | B72: =B2+B8+B24+B25+B29+B30 -> 2106.5 | C72: =C2+C8+C24+C25+C29+C30 -> 14.3 | D72: =D2+D8+D24+D25+D29+D30 -> 25.5 | E72: =E2+E8+E24+E25+E29+E30 -> 34 | F72: =F2+F8+F24+F25+F29+F30 -> 41.1 | G72: =G2+G8+G24+G25+G29+G30 -> 50.4 | H72: =H2+H8+H24+H25+H29+H30 -> 58.7 | I72: =I2+I8+I24+I25+I29+I30 -> 64.4 | ... V72: =V2+V8+V24+V25+V29+V30 -> 459.5
A74: Notes: We apply the WIL DINA guidelines to reconstitute the distribution of pretax income. See https://wid.world/document/distributional-national-accounts-guidelines-2020-concepts-and-methods-used-in-the-world-inequality-database/
A76: Alternative tax rate definitions | B76: Total | C76: V1 | D76: V2 | E76: V3 | F76: V4 | G76: V5 | H76: V6 | I76: V7 | J76: V8 | K76: V9 | L76: V10 | M76: V11 | N76: V12 | O76: V13 | P76: V14 | Q76: V15 | R76: V16 | S76: V17 | T76: V18 | U76: V19 | V76: V20
A77: All taxes / factor income | B77: =-B15/B65 -> 0.53626735 | C77: =-C15/C65 -> 1.1428571 | D77: =-D15/D65 -> 0.84574468 | E77: =-E15/E65 -> 0.63541667 | F77: =-F15/F65 -> 0.61517615 | G77: =-G15/G65 -> 0.57173913 | H77: =-H15/H65 -> 0.56261682 | I77: =-I15/I65 -> 0.54501608 | ... V77: =-V15/V65 -> 0.51503429
A78: All taxes / narrow pretax income | B78: =-B15/B66 -> 0.53626735 | C78: =-C15/C66 -> 1.0849586 | D78: =-D15/D66 -> 0.66787473 | E78: =-E15/E66 -> 0.53654722 | F78: =-F15/F66 -> 0.5370325 | G78: =-G15/G66 -> 0.49753177 | H78: =-H15/H66 -> 0.47951031 | I78: =-I15/I66 -> 0.48793012 | ... V78: =-V15/V66 -> 0.5502516
A79: (All taxes - share of indirect taxes paid out of transfer income) / narrow pretax income | B79: =- (B15 - (B16+B17)*(B30+B31+B32+B33)/B52)/B66 -> 0.52525649 | C79: =- (C15 - (C16+C17)*(C30+C31+C32+C33)/C52)/C66 -> 0.76171965 | D79: =- (D15 - (D16+D17)*(D30+D31+D32+D33)/D52)/D66 -> 0.52201403 | E79: =- (E15 - (E16+E17)*(E30+E31+E32+E33)/E52)/E66 -> 0.46996538 | F79: =- (F15 - (F16+F17)*(F30+F31+F32+F33)/F52)/F66 -> 0.48303701 | G79: =- (G15 - (G16+G17)*(G30+G31+G32+G33)/G52)/G66 -> 0.46385707 | H79: =- (H15 - (H16+H17)*(H30+H31+H32+H33)/H52)/H66 -> 0.45609044 | I79: =- (I15 - (I16+I17)*(I30+I31+I32+I33)/I52)/I66 -> 0.46773319 | ... V79: =- (V15 - (V16+V17)*(V30+V31+V32+V33)/V52)/V66 -> 0.54811552
A80: (All taxes - share of indirect taxes paid out of transfer income including debt-financed pension benefits) / narrow pretax income | B80: =- (B15 - (B16+B17)*(B30+B31+B32+B33+($B67/$B29)*B29)/B52)/B66 -> 0.52024496 | C80: =- (C15 - (C16+C17)*(C30+C31+C32+C33+($B67/$B29)*C29)/C52)/C66 -> 0.75002163 | D80: =- (D15 - (D16+D17)*(D30+D31+D32+D33+($B67/$B29)*D29)/D52)/D66 -> 0.5048728 | E80: =- (E15 - (E16+E17)*(E30+E31+E32+E33+($B67/$B29)*E29)/E52)/E66 -> 0.45874012 | F80: =- (F15 - (F16+F17)*(F30+F31+F32+F33+($B67/$B29)*F29)/F52)/F66 -> 0.47245986 | G80: =- (G15 - (G16+G17)*(G30+G31+G32+G33+($B67/$B29)*G29)/G52)/G66 -> 0.45414566 | H80: =- (H15 - (H16+H17)*(H30+H31+H32+H33+($B67/$B29)*H29)/H52)/H66 -> 0.44599075 | I80: =- (I15 - (I16+I17)*(I30+I31+I32+I33+($B67/$B29)*I29)/I52)/I66 -> 0.45904734 | ... V80: =- (V15 - (V16+V17)*(V30+V31+V32+V33+($B67/$B29)*V29)/V52)/V66 -> 0.54663385
A81: All taxes / broad pretax income | B81: =-B15/B69 -> 0.53626735 | C81: =-C15/C69 -> 0.91560117 | D81: =-D15/D69 -> 0.59198225 | E81: =-E15/E69 -> 0.50014234 | F81: =-F15/F69 -> 0.51000414 | G81: =-G15/G69 -> 0.47784201 | H81: =-H15/H69 -> 0.46925222 | I81: =-I15/I69 -> 0.47680752 | ... V81: =-V15/V69 -> 0.55835545
A82: (All taxes - share of indirect taxes paid out of transfer income) / broad pretax income | B82: =- (B15 - (B16+B17)*(B32+B33+B34)/B52)/B69 -> 0.52970151 | C82: =- (C15 - (C16+C17)*(C32+C33+C34)/C52)/C69 -> 0.69500296 | D82: =- (D15 - (D16+D17)*(D32+D33+D34)/D52)/D69 -> 0.48406572 | E82: =- (E15 - (E16+E17)*(E32+E33+E34)/E52)/E69 -> 0.44612347 | F82: =- (F15 - (F16+F17)*(F32+F33+F34)/F52)/F69 -> 0.4682221 | G82: =- (G15 - (G16+G17)*(G32+G33+G34)/G52)/G69 -> 0.45428858 | H82: =- (H15 - (H16+H17)*(H32+H33+H34)/H52)/H69 -> 0.45206308 | I82: =- (I15 - (I16+I17)*(I32+I33+I34)/I52)/I69 -> 0.46338668 | ... V82: =- (V15 - (V16+V17)*(V32+V33+V34)/V52)/V69 -> 0.55809344
A83: (All taxes - share of indirect taxes paid out of transfer income including debt-financed pensions and unemployment benefits) / broad pretax income | B83: =- (B15 - (B16+B17)*(B32+B33+B34+$B70/($B29+$B30+$B31)*(B29+B30+B31))/B52)/B69 -> 0.52375303 | C83: =- (C15 - (C16+C17)*(C32+C33+C34+$B70/($B29+$B30+$B31)*(C29+C30+C31))/C52)/C69 -> 0.67444756 | D83: =- (D15 - (D16+D17)*(D32+D33+D34+$B70/($B29+$B30+$B31)*(D29+D30+D31))/D52)/D69 -> 0.46246092 | E83: =- (E15 - (E16+E17)*(E32+E33+E34+$B70/($B29+$B30+$B31)*(E29+E30+E31))/E52)/E69 -> 0.43245303 | F83: =- (F15 - (F16+F17)*(F32+F33+F34+$B70/($B29+$B30+$B31)*(F29+F30+F31))/F52)/F69 -> 0.45555599 | G83: =- (G15 - (G16+G17)*(G32+G33+G34+$B70/($B29+$B30+$B31)*(G29+G30+G31))/G52)/G69 -> 0.44287952 | H83: =- (H15 - (H16+H17)*(H32+H33+H34+$B70/($B29+$B30+$B31)*(H29+H30+H31))/H52)/H69 -> 0.44073886 | I83: =- (I15 - (I16+I17)*(I32+I33+I34+$B70/($B29+$B30+$B31)*(I29+I30+I31))/I52)/I69 -> 0.45341538 | ... V83: =- (V15 - (V16+V17)*(V32+V33+V34+$B70/($B29+$B30+$B31)*(V29+V30+V31))/V52)/V69 -> 0.55627217
B84: Total | C84: D1 | E84: D2 | G84: D3 | I84: D4 | K84: D5 | M84: D6 | O84: D7 | Q84: D8 | S84: D9 | U84: D10
A85: All taxes / factor income | B85: =B77 -> 0.53626735 | C85: =SUMPRODUCT(C77:D77,C$42:D$42)/SUM(C$42:D$42) -> 1.0177572 | E85: =SUMPRODUCT(E77:F77,E$42:F$42)/SUM(E$42:F$42) -> 0.62687067 | G85: =SUMPRODUCT(G77:H77,G$42:H$42)/SUM(G$42:H$42) -> 0.56851949 | I85: =SUMPRODUCT(I77:J77,I$42:J$42)/SUM(I$42:J$42) -> 0.53986501 | K85: =SUMPRODUCT(K77:L77,K$42:L$42)/SUM(K$42:L$42) -> 0.53316226 | M85: =SUMPRODUCT(M77:N77,M$42:N$42)/SUM(M$42:N$42) -> 0.5317977 | O85: =SUMPRODUCT(O77:P77,O$42:P$42)/SUM(O$42:P$42) -> 0.5296008 | Q85: =SUMPRODUCT(Q77:R77,Q$42:R$42)/SUM(Q$42:R$42) -> 0.52835793 | S85: =SUMPRODUCT(S77:T77,S$42:T$42)/SUM(S$42:T$42) -> 0.53078943 | U85: =SUMPRODUCT(U77:V77,U$42:V$42)/SUM(U$42:V$42) -> 0.51920127
A86: All taxes / narrow pretax income | B86: =B78 -> 0.53626735 | C86: =SUMPRODUCT(C78:D78,C$42:D$42)/SUM(C$42:D$42) -> 0.90934435 | E86: =SUMPRODUCT(E78:F78,E$42:F$42)/SUM(E$42:F$42) -> 0.53675212 | G86: =SUMPRODUCT(G78:H78,G$42:H$42)/SUM(G$42:H$42) -> 0.49117126 | I86: =SUMPRODUCT(I78:J78,I$42:J$42)/SUM(I$42:J$42) -> 0.4939454 | K86: =SUMPRODUCT(K78:L78,K$42:L$42)/SUM(K$42:L$42) -> 0.50452019 | M86: =SUMPRODUCT(M78:N78,M$42:N$42)/SUM(M$42:N$42) -> 0.50680388 | O86: =SUMPRODUCT(O78:P78,O$42:P$42)/SUM(O$42:P$42) -> 0.52433521 | Q86: =SUMPRODUCT(Q78:R78,Q$42:R$42)/SUM(Q$42:R$42) -> 0.53551448 | S86: =SUMPRODUCT(S78:T78,S$42:T$42)/SUM(S$42:T$42) -> 0.54981927 | U86: =SUMPRODUCT(U78:V78,U$42:V$42)/SUM(U$42:V$42) -> 0.55053177
A87: (All taxes - share of indirect taxes paid out of transfer income) / narrow pretax income | B87: =B79 -> 0.52525649 | C87: =SUMPRODUCT(C79:D79,C$42:D$42)/SUM(C$42:D$42) -> 0.66079097 | E87: =SUMPRODUCT(E79:F79,E$42:F$42)/SUM(E$42:F$42) -> 0.47548451 | G87: =SUMPRODUCT(G79:H79,G$42:H$42)/SUM(G$42:H$42) -> 0.46111591 | I87: =SUMPRODUCT(I79:J79,I$42:J$42)/SUM(I$42:J$42) -> 0.47480871 | K87: =SUMPRODUCT(K79:L79,K$42:L$42)/SUM(K$42:L$42) -> 0.48983738 | M87: =SUMPRODUCT(M79:N79,M$42:N$42)/SUM(M$42:N$42) -> 0.49623013 | O87: =SUMPRODUCT(O79:P79,O$42:P$42)/SUM(O$42:P$42) -> 0.51583662 | Q87: =SUMPRODUCT(Q79:R79,Q$42:R$42)/SUM(Q$42:R$42) -> 0.52875053 | S87: =SUMPRODUCT(S79:T79,S$42:T$42)/SUM(S$42:T$42) -> 0.54437234 | U87: =SUMPRODUCT(U79:V79,U$42:V$42)/SUM(U$42:V$42) -> 0.54749805
A88: (All taxes - share of indirect taxes paid out of transfer income including debt-financed pension benefits) / narrow pretax income | B88: =B80 -> 0.52024496 | C88: =SUMPRODUCT(C80:D80,C$42:D$42)/SUM(C$42:D$42) -> 0.64680107 | E88: =SUMPRODUCT(E80:F80,E$42:F$42)/SUM(E$42:F$42) -> 0.4645329 | G88: =SUMPRODUCT(G80:H80,G$42:H$42)/SUM(G$42:H$42) -> 0.45126746 | I88: =SUMPRODUCT(I80:J80,I$42:J$42)/SUM(I$42:J$42) -> 0.46660856 | K88: =SUMPRODUCT(K80:L80,K$42:L$42)/SUM(K$42:L$42) -> 0.48260613 | M88: =SUMPRODUCT(M80:N80,M$42:N$42)/SUM(M$42:N$42) -> 0.48917509 | O88: =SUMPRODUCT(O80:P80,O$42:P$42)/SUM(O$42:P$42) -> 0.50986525 | Q88: =SUMPRODUCT(Q80:R80,Q$42:R$42)/SUM(Q$42:R$42) -> 0.52361745 | S88: =SUMPRODUCT(S80:T80,S$42:T$42)/SUM(S$42:T$42) -> 0.54009579 | U88: =SUMPRODUCT(U80:V80,U$42:V$42)/SUM(U$42:V$42) -> 0.54534705
A89: All taxes / broad pretax income | B89: =B81 -> 0.53626735 | C89: =SUMPRODUCT(C81:D81,C$42:D$42)/SUM(C$42:D$42) -> 0.77934058 | E89: =SUMPRODUCT(E81:F81,E$42:F$42)/SUM(E$42:F$42) -> 0.50430621 | G89: =SUMPRODUCT(G81:H81,G$42:H$42)/SUM(G$42:H$42) -> 0.47481032 | I89: =SUMPRODUCT(I81:J81,I$42:J$42)/SUM(I$42:J$42) -> 0.48436017 | K89: =SUMPRODUCT(K81:L81,K$42:L$42)/SUM(K$42:L$42) -> 0.49857485 | M89: =SUMPRODUCT(M81:N81,M$42:N$42)/SUM(M$42:N$42) -> 0.50639811 | O89: =SUMPRODUCT(O81:P81,O$42:P$42)/SUM(O$42:P$42) -> 0.52614675 | Q89: =SUMPRODUCT(Q81:R81,Q$42:R$42)/SUM(Q$42:R$42) -> 0.54045245 | S89: =SUMPRODUCT(S81:T81,S$42:T$42)/SUM(S$42:T$42) -> 0.55719283 | U89: =SUMPRODUCT(U81:V81,U$42:V$42)/SUM(U$42:V$42) -> 0.55815906
A90: (All taxes - share of indirect taxes paid out of transfer income) / broad pretax income | B90: =B82 -> 0.52970151 | C90: =SUMPRODUCT(C82:D82,C$42:D$42)/SUM(C$42:D$42) -> 0.60618728 | E90: =SUMPRODUCT(E82:F82,E$42:F$42)/SUM(E$42:F$42) -> 0.455454 | G90: =SUMPRODUCT(G82:H82,G$42:H$42)/SUM(G$42:H$42) -> 0.45350311 | I90: =SUMPRODUCT(I82:J82,I$42:J$42)/SUM(I$42:J$42) -> 0.47214042 | K90: =SUMPRODUCT(K82:L82,K$42:L$42)/SUM(K$42:L$42) -> 0.49004678 | M90: =SUMPRODUCT(M82:N82,M$42:N$42)/SUM(M$42:N$42) -> 0.50028963 | O90: =SUMPRODUCT(O82:P82,O$42:P$42)/SUM(O$42:P$42) -> 0.52188296 | Q90: =SUMPRODUCT(Q82:R82,Q$42:R$42)/SUM(Q$42:R$42) -> 0.53751356 | S90: =SUMPRODUCT(S82:T82,S$42:T$42)/SUM(S$42:T$42) -> 0.55536807 | U90: =SUMPRODUCT(U82:V82,U$42:V$42)/SUM(U$42:V$42) -> 0.55764618
A91: (All taxes - share of indirect taxes paid out of transfer income including debt-financed pensions and unemployment benefits) / broad pretax income | B91: =B83 -> 0.52375303 | C91: =SUMPRODUCT(C83:D83,C$42:D$42)/SUM(C$42:D$42) -> 0.58519002 | E91: =SUMPRODUCT(E83:F83,E$42:F$42)/SUM(E$42:F$42) -> 0.44220761 | G91: =SUMPRODUCT(G83:H83,G$42:H$42)/SUM(G$42:H$42) -> 0.44212399 | I91: =SUMPRODUCT(I83:J83,I$42:J$42)/SUM(I$42:J$42) -> 0.46266399 | K91: =SUMPRODUCT(K83:L83,K$42:L$42)/SUM(K$42:L$42) -> 0.48163197 | M91: =SUMPRODUCT(M83:N83,M$42:N$42)/SUM(M$42:N$42) -> 0.49227262 | O91: =SUMPRODUCT(O83:P83,O$42:P$42)/SUM(O$42:P$42) -> 0.51497106 | Q91: =SUMPRODUCT(Q83:R83,Q$42:R$42)/SUM(Q$42:R$42) -> 0.53154438 | S91: =SUMPRODUCT(S83:T83,S$42:T$42)/SUM(S$42:T$42) -> 0.55033213 | U91: =SUMPRODUCT(U83:V83,U$42:V$42)/SUM(U$42:V$42) -> 0.55502532
A93: Notes: Indirect taxes paid out of transfer income are computed by multiplying total indirect taxes by the share of monetary transfers in disposable income within each group.
A94: When the income concept used in the denominator is narrow pretax income, we consider as 'transfer income' all monetary transfers except pensions, since in this case pensions are already included in pretax income.
A95: When the income concept used in the denominator is broad pretax income, we consider as 'transfer income' all monetary transfers except pensions and unemployment benefits, since in this case both pensions and UB are already included in pretax income.
A96: Debt financed pensions and unemployment benefits are computed as a fixed share of pensions and UB across income groups, where the share is equal to the aggregate ratio of deficit to total benefits.
A97: See Appendix 4 in Saez & Zucman (2023), Distributional Tax Analysis in Theory and Practice: Harberger Meets Diamond-Mirrlees.
A99: Breakdown by type of taxes | B99: Total | C99: V1 | D99: V2 | E99: V3 | F99: V4 | G99: V5 | H99: V6 | I99: V7 | J99: V8 | K99: V9 | L99: V10 | M99: V11 | N99: V12 | O99: V13 | P99: V14 | Q99: V15 | R99: V16 | S99: V17 | T99: V18 | U99: V19 | V99: V20
A100: Consumption taxes (exluding those paid out of transfer income) | B100: =- (B16+B17 - (B16+B17)*(B32+B33+B34+$B70/($B29+$B30+$B31)*(B29+B30+B31))/B52)/B69 -> 0.10850344 | C100: =- (C16+C17 - (C16+C17)*(C32+C33+C34+$B70/($B29+$B30+$B31)*(C29+C30+C31))/C52)/C69 -> 0.21664697 | D100: =- (D16+D17 - (D16+D17)*(D32+D33+D34+$B70/($B29+$B30+$B31)*(D29+D30+D31))/D52)/D69 -> 0.23162507 | E100: =- (E16+E17 - (E16+E17)*(E32+E33+E34+$B70/($B29+$B30+$B31)*(E29+E30+E31))/E52)/E69 -> 0.16735025 | F100: =- (F16+F17 - (F16+F17)*(F32+F33+F34+$B70/($B29+$B30+$B31)*(F29+F30+F31))/F52)/F69 -> 0.16348314 | G100: =- (G16+G17 - (G16+G17)*(G32+G33+G34+$B70/($B29+$B30+$B31)*(G29+G30+G31))/G52)/G69 -> 0.14854338 | H100: =- (H16+H17 - (H16+H17)*(H32+H33+H34+$B70/($B29+$B30+$B31)*(H29+H30+H31))/H52)/H69 -> 0.14609211 | I100: =- (I16+I17 - (I16+I17)*(I32+I33+I34+$B70/($B29+$B30+$B31)*(I29+I30+I31))/I52)/I69 -> 0.13976324 | ... V100: =- (V16+V17 - (V16+V17)*(V32+V33+V34+$B70/($B29+$B30+$B31)*(V29+V30+V31))/V52)/V69 -> 0.056821405
A101: Production taxes | B101: =- (B18+B19)/B69 -> 0.03793409 | C101: =- (C18+C19)/C69 -> 0.047126531 | D101: =- (D18+D19)/D69 -> 0.037231588 | E101: =- (E18+E19)/E69 -> 0.035529238 | F101: =- (F18+F19)/F69 -> 0.038194142 | G101: =- (G18+G19)/G69 -> 0.038154686 | H101: =- (H18+H19)/H69 -> 0.038974437 | I101: =- (I18+I19)/I69 -> 0.039382332 | ... V101: =- (V18+V19)/V69 -> 0.027641359
A102: Corporate income tax | B102: =- B20/B$69 -> 0.032912781 | C102: =- C20/C$69 -> 0.026929446 | D102: =- D20/D$69 -> 0.011169476 | E102: =- E20/E$69 -> 0.0081990548 | F102: =- F20/F$69 -> 0.0067401428 | G102: =- G20/G$69 -> 0.0054506694 | H102: =- H20/H$69 -> 0.0077948874 | I102: =- I20/I$69 -> 0.0042195356 | ... V102: =- V20/V$69 -> 0.10942166
A103: Contribution sociale généralisée (CSG) | B103: =- B21/B$69 -> 0.062154521 | C103: =- C21/C$69 -> 0.033661808 | D103: =- D21/D$69 -> 0.033508429 | E103: =- E21/E$69 -> 0.040995274 | F103: =- F21/F$69 -> 0.049427714 | G103: =- G21/G$69 -> 0.050872914 | H103: =- H21/H$69 -> 0.057682167 | I103: =- I21/I$69 -> 0.06048001 | ... V103: =- V21/V$69 -> 0.055854608
A104: Income tax | B104: =- B22/B$69 -> 0.042871007 | C104: =- C22/C$69 -> 0.18177376 | D104: =- D22/D$69 -> 0 | E104: =- E22/E$69 -> 0 | F104: =- F22/F$69 -> 0.0022467143 | G104: =- G22/G$69 -> 0 | H104: =- H22/H$69 -> 0 | I104: =- I22/I$69 -> 0.0028130237 | ... V104: =- V22/V$69 -> 0.09417125
A105: Other taxes on personal income and wealth | B105: =- B23/B$69 -> 0.010295793 | C105: =- C23/C$69 -> 0.013464723 | D105: =- D23/D$69 -> 0.0074463177 | E105: =- E23/E$69 -> 0.0054660365 | F105: =- F23/F$69 -> 0.0044934285 | G105: =- G23/G$69 -> 0.0054506694 | H105: =- H23/H$69 -> 0.0062359099 | I105: =- I23/I$69 -> 0.0056260474 | ... V105: =- V23/V$69 -> 0.016775445
A106: Pension SSCs | B106: =- B24/B$69 -> 0.13878223 | C106: =- C24/C$69 -> 0.094253062 | D106: =- D24/D$69 -> 0.093078971 | E106: =- E24/E$69 -> 0.11478677 | F106: =- F24/F$69 -> 0.125816 | G106: =- G24/G$69 -> 0.1253654 | H106: =- H24/H$69 -> 0.12160024 | I106: =- I24/I$69 -> 0.1308056 | ... V106: =- V24/V$69 -> 0.10923103
A107: UI SSCs | B107: =- B25/B$69 -> 0.01400903 | C107: =- C25/C$69 -> 0.0067323616 | D107: =- D25/D$69 -> 0.0074463177 | E107: =- E25/E$69 -> 0.010932073 | F107: =- F25/F$69 -> 0.011233571 | G107: =- G25/G$69 -> 0.012718229 | H107: =- H25/H$69 -> 0.01247182 | I107: =- I25/I$69 -> 0.012658607 | ... V107: =- V25/V$69 -> 0.0097221331
A108: Family SSCs | B108: =- B26/B$69 -> 0.016034432 | C108: =- C26/C$69 -> 0.0067323616 | D108: =- D26/D$69 -> 0.011169476 | E108: =- E26/E$69 -> 0.013665091 | F108: =- F26/F$69 -> 0.013480286 | G108: =- G26/G$69 -> 0.014535118 | H108: =- H26/H$69 -> 0.014030797 | I108: =- I26/I$69 -> 0.01547163 | ... V108: =- V26/V$69 -> 0.014678515
A109: Other SSCs | B109: =- B27/B$69 -> 0.060255707 | C109: =- C27/C$69 -> 0.033661808 | D109: =- D27/D$69 -> 0.029785271 | E109: =- E27/E$69 -> 0.035529238 | F109: =- F27/F$69 -> 0.038194142 | G109: =- G27/G$69 -> 0.038154686 | H109: =- H27/H$69 -> 0.03741546 | I109: =- I27/I$69 -> 0.039382332 | ... V109: =- V27/V$69 -> 0.06157351

Sheet Bach et al. (2025)
B2: Distribution of pre-tax income | H2: Tax rates by pre-tax income groups (% of pre-tax income) | V2: Tax imputations | AE2: Correction parameters | AK2: Anchor variables
B3: Percentile | C3: Number of households above | D3: Income threshold | E3: Mean income above | F3: Income share | H3: p | I3: Income share | K3: Personal Income Tax | L3: Wealth Tax | M3: Non contributive SSCs | N3: Flat-rate withholding tax | O3: CIT | P3: CIT (foreing) | Q3: CIT (domestic) | R3: Total | T3: Memo: DINA correction ? | V3: Indirect taxes | W3: Taxes on production | X3: Gift and inheritance taxes | Y3: Contributive SSCs | AA3: Corrected Total | AE3: P90-P95 | AF3: P95-P99 | AG3: P99-P99.9 | AH3: P99.9-P99.99 | AI3: P99.99-P100
B4: P0 | C4: 37833502 | E4: 32900 | F4: 100 | H4: 90 | I4: 0.0177 | K4: 0.064 | L4: 0.0019 | M4: 0.1248 | N4: 0.0742 | O4: 0.0028 | P4: 0.0001 | Q4: 0.0027 | R4: 0.2676 | T4: =R4/$T$48 -> 0.23785788 | V4: =N4*AE$9 -> 0.074942 | W4: =N4*$AE$13 -> 0.039326 | X4: =L4*AE$17 -> 0.0077669367 | Y4: =M4*AE$5 -> 0.127296 | AA4: =V4 + W4 + R4 + X4 + Y4 -> 0.51693094
B5: P10 | C5: 34050091 | D5: 3400 | E5: 36500 | F5: 99.85 | H5: 91 | I5: 0.0184 | K5: 0.0664 | L5: 0.0021 | M5: 0.1273 | N5: 0.074 | O5: 0.003 | P5: 0.0001 | Q5: 0.003 | R5: 0.2728 | T5: =R5/$T$48 -> 0.24247994 | V5: =N5*AE$9 -> 0.07474 | W5: =N5*$AE$13 -> 0.03922 | X5: =L5*AE$17 -> 0.008584509 | Y5: =M5*AE$5 -> 0.129846 | AA5: =V5 + W5 + R5 + X5 + Y5 -> 0.52519051 | AD5: Contributive SSCs multiplier | AE5: 1.02 | AF5: 0.7 | AG5: 0.5 | AH5: 0.5 | AI5: 0.5 | AK5: Non contributive SSCs
B6: P20 | C6: 30266479 | D6: 9700 | E6: 40200 | F6: 97.75 | H6: 92 | I6: 0.0191 | K6: 0.0689 | L6: 0.0022 | M6: 0.1307 | N6: 0.0737 | O6: 0.0035 | P6: 0.0001 | Q6: 0.0034 | R6: 0.279 | T6: =R6/$T$48 -> 0.24799084 | V6: =N6*AE$9 -> 0.074437 | W6: =N6*$AE$13 -> 0.039061 | X6: =L6*AE$17 -> 0.0089932951 | Y6: =M6*AE$5 -> 0.133314 | AA6: =V6 + W6 + R6 + X6 + Y6 -> 0.5348053 | AD6: Induced SSCs tax rate | AE6: =(SUMPRODUCT(Y4:Y8, I4:I8))/SUM(I4:I8) + (SUMPRODUCT(M4:M8, I4:I8))/SUM(I4:I8) -> 0.26544064 | AF6: =(SUMPRODUCT(Y9:Y39, I9:I39)+AVERAGE(Y40:Y45)*I40)/SUM(I9:I40) + (SUMPRODUCT(M9:M39, I9:I39)+AVERAGE(M40:M45)*I40)/SUM(I9:I40) -> 0.19475484
B7: P30 | C7: 26483450 | D7: 14500 | E7: 44200 | F7: 94.04 | H7: 93 | I7: 0.0197 | K7: 0.072 | L7: 0.0026 | M7: 0.1343 | N7: 0.0736 | O7: 0.004 | P7: 0.0001 | Q7: 0.0039 | R7: 0.2865 | T7: =R7/$T$48 -> 0.25465726 | V7: =N7*AE$9 -> 0.074336 | W7: =N7*$AE$13 -> 0.039008 | X7: =L7*AE$17 -> 0.01062844 | Y7: =M7*AE$5 -> 0.136986 | AA7: =V7 + W7 + R7 + X7 + Y7 -> 0.54745844 | AD7: Insee target | AE7: =SUM('Insee (2026)'!U106:U109) -> 0.26502153 | AF7: =SUM('Insee (2026)'!V106:V109) -> 0.19520518
B8: P40 | C8: 22699895 | D8: 18200 | E8: 48900 | F8: 89.18 | H8: 94 | I8: 0.021 | K8: 0.0753 | L8: 0.0028 | M8: 0.1385 | N8: 0.0733 | O8: 0.0046 | P8: 0.0001 | Q8: 0.0045 | R8: 0.2946 | T8: =R8/$T$48 -> 0.261857 | V8: =N8*AE$9 -> 0.074033 | W8: =N8*$AE$13 -> 0.038849 | X8: =L8*AE$17 -> 0.011446012 | Y8: =M8*AE$5 -> 0.14127 | AA8: =V8 + W8 + R8 + X8 + Y8 -> 0.56019801
B9: P50 | C9: 18915941 | D9: 21900 | E9: 54600 | F9: 82.98 | H9: 95 | I9: 0.0251 | K9: 0.0798 | L9: 0.0033 | M9: 0.1415 | N9: 0.0729 | O9: 0.0053 | P9: 0.0001 | Q9: 0.0052 | R9: 0.303 | T9: =R9/$T$48 -> 0.26932339 | V9: =N9*AF$9 -> 0.0729 | W9: =N9*$AF$13 -> 0.031347 | X9: =L9*AF$17 -> 0.013489943 | Y9: =M9*AF$5 -> 0.09905 | AA9: =V9 + W9 + R9 + X9 + Y9 -> 0.51978694 | AD9: Indirect taxes multiplier | AE9: 1.01 | AF9: 1 | AG9: 0.8 | AH9: 0.4 | AI9: 0.4 | AK9: CSG
B10: P60 | C10: 15133006 | D10: 27000 | E10: 62200 | F10: 75.62 | H10: 96 | I10: 0.0295 | K10: 0.0866 | L10: 0.0038 | M10: 0.1436 | N10: 0.0728 | O10: 0.0067 | P10: 0.0001 | Q10: 0.0066 | R10: 0.3136 | T10: =R10/$T$48 -> 0.27874526 | V10: =N10*AF$9 -> 0.0728 | W10: =N10*$AF$13 -> 0.031304 | X10: =L10*AF$17 -> 0.015533873 | Y10: =M10*AF$5 -> 0.10052 | AA10: =V10 + W10 + R10 + X10 + Y10 -> 0.53375787 | AD10: Induced indirect tax rate | AE10: =(SUMPRODUCT(V4:V8, I4:I8))/SUM(I4:I8) -> 0.074479127 | AF10: =(SUMPRODUCT(V9:V39, I9:I39)+AVERAGE(V40:V45)*I40)/SUM(I9:I40) -> 0.056630719
B11: P70 | C11: 11349720 | D11: 33600 | E11: 72900 | F11: 66.47 | H11: 97 | I11: 0.0315 | K11: 0.0954 | L11: 0.0047 | M11: 0.1452 | N11: 0.0726 | O11: 0.0088 | P11: 0.0002 | Q11: 0.0086 | R11: 0.3267 | T11: =R11/$T$48 -> 0.29038928 | V11: =N11*AF$9 -> 0.0726 | W11: =N11*$AF$13 -> 0.031218 | X11: =L11*AF$17 -> 0.019212949 | Y11: =M11*AF$5 -> 0.10164 | AA11: =V11 + W11 + R11 + X11 + Y11 -> 0.55137095 | AD11: Insee target | AE11: ='Insee (2026)'!U100 -> 0.073990703 | AF11: ='Insee (2026)'!V100 -> 0.056821405
B12: P80 | C12: 7566688 | D12: 44300 | E12: 90100 | F12: 54.77 | H12: 98 | I12: 0.0398 | K12: 0.1065 | L12: 0.006 | M12: 0.1442 | N12: 0.0725 | O12: 0.0125 | P12: 0.0003 | Q12: 0.0122 | R12: 0.3417 | T12: =R12/$T$48 -> 0.30372212 | V12: =N12*AF$9 -> 0.0725 | W12: =N12*$AF$13 -> 0.031175 | X12: =L12*AF$17 -> 0.024527168 | Y12: =M12*AF$5 -> 0.10094 | AA12: =V12 + W12 + R12 + X12 + Y12 -> 0.57084217
B13: P90 | C13: 3783318 | D13: 62900 | E13: 128000 | F13: 38.91 | H13: 99 | I13: 0.0051 | K13: 0.1213 | L13: 0.008 | M13: 0.1378 | N13: 0.0722 | O13: 0.0213 | P13: 0.0005 | Q13: 0.0208 | R13: 0.3605 | T13: =R13/$T$48 -> 0.32043261 | V13: =N13*AG$9 -> 0.05776 | W13: =N13*$AF$13 -> 0.031046 | X13: =L13*AG$17 -> 0.011646859 | Y13: =M13*AG$5 -> 0.0689 | AA13: =V13 + W13 + R13 + X13 + Y13 -> 0.52985286 | AD13: Production taxes multiplier | AE13: 0.53 | AF13: 0.43 | AK13: CSG
B14: P95 | C14: 1891637 | D14: 86300 | E14: 183000 | F14: 27.81 | H14: 99.1 | I14: 0.0057 | K14: 0.1324 | L14: 0.0095 | M14: 0.1316 | N14: 0.0714 | O14: 0.0311 | P14: 0.0007 | Q14: 0.0304 | R14: 0.376 | T14: =R14/$T$48 -> 0.33420988 | V14: =N14*AG$9 -> 0.05712 | W14: =N14*$AF$13 -> 0.030702 | X14: =L14*AG$17 -> 0.013830645 | Y14: =M14*AG$5 -> 0.0658 | AA14: =V14 + W14 + R14 + X14 + Y14 -> 0.54345265 | AD14: Induced production tax rate | AE14: =(SUMPRODUCT(W4:W8, I4:I8))/SUM(I4:I8) -> 0.039083106 | AF14: =(SUMPRODUCT(W9:W39, I9:I39)+AVERAGE(W40:W45)*I40)/SUM(I9:I40) -> 0.028100453
B15: P99 | C15: 378333 | D15: 180000 | E15: 455000 | F15: 13.83 | H15: 99.2 | I15: 0.0063 | K15: 0.1356 | L15: 0.0095 | M15: 0.131 | N15: 0.071 | O15: 0.0342 | P15: 0.0008 | Q15: 0.0334 | R15: 0.3813 | T15: =R15/$T$48 -> 0.33892082 | V15: =N15*AG$9 -> 0.0568 | W15: =N15*$AF$13 -> 0.03053 | X15: =L15*AG$17 -> 0.013830645 | Y15: =M15*AG$5 -> 0.0655 | AA15: =V15 + W15 + R15 + X15 + Y15 -> 0.54796065 | AD15: Insee target | AE15: ='Insee (2026)'!U101 -> 0.039087454 | AF15: ='Insee (2026)'!V101 -> 0.027641359
B16: P99.9 | C16: 37833 | D16: 626000 | E16: 2035000 | F16: 6.19 | H16: 99.3 | I16: 0.0067 | K16: 0.1406 | L16: 0.0101 | M16: 0.1301 | N16: 0.071 | O16: 0.0372 | P16: 0.0009 | Q16: 0.0363 | R16: 0.3891 | T16: =R16/$T$48 -> 0.3458539 | V16: =N16*AG$9 -> 0.0568 | W16: =N16*$AF$13 -> 0.03053 | X16: =L16*AG$17 -> 0.01470416 | Y16: =M16*AG$5 -> 0.06505 | AA16: =V16 + W16 + R16 + X16 + Y16 -> 0.55618416
B17: P99.99 | C17: 3783 | D17: 2592000 | E17: 10875000 | F17: 3.31 | H17: 99.4 | I17: 0.0068 | K17: 0.1443 | L17: 0.0109 | M17: 0.127 | N17: 0.07 | O17: 0.0426 | P17: 0.0009 | Q17: 0.0417 | R17: 0.3948 | T17: =R17/$T$48 -> 0.35092038 | V17: =N17*AG$9 -> 0.056 | W17: =N17*$AF$13 -> 0.0301 | X17: =L17*AG$17 -> 0.015868846 | Y17: =M17*AG$5 -> 0.0635 | AA17: =V17 + W17 + R17 + X17 + Y17 -> 0.56026885 | AD17: Inheritance tax multiplier | AE17: ='Bozio et al. (2020)'!L6 -> 4.0878614 | AF17: ='Bozio et al. (2020)'!L6 -> 4.0878614 | AG17: ='Bozio et al. (2020)'!L7 -> 1.4558574 | AH17: ='Bozio et al. (2020)'!L8 -> 1.2238981 | AI17: ='Bozio et al. (2020)'!L9 -> 0.88039752 | AK17: Wealth tax
B18: P99.999 | C18: 378 | D18: 14876000 | E18: 64768000 | F18: 1.97 | H18: 99.5 | I18: 0.0073 | K18: 0.1483 | L18: 0.011 | M18: 0.1247 | N18: 0.0693 | O18: 0.0474 | P18: 0.0011 | Q18: 0.0463 | R18: 0.4007 | T18: =R18/$T$48 -> 0.35616463 | V18: =N18*AG$9 -> 0.05544 | W18: =N18*$AF$13 -> 0.029799 | X18: =L18*AG$17 -> 0.016014431 | Y18: =M18*AG$5 -> 0.06235 | AA18: =V18 + W18 + R18 + X18 + Y18 -> 0.56430343
B19: P99.9998 | C19: 75 | D19: 61540000 | E19: 217289000 | F19: 1.31 | H19: 99.6 | I19: 0.0084 | K19: 0.1523 | L19: 0.0118 | M19: 0.1213 | N19: 0.0684 | O19: 0.0541 | P19: 0.0014 | Q19: 0.0527 | R19: 0.4078 | T19: =R19/$T$48 -> 0.36247551 | V19: =N19*AG$9 -> 0.05472 | W19: =N19*$AF$13 -> 0.029412 | X19: =L19*AG$17 -> 0.017179117 | Y19: =M19*AG$5 -> 0.06065 | AA19: =V19 + W19 + R19 + X19 + Y19 -> 0.56976112
H20: 99.7 | I20: 0.0105 | K20: 0.1564 | L20: 0.0121 | M20: 0.1153 | N20: 0.0666 | O20: 0.0643 | P20: 0.0015 | Q20: 0.0628 | R20: 0.4147 | T20: =R20/$T$48 -> 0.36860861 | V20: =N20*AG$9 -> 0.05328 | W20: =N20*$AF$13 -> 0.028638 | X20: =L20*AG$17 -> 0.017615875 | Y20: =M20*AG$5 -> 0.05765 | AA20: =V20 + W20 + R20 + X20 + Y20 -> 0.57188387
B21: Source: Bach et al. (2025), Table 1: Income distribution. Data is for year 2016. | H21: 99.8 | I21: 0.0141 | K21: 0.1612 | L21: 0.0134 | M21: 0.1071 | N21: 0.0653 | O21: 0.0775 | P21: 0.002 | Q21: 0.0755 | R21: 0.4245 | T21: =R21/$T$48 -> 0.3773194 | V21: =N21*AG$9 -> 0.05224 | W21: =N21*$AF$13 -> 0.028079 | X21: =L21*AG$17 -> 0.019508489 | Y21: =M21*AG$5 -> 0.05355 | AA21: =V21 + W21 + R21 + X21 + Y21 -> 0.57787749
H22: 99.9 | I22: 0.0018 | K22: 0.163 | L22: 0.0135 | M22: 0.0995 | N22: 0.0615 | O22: 0.099 | P22: 0.0028 | Q22: 0.0961 | R22: 0.4365 | T22: =R22/$T$48 -> 0.38798567 | V22: =N22*AH$9 -> 0.0246 | W22: =N22*$AF$13 -> 0.026445 | X22: =L22*AH$17 -> 0.016522624 | Y22: =M22*AH$5 -> 0.04975 | AA22: =V22 + W22 + R22 + X22 + Y22 -> 0.55381762
H23: 99.91 | I23: 0.002 | K23: 0.1651 | L23: 0.0144 | M23: 0.0922 | N23: 0.0591 | O23: 0.1167 | P23: 0.0035 | Q23: 0.1132 | R23: 0.4475 | T23: =R23/$T$48 -> 0.39776309 | V23: =N23*AH$9 -> 0.02364 | W23: =N23*$AF$13 -> 0.025413 | X23: =L23*AH$17 -> 0.017624132 | Y23: =M23*AH$5 -> 0.0461 | AA23: =V23 + W23 + R23 + X23 + Y23 -> 0.56027713
H24: 99.92 | I24: 0.0021 | K24: 0.1628 | L24: 0.0138 | M24: 0.0924 | N24: 0.0575 | O24: 0.1207 | P24: 0.0036 | Q24: 0.1171 | R24: 0.4472 | T24: =R24/$T$48 -> 0.39749643 | V24: =N24*AH$9 -> 0.023 | W24: =N24*$AF$13 -> 0.024725 | X24: =L24*AH$17 -> 0.016889793 | Y24: =M24*AH$5 -> 0.0462 | AA24: =V24 + W24 + R24 + X24 + Y24 -> 0.55801479
H25: 99.93 | I25: 0.0023 | K25: 0.1561 | L25: 0.0144 | M25: 0.0857 | N25: 0.0551 | O25: 0.1294 | P25: 0.0042 | Q25: 0.1252 | R25: 0.4406 | T25: =R25/$T$48 -> 0.39162998 | V25: =N25*AH$9 -> 0.02204 | W25: =N25*$AF$13 -> 0.023693 | X25: =L25*AH$17 -> 0.017624132 | Y25: =M25*AH$5 -> 0.04285 | AA25: =V25 + W25 + R25 + X25 + Y25 -> 0.54680713
H26: 99.94 | I26: 0.0026 | K26: 0.1546 | L26: 0.0148 | M26: 0.0819 | N26: 0.0551 | O26: 0.137 | P26: 0.0047 | Q26: 0.1323 | R26: 0.4435 | T26: =R26/$T$48 -> 0.39420767 | V26: =N26*AH$9 -> 0.02204 | W26: =N26*$AF$13 -> 0.023693 | X26: =L26*AH$17 -> 0.018113692 | Y26: =M26*AH$5 -> 0.04095 | AA26: =V26 + W26 + R26 + X26 + Y26 -> 0.54829669
H27: 99.95 | I27: 0.0029 | K27: 0.1544 | L27: 0.0151 | M27: 0.0762 | N27: 0.0534 | O27: 0.1406 | P27: 0.0048 | Q27: 0.1359 | R27: 0.4398 | T27: =R27/$T$48 -> 0.3909189 | V27: =N27*AH$9 -> 0.02136 | W27: =N27*$AF$13 -> 0.022962 | X27: =L27*AH$17 -> 0.018480861 | Y27: =M27*AH$5 -> 0.0381 | AA27: =V27 + W27 + R27 + X27 + Y27 -> 0.54070286
H28: 99.96 | I28: 0.0034 | K28: 0.1521 | L28: 0.0148 | M28: 0.0739 | N28: 0.0521 | O28: 0.1488 | P28: 0.0047 | Q28: 0.1441 | R28: 0.4416 | T28: =R28/$T$48 -> 0.39251884 | V28: =N28*AH$9 -> 0.02084 | W28: =N28*$AF$13 -> 0.022403 | X28: =L28*AH$17 -> 0.018113692 | Y28: =M28*AH$5 -> 0.03695 | AA28: =V28 + W28 + R28 + X28 + Y28 -> 0.53990669
H29: 99.97 | I29: 0.0043 | K29: 0.1462 | L29: 0.0139 | M29: 0.0674 | N29: 0.0482 | O29: 0.1573 | P29: 0.0071 | Q29: 0.1501 | R29: 0.4329 | T29: =R29/$T$48 -> 0.38478579 | V29: =N29*AH$9 -> 0.01928 | W29: =N29*$AF$13 -> 0.020726 | X29: =L29*AH$17 -> 0.017012183 | Y29: =M29*AH$5 -> 0.0337 | AA29: =V29 + W29 + R29 + X29 + Y29 -> 0.52361818
H30: 99.98 | I30: 0.0059 | K30: 0.1371 | L30: 0.0152 | M30: 0.0581 | N30: 0.0456 | O30: 0.1708 | P30: 0.0077 | Q30: 0.163 | R30: 0.4268 | T30: =R30/$T$48 -> 0.37936377 | V30: =N30*AH$9 -> 0.01824 | W30: =N30*$AF$13 -> 0.019608 | X30: =L30*AH$17 -> 0.018603251 | Y30: =M30*AH$5 -> 0.02905 | AA30: =V30 + W30 + R30 + X30 + Y30 -> 0.51230125
H31: 99.99 | I31: 0.0008 | K31: 0.1241 | L31: 0.0141 | M31: 0.0463 | N31: 0.0421 | O31: 0.1902 | P31: 0.0093 | Q31: 0.1809 | R31: 0.4168 | T31: =R31/$T$48 -> 0.37047521 | V31: =N31*AI$9 -> 0.01684 | W31: =N31*$AF$13 -> 0.018103 | X31: =L31*AH$17 -> 0.017256963 | Y31: =M31*AI$5 -> 0.02315 | AA31: =V31 + W31 + R31 + X31 + Y31 -> 0.49214996
H32: 99.991 | I32: 0.0008 | K32: 0.1067 | L32: 0.0143 | M32: 0.0363 | N32: 0.0349 | O32: 0.2171 | P32: 0.0133 | Q32: 0.2038 | R32: 0.4093 | T32: =R32/$T$48 -> 0.36380879 | V32: =N32*AI$9 -> 0.01396 | W32: =N32*$AF$13 -> 0.015007 | X32: =L32*AH$17 -> 0.017501743 | Y32: =M32*AI$5 -> 0.01815 | AA32: =V32 + W32 + R32 + X32 + Y32 -> 0.47391874
H33: 99.992 | I33: 0.0009 | K33: 0.1223 | L33: 0.0126 | M33: 0.0391 | N33: 0.0356 | O33: 0.1985 | P33: 0.0106 | Q33: 0.1879 | R33: 0.4081 | T33: =R33/$T$48 -> 0.36274216 | V33: =N33*AI$9 -> 0.01424 | W33: =N33*$AF$13 -> 0.015308 | X33: =L33*AH$17 -> 0.015421116 | Y33: =M33*AI$5 -> 0.01955 | AA33: =V33 + W33 + R33 + X33 + Y33 -> 0.47261912
H34: 99.993 | I34: 0.001 | K34: 0.1208 | L34: 0.0142 | M34: 0.0388 | N34: 0.0427 | O34: 0.2135 | P34: 0.0128 | Q34: 0.2008 | R34: 0.43 | T34: =R34/$T$48 -> 0.38220811 | V34: =N34*AI$9 -> 0.01708 | W34: =N34*$AF$13 -> 0.018361 | X34: =L34*AH$17 -> 0.017379353 | Y34: =M34*AI$5 -> 0.0194 | AA34: =V34 + W34 + R34 + X34 + Y34 -> 0.50222035
H35: 99.994 | I35: 0.001 | K35: 0.1124 | L35: 0.012 | M35: 0.035 | N35: 0.0368 | O35: 0.2072 | P35: 0.0156 | Q35: 0.1916 | R35: 0.4035 | T35: =R35/$T$48 -> 0.35865342 | V35: =N35*AI$9 -> 0.01472 | W35: =N35*$AF$13 -> 0.015824 | X35: =L35*AH$17 -> 0.014686777 | Y35: =M35*AI$5 -> 0.0175 | AA35: =V35 + W35 + R35 + X35 + Y35 -> 0.46623078
H36: 99.995 | I36: 0.0012 | K36: 0.0952 | L36: 0.0117 | M36: 0.0312 | N36: 0.0298 | O36: 0.2182 | P36: 0.0188 | Q36: 0.1995 | R36: 0.3861 | T36: =R36/$T$48 -> 0.34318733 | V36: =N36*AI$9 -> 0.01192 | W36: =N36*$AF$13 -> 0.012814 | X36: =L36*AH$17 -> 0.014319608 | Y36: =M36*AI$5 -> 0.0156 | AA36: =V36 + W36 + R36 + X36 + Y36 -> 0.44075361
H37: 99.996 | I37: 0.0014 | K37: 0.1067 | L37: 0.013 | M37: 0.0309 | N37: 0.0363 | O37: 0.2213 | P37: 0.0182 | Q37: 0.203 | R37: 0.4083 | T37: =R37/$T$48 -> 0.36291993 | V37: =N37*AI$9 -> 0.01452 | W37: =N37*$AF$13 -> 0.015609 | X37: =L37*AH$17 -> 0.015910675 | Y37: =M37*AI$5 -> 0.01545 | AA37: =V37 + W37 + R37 + X37 + Y37 -> 0.46978968
H38: 99.997 | I38: 0.0017 | K38: 0.0943 | L38: 0.0097 | M38: 0.028 | N38: 0.0343 | O38: 0.2233 | P38: 0.0228 | Q38: 0.2005 | R38: 0.3896 | T38: =R38/$T$48 -> 0.34629832 | V38: =N38*AI$9 -> 0.01372 | W38: =N38*$AF$13 -> 0.014749 | X38: =L38*AH$17 -> 0.011871811 | Y38: =M38*AI$5 -> 0.014 | AA38: =V38 + W38 + R38 + X38 + Y38 -> 0.44394081
H39: 99.998 | I39: 0.0023 | K39: 0.0811 | L39: 0.0105 | M39: 0.0252 | N39: 0.026 | O39: 0.2373 | P39: 0.0264 | Q39: 0.2108 | R39: 0.3801 | T39: =R39/$T$48 -> 0.33785419 | V39: =N39*AI$9 -> 0.0104 | W39: =N39*$AF$13 -> 0.01118 | X39: =L39*AH$17 -> 0.01285093 | Y39: =M39*AI$5 -> 0.0126 | AA39: =V39 + W39 + R39 + X39 + Y39 -> 0.42713093
H40: 99.999 | I40: 0.0088 | K40: 0.0712 | L40: 0.0086 | M40: 0.0153 | N40: 0.0256 | O40: 0.2396 | P40: 0.0409 | Q40: 0.1987 | R40: 0.3604 | T40: =R40/$T$48 -> 0.32034373 | V40: =N40*AI$9 -> 0.01024 | W40: =N40*$AF$13 -> 0.011008 | X40: =L40*AH$17 -> 0.010525523 | Y40: =M40*AI$5 -> 0.00765 | AA40: =V40 + W40 + R40 + X40 + Y40 -> 0.39982352
H41: 99.9992 | K41: 0.0487 | L41: 0.0097 | M41: 0.011 | N41: 0.0188 | O41: 0.2293 | P41: 0.0678 | Q41: 0.1614 | R41: 0.3176 | T41: =R41/$T$48 -> 0.28230069 | V41: =N41*AI$9 -> 0.00752 | W41: =N41*$AF$13 -> 0.008084 | X41: =L41*AH$17 -> 0.011871811 | Y41: =M41*AI$5 -> 0.0055 | AA41: =V41 + W41 + R41 + X41 + Y41 -> 0.35057581
H42: 99.9994 | K42: 0.0443 | L42: 0.0047 | M42: 0.0119 | N42: 0.0098 | O42: 0.1744 | P42: 0.0773 | Q42: 0.0971 | R42: 0.2451 | T42: =R42/$T$48 -> 0.21785862 | V42: =N42*AI$9 -> 0.00392 | W42: =N42*$AF$13 -> 0.004214 | X42: =L42*AH$17 -> 0.005752321 | Y42: =M42*AI$5 -> 0.00595 | AA42: =V42 + W42 + R42 + X42 + Y42 -> 0.26493632
H43: 99.9996 | K43: 0.0434 | L43: 0.0038 | M43: 0.0059 | N43: 0.0086 | O43: 0.2433 | P43: 0.0797 | Q43: 0.1636 | R43: 0.3052 | T43: =R43/$T$48 -> 0.27127887 | V43: =N43*AI$9 -> 0.00344 | W43: =N43*$AF$13 -> 0.003698 | X43: =L43*AH$17 -> 0.0046508127 | Y43: =M43*AI$5 -> 0.00295 | AA43: =V43 + W43 + R43 + X43 + Y43 -> 0.31993881
H44: 99.9998 | K44: 0.0204 | L44: 0.0032 | M44: 0.002 | N44: 0.0097 | O44: 0.2526 | P44: 0.1283 | Q44: 0.1243 | R44: 0.2879 | T44: =R44/$T$48 -> 0.25590166 | V44: =N44*AI$9 -> 0.00388 | W44: =N44*$AF$13 -> 0.004171 | X44: =L44*AH$17 -> 0.0039164739 | Y44: =M44*AI$5 -> 0.001 | AA44: =V44 + W44 + R44 + X44 + Y44 -> 0.30086747
H45: 100 | K45: 0.0122 | L45: 0.0013 | M45: 0.0007 | N45: 0.006 | O45: 0.2304 | P45: 0.1183 | Q45: 0.1122 | R45: 0.2506 | T45: =R45/$T$48 -> 0.22274733 | V45: =N45*AI$9 -> 0.0024 | W45: =N45*$AF$13 -> 0.00258 | X45: =L45*AH$17 -> 0.0015910675 | Y45: =M45*AI$5 -> 0.00035 | AA45: =V45 + W45 + R45 + X45 + Y45 -> 0.25752107
H47: Source: Bach et al. (2025), Figure 6, Effective tax rates as a share of comprehensive income.
H48: Notes: Tax household level. Data is for year 2016. | T48: ='Insee (2026)'!B14/'Insee (2026)'!B72 -> 1.1250415 | V48: Notes: We apply some corrections to Bach et al. (2025) tax rate estimates, in order to include some missing taxes.
H49: Income shares are from WID.world (ptinc992j, 2016). They are included for more precise tax rates aggregation.
V50: For contributive SSCs, indirect taxes and production taxes, our corrections are based on the following strategy:
V51: (i) For each missing tax, we choose an anchor tax from Bach et al (2025) and distribute the missing tax in proportion to this anchor.
V52: (ii) When we have good reasons to think that the missing tax is distributed more progressively (regressively) than the anchor, we use decreasing (increasing) multiplier along the income distribution.
V53: (iii) We calibrate the set of multipliers in such a way that the aggregate tax rates for group P90-P95 and P95-P100 matches the corresponding tax rates in Insee (2024).
V54: For inheritance and gift taxes, we use the ratio of inheritance and gift taxes to wealth tax observed in Bozio et al. (2020). See 'Bozio et al. (2020)' sheet.
V56: Details of the correction strategy:
V58: Bach et al. (2025) estimates exclude "contributive" SSCs, where all pension and unemployment insurance SSCs are considered as contributive.
V59: For computing rates on contributive SSCs, we usethe rate of non-contributive SSCs provided in Bach et al. (2025) as an anchor in order to capture the decreasing share of wage in pre-tax income.
V60: Contributive SSCs are more frequently capped than non contributive SSCs, and therefore much more regressive, so we apply drecreasing multipliers along the income distribution.
V62: Bach et al. (2025) estimates exclude all indirect taxes.
V63: For computing indirect taxes rates, we use the flat-rate witholding tax (CSG) rate as an anchor in order to capture the decreasing share of cash disposable income (fiscal income) in pretax income.
V64: In order to account for decreasing saving rates on fiscal income, we apply drecreasing multipliers along the income distribution.
... V72: We impute inheritance and gift tax by applying these income-group-specific ratios to the wealth tax rates provided in Bach et al (2025).

Sheet Bozio et al. (2020)
C2: Income share | D2: Capital taxes | E2: incl. Corporate taxes | F2: incl. Others capital taxes | G2: incl. Property taxes | H2: incl. Inheritance tax | I2: incl. Wealth taxes | K2: Ratio of property taxes to wealth taxes | L2: Ratio of inheritance tax to wealth taxes
B4: Bottom 50% | C4: 0.22011373 | D4: 0.019037136 | E4: 0.0083147901 | F4: 0.010722346 | G4: 0.009646485 | H4: 0.0010758614 | I4: 0
B5: Middle 40% | C5: 0.46062522 | D5: 0.026619254 | E5: 0.011885801 | F5: 0.014733453 | G5: 0.011248435 | H5: 0.0034333769 | I5: 5.164053e-05 | K5: =G5/I5 -> 217.82184 | L5: =H5/I5 -> 66.48609
B6: Top 10-1% | C6: 0.22048752 | D6: 0.051418856 | E6: 0.026919973 | F6: 0.024498883 | G6: 0.011937176 | H6: 0.01009275 | I6: 0.002468956 | K6: =G6/I6 -> 4.8349084 | L6: =H6/I6 -> 4.0878614
B7: Top 1-0.1% | C7: 0.064790063 | D7: 0.16582075 | E7: 0.11486563 | F7: 0.050955111 | G7: 0.0095300628 | H7: 0.024557193 | I7: 0.016867856 | K7: =G7/I7 -> 0.56498365 | L7: =H7/I7 -> 1.4558574
B8: Top 0,1-0,01% | C8: 0.021636149 | D8: 0.254358 | E8: 0.19791019 | F8: 0.056447817 | G8: 0.0044654578 | H8: 0.028607924 | I8: 0.023374433 | K8: =G8/I8 -> 0.19104026 | L8: =H8/I8 -> 1.2238981
B9: Top 0.01% | C9: 0.012347344 | D9: 0.31878142 | E9: 0.25214389 | F9: 0.066637517 | G9: 0.0011575412 | H9: 0.030657562 | I9: 0.034822409 | K9: =G9/I9 -> 0.033241272 | L9: =H9/I9 -> 0.88039752
B11: Source: Bozio et al (2020), exportresults_tax.xlsx file, 'pretax_tax_det' sheet | K11: =SUMPRODUCT(C4:C9,G4:G9) / SUMPRODUCT(C4:C9,I4:I9) -> 4.1070913 | L11: =SUMPRODUCT(C4:C9,H4:H9) / SUMPRODUCT(C4:C9,I4:I9) -> 2.5540626
B12: Notes: Estimates for year 2016 (before the change from ISF to IFI, as in Bach et al 2025).
B13: Taxes are expressed in % of pre-tax income, by income groups of equal-split adults.
B14: Inheritance tax' include both inheritance and gift taxes

Sheet Piketty, Saez, Zucman (2018)
B2: Distribution of pre-tax income | G2: Tax rates by pre-tax income groups (% of pre-tax income) | P2: Wealth
B3: gperc | C3: nb | D3: thres | E3: sh | F3: avg | G3: tax | H3: effrate | I3: salestax | J3: proptax | K3: govcontrib | L3: ditax | M3: corptax | N3: estatetax | O3: healthtax | P3: hweal | Q3: inctowealth
B4: 0 | C4: 1825869 | D4: 0 | E4: 3.9999999e-05 | F4: 495 | G4: 918 | H4: 1.8545455 | I4: 0.9818182 | J4: 0.18585859 | K4: 0.45858586 | L4: 0.18787879 | M4: 0.038383838 | N4: 0 | O4: 0.20456782 | P4: 7722 | Q4: 0.064102568
B5: 1 | C5: 1826627 | D5: 1100 | E5: 0.00013 | F5: 1707 | G5: 1290 | H5: 0.75571179 | I5: 0.39543059 | J5: 0.065026365 | K5: 0.24604569 | L5: 0.032806091 | M5: 0.015817223 | N5: 0 | O5: 0.042372196 | P5: 6725 | Q5: 0.253829
B6: 2 | C6: 1828777 | D6: 2300 | E6: 0.00021 | F6: 2847 | G6: 1590 | H6: 0.55848259 | I6: 0.26940638 | J6: 0.041447137 | K6: 0.2184756 | L6: 0.017562347 | M6: 0.011942396 | N6: 0 | O6: 0.0050810915 | P6: 5429 | Q6: 0.52440596
B7: 3 | C7: 1826687 | D7: 3400 | E7: 0.00030000001 | F7: 3983 | G7: 1884 | H7: 0.4730103 | I7: 0.21491338 | J7: 0.028370574 | K7: 0.21692193 | L7: 0.0060256086 | M7: 0.0065277428 | N7: 0 | O7: 0.025423317 | P7: 1073 | Q7: 3.7120223
B8: 4 | C8: 1827668 | D8: 4600 | E8: 0.00039999999 | F8: 5365 | G8: 2228 | H8: 0.41528425 | I8: 0.20316869 | J8: 0.030195713 | K8: 0.16756757 | L8: 0.0067101587 | M8: 0.0076421248 | N8: 0 | O8: 0.024267066 | P8: 12733 | Q8: 0.4213461
B9: 5 | C9: 1827423 | D9: 6150 | E9: 0.00052 | F9: 6919 | G9: 2602 | H9: 0.37606591 | I9: 0.19395867 | J9: 0.021534903 | K9: 0.14843185 | L9: 0.0063593006 | M9: 0.0057811821 | N9: 0 | O9: 0.031361181 | P9: 11603 | Q9: 0.59631127
B10: 6 | C10: 1826782 | D10: 7650 | E10: 0.00062000001 | F10: 8275 | G10: 3056 | H10: 0.36930513 | I10: 0.18187311 | J10: 0.014984895 | K10: 0.16036254 | L10: 0.0074924473 | M10: 0.0045921449 | N10: 0 | O10: 0.043703527 | P10: 8995 | Q10: 0.91995555
B11: 7 | C11: 1826475 | D11: 8900 | E11: 0.00070999999 | F11: 9467 | G11: 3204 | H11: 0.33843878 | I11: 0.15664941 | J11: 0.015527622 | K11: 0.15284672 | L11: 0.009823598 | M11: 0.0034857928 | N11: 0 | O11: 0.061121232 | P11: 9199 | Q11: 1.0291336
B12: 8 | C12: 1827870 | D12: 10000 | E12: 0.00079000002 | F12: 10514 | G12: 3491 | H12: 0.33203349 | I12: 0.15255849 | J12: 0.01188891 | K12: 0.1576945 | L12: 0.00741868 | M12: 0.002377782 | N12: 0 | O12: 0.078424429 | P12: 6379 | Q12: 1.6482208
B13: 9 | C13: 1826935 | D13: 11100 | E13: 0.00088000001 | F13: 11699 | G13: 3661 | H13: 0.31293273 | I13: 0.14650825 | J13: 0.014616634 | K13: 0.13650739 | L13: 0.012565177 | M13: 0.0027352765 | N13: 0 | O13: 0.054406203 | P13: 13104 | Q13: 0.89278084
B14: 10 | C14: 1824854 | D14: 12300 | E14: 0.00096999999 | F14: 12842 | G14: 3640 | H14: 0.28344494 | I14: 0.1416446 | J14: 0.011991901 | K14: 0.12552562 | L14: 0.0019467373 | M14: 0.0023360846 | N14: 0 | O14: 0.072656008 | P14: 8188 | Q14: 1.5683928
B15: 11 | C15: 1830117 | D15: 13300 | E15: 0.00105 | F15: 13846 | G15: 3919 | H15: 0.28304204 | I15: 0.13837932 | J15: 0.012927921 | K15: 0.12379026 | L15: 0.0049111657 | M15: 0.003033367 | N15: 0 | O15: 0.068171158 | P15: 13900 | Q15: 0.99611509
... B131: 400 | C131: 411 | D131: 367000000 | E131: 0.01612 | F131: 950575488 | G131: 344839328 | H131: 0.36276901 | I131: 0.023340568 | J131: 0.074621633 | K131: 0.0023451047 | L131: 0.12396587 | M131: 0.12451723 | N131: 0.013978609 | O131: 1.4818538e-05 | P131: 13299999744 | Q131: 0.07147184
B133: Source: Piketty, Saez, Zucman (2018). US DINA files for year 2024. See https://gabriel-zucman.eu/usdina/
B134: Note: Unit of observation is tax unit. Income variable is 'peinc' (no capital gain included).

Sheet Balkir et al. (2025)
B3: Group | C3: Number of tax units | D3: Average Income | E3: Income to wealth ratio | F3: Tax rates by pre-tax income groups (% of pre-tax income)
F4: Total | G4: Individual income and payroll taxes | H4: Corporate income taxes | I4: Estate tax | J4: Other taxes (property, sales
B5: Including pure capital gains
B6: Top 0,0002% (top 400) | C6: 367 | D6: 452300000 | E6: 0.056 | F6: 0.238 | G6: 0.11 | H6: 0.089 | I6: 0.006 | J6: 0.034
B7: Top 0,00005% (top 100) | C7: 92 | D7: 1093400000 | E7: 0.053 | F7: 0.22 | G7: 0.08 | H7: 0.101 | I7: 0.004 | J7: 0.036
B8: Next 0,00015% (next 300) | C8: 276 | D8: 238700000 | E8: 0.063 | F8: 0.266 | G8: 0.156 | H8: 0.071 | I8: 0.009 | J8: 0.03
B9: Excluding pure capital gains
B10: Top 0,0002% (top 400) | C10: 367 | D10: =(D6*C6-F16)/C6 -> 3.9595668e+08 | E10: =E6*(D10/D6) -> 0.049024041 | F10: =F6*($D6/$D10) -> 0.27186661 | G10: =G6*($D6/$D10) -> 0.12565264 | H10: =H6*($D6/$D10) -> 0.10166441 | I10: =I6*($D6/$D10) -> 0.0068537801 | J10: =J6*($D6/$D10) -> 0.038838087
B12: Source : Balkir et al. (2025), Tables 1 and 2.
B13: Notes: Estimates are for years 2018-2020. Observations are tax units.
B14: Income concept in the paper includes "pure capital gains". We use the total amount of pure capital gains provided in the paper in order to remove them from income and to align with the income concept used for the other countries.
B16: Total realized capital gains included in economic income of the top 0,0002% | F16: =0.49*42.2*1000000000 -> 20678000000
B17: Source: Balkir et al. (2025), Table A6.

Sheet Bruil et al. (2025)
C2: Total tax rates by pre-tax income groups (% of pre-tax income) | I2: Distribution of pre-tax national income
B3: Group | C3: Taxes on Personal Income & Wealth | D3: Payroll Taxes | E3: Consumption Taxes | F3: Corporate Income Tax | G3: Total Tax Rate | I3: Group | J3: Number of adults | K3: Income threshold | L3: Average income | M3: Income share (%)
B4: P10-P20 | C4: 0.075960684 | D4: 0.21274184 | E4: 0.20531546 | F4: 0.012630051 | G4: 0.50664804 | I4: Full population | J4: 13332368 | L4: 44371 | M4: 1
B5: P20-P30 | C5: 0.090593913 | D5: 0.17665944 | E5: 0.1730791 | F5: 0.017366535 | G5: 0.45769899 | I5: Bottom 50% | J5: 6666184 | L5: 19049 | M5: 0.215
B6: P30-P40 | C6: 0.10363515 | D6: 0.17453947 | E6: 0.16063245 | F6: 0.018261422 | G6: 0.45706849 | I6: Middle 40% | J6: 5332947 | K6: 34158 | L6: 47982 | M6: 0.433
B7: P40-P50 | C7: 0.11447395 | D7: 0.17761434 | E7: 0.15186467 | F7: 0.017500377 | G7: 0.46145334 | I7: Top 10% | J7: 1333237 | K7: 72164 | L7: 156533 | M7: 0.353
B8: P50-P60 | C8: 0.12764931 | D8: 0.17859025 | E8: 0.14354703 | F8: 0.016906828 | G8: 0.46669341 | I8: Top 1% | J8: 133324 | K8: 226162 | L8: 625482 | M8: 0.141
B9: P60-P70 | C9: 0.1433342 | D9: 0.17669006 | E9: 0.13723024 | F9: 0.016946956 | G9: 0.47420146 | I9: Top 0.1% | J9: 13333 | K9: 1023879 | L9: 2694670 | M9: 0.061
B10: P70-P80 | C10: 0.16273693 | D10: 0.17128099 | E10: 0.13140199 | F10: 0.017638341 | G10: 0.48305826 | I10: Top 0.01% | J10: 1334 | K10: 4372218 | L10: 10921054 | M10: 0.025
B11: P80-P90 | C11: 0.18809367 | D11: 0.15776474 | E11: 0.120821 | F11: 0.019591497 | G11: 0.4862709 | I11: Top 0.001% | J11: 134 | K11: 18828918 | L11: 40602767 | M11: 0.009
B12: P90-P99 | C12: 0.20728807 | D12: 0.10120689 | E12: 0.095152075 | F12: 0.033828154 | G12: 0.43747519 | I12: Top 0.0001% | J12: 14 | K12: 89761129 | L12: 111562388 | M12: 0.003
B13: P99-P99.9 | C13: 0.11227558 | D13: 0.023027495 | E13: 0.047575856 | F13: 0.088936574 | G13: 0.27181551 | I13: Source: Bruil et al. (2025), Table 2: The distribution of pre and post-tax income in 2016. The unit of analysis is the adult (20+ years old) and income is split among all adult members of a household equally. Income groups are defined in terms of all adults in the population, with adults ranked according to pre-tax national income.
B14: P99.9-P99.99 | C14: 0.061872382 | D14: 0.0052210869 | E14: 0.035201892 | F14: 0.11183797 | G14: 0.21413333
B15: P99.99-P99.999 | C15: 0.044620932 | D15: 0.0013255245 | E15: 0.029789039 | F15: 0.11487752 | G15: 0.19061302
B16: P99.999-P99.9999 | C16: 0.02212867 | D16: 0.00031994709 | E16: 0.026581063 | F16: 0.13276331 | G16: 0.18179299
B17: P99.9999-P100 | C17: 0.0023009031 | D17: 6.9734195e-05 | E17: 0.017716005 | F17: 0.14434713 | G17: 0.16443377
C19: Source: Bruil et al. (2025), Figure 6: The effective tax rate by tax type. The unit of analysis is the individual adult and income is split equally among the adult members of a household. Adults are ranked by their pre-tax national income. Estimates are for year 2016.

Sheet Palomo et al. (2025)
C2: Total tax rates by pre-tax income groups (% of pre-tax income) | K2: Distribution of pre-tax income
B3: Group | C3: Total | D3: Indirect taxes | E3: SSC | F3: Personal Income Taxes | G3: Business Income Taxes | H3: Property Taxes | I3: Other | K3: Fractile | L3: N | M3: Income threshold (R$) | N3: Mean income above (R$) | O3: Income threshold (R$) | P3: Mean income above (R$) | Q3: Income share
K4: P0 | Q4: 1
B5: P10-P30 | C5: 0.48921796 | D5: 0.35078787 | E5: 0.07307659 | F5: 0.00011969 | G5: 0.00030281 | H5: 0.03724766 | I5: 0.02768334 | K5: P10 | L5: =L8*(9/5) -> 1.3657529e+08 | N5: =(N6*L6+(L5-L6)*6681)/L5 -> 42778.889 | P5: =N5/4.03 -> 10615.109 | Q5: ='Bach et al. (2025)'!F5/100 -> 0.9985
B6: P30-P40 | C6: 0.4809789 | D6: 0.30598336 | E6: 0.12977363 | F6: 2.907e-05 | G6: 4.455e-05 | H6: 0.01840049 | I6: 0.0267478 | K6: P30 | L6: =L8*(7/5) -> 1.0622522e+08 | N6: =(N7*L7+(L6-L7)*13151)/L6 -> 53092.571 | P6: =N6/4.03 -> 13174.335 | Q6: =(L6*N6)/(L5*N5)*Q5 -> 0.96384647
B7: P40-P50 | C7: 0.44749116 | D7: 0.28814492 | E7: 0.11425879 | F7: 3.216e-05 | G7: 7.44e-05 | H7: 0.01999169 | I7: 0.0249892 | K7: P40 | L7: =L8*(6/5) -> 91050191 | N7: =(N8*L8+(L7-L8)*15882)/L7 -> 59749.5 | P7: =N7/4.03 -> 14826.179 | Q7: =(L7*N7)/(L6*N6)*Q6 -> 0.92974015
B8: P50-P60 | C8: 0.46344125 | D8: 0.27923705 | E8: 0.1365203 | F8: 3.93e-05 | G8: 5.94e-05 | H8: 0.02199091 | I8: 0.02559429 | K8: P50 | L8: 75875159 | M8: 14305 | N8: 68523 | O8: =M8/4.03 -> 3549.6278 | P8: =N8/4.03 -> 17003.226 | Q8: =(L8*N8)/(L7*N7)*Q7 -> 0.88855115
B9: P60-P70 | C9: 0.46875623 | D9: 0.27187731 | E9: 0.14923669 | F9: 6.36e-05 | G9: 5.358e-05 | H9: 0.021793 | I9: 0.02573205 | K9: P60 | L9: =L8*(4/5) -> 60700127 | N9: =(N8*L8-(L8-L9)*19241)/L9 -> 80843.5 | P9: =N9/4.03 -> 20060.422 | Q9: =(L9*N9)/(L8*N8)*Q8 -> 0.83865079
B10: P70-P80 | C10: 0.4378783 | D10: 0.24387754 | E10: 0.14179303 | F10: 0.00442703 | G10: 0.00051422 | H10: 0.02343706 | I10: 0.02382942 | K10: P70 | L10: =L8*(3/5) -> 45525095 | N10: =(N9*L9-(L9-L10)*24114)/L10 -> 99753.333 | P10: =N10/4.03 -> 24752.688 | Q10: =(L10*N10)/(L9*N9)*Q9 -> 0.77611259
B11: P80-P90 | C11: 0.49957817 | D11: 0.20272693 | E11: 0.2220702 | F11: 0.02889696 | G11: 0.00164678 | H11: 0.01911592 | I11: 0.02512138 | K11: P80 | L11: 29837281 | M11: 36178 | N11: 141121 | O11: =M11/4.03 -> 8977.1712 | P11: =N11/4.03 -> 35017.618 | Q11: =(L11*N11)/(L10*N10)*Q10 -> 0.71961025
B12: P90-P95 | C12: 0.51614699 | D12: 0.18110766 | E12: 0.22354726 | F12: 0.06833736 | G12: 0.00311536 | H12: 0.01599547 | I12: 0.02404388 | K12: P90 | L12: 14918640 | M12: 73213 | N12: 230814 | O12: =M12/4.03 -> 18166.998 | P12: =N12/4.03 -> 57273.945 | Q12: =(L12*N12)/(L11*N11)*Q11 -> 0.5884883
B13: P95-P99 | C13: 0.41765649 | D13: 0.10663189 | E13: 0.17045791 | F13: 0.10205763 | G13: 0.00836216 | H13: 0.01140704 | I13: 0.01873986 | K13: P95 | L13: 7459319 | M13: 129125 | N13: 365465 | O13: =M13/4.03 -> 32040.943 | P13: =N13/4.03 -> 90686.104 | Q13: =(L13*N13)/(L12*N12)*Q12 -> 0.46589862
B14: P99-P99.9 | C14: 0.30034455 | D14: 0.06541951 | E14: 0.09615306 | F14: 0.08803768 | G14: 0.02866081 | H14: 0.00737792 | I14: 0.01469557 | K14: P99 | L14: 1491870 | M14: 374526 | N14: 1004838 | O14: =M14/4.03 -> 92934.491 | P14: =N14/4.03 -> 249339.45 | Q14: =(L14*N14)/(L13*N13)*Q13 -> 0.25619667
B15: P99.9-P99.99 | C15: 0.22436049 | D15: 0.0538477 | E15: 0.02595647 | F15: 0.04407764 | G15: 0.08183012 | H15: 0.00447078 | I15: 0.01417778 | K15: P99.9 | L15: 149187 | M15: 1422293 | N15: 4586560 | O15: =M15/4.03 -> 352926.3 | P15: =N15/4.03 -> 1138104.2 | Q15: =(L15*N15)/(L14*N14)*Q14 -> 0.11694038
B16: P99.99-P99.999 | C16: 0.21458076 | D16: 0.04940005 | E16: 0.00979626 | F16: 0.03099338 | G16: 0.10685298 | H16: 0.00269878 | I16: 0.01483931 | K16: P99.99 | L16: 14922 | M16: 7003875 | N16: 22950356 | O16: =M16/4.03 -> 1737934.2 | P16: =N16/4.03 -> 5694877.4 | Q16: =(L16*N16)/(L15*N15)*Q15 -> 0.058527896
B17: Top 0.001% | C17: 0.19708729 | D17: 0.04090658 | E17: 0.00188454 | F17: 0.01979182 | G17: 0.11906232 | H17: 0.00066878 | I17: 0.01477325 | K17: P99.999 | L17: 1492 | M17: 36343312 | N17: 111879448 | O17: =M17/4.03 -> 9018191.6 | P17: =N17/4.03 -> 27761650 | Q17: =(L17*N17)/(L16*N16)*Q16 -> 0.028527623
K18: P99.9999 | L18: 152 | M18: 199694816 | N18: 491618912 | O18: =M18/4.03 -> 49552064 | P18: =N18/4.03 -> 1.219898e+08 | Q18: =(L18*N18)/(L17*N17)*Q17 -> 0.012770815
B20: Source: Palomo et al. (2025), Figure 10: Effective Tax Rate by Income Groups, All Taxes. The unit of analysis is the individual adult and income is split equally among the adult members of a household. Adults are ranked by their pre-tax national income. Estimates are for year 2019. Values were eyeballed. | K20: Source: Palomo et al. (2025), Table A1: Descriptive Statistics of Fiscal and Economic Income. Data is for year 2019.
K21: Notes: R$ values are converted to USD values using the end-of-year market exchange rate of USD 1 = R$ 4.03 for 2019
K22: Data reported in the paper was completed with additional data provided by the authors (values in light grey).

Sheet Guzzardi et al. (2024)
B2: Total tax rates by pre-tax income groups (% of pre-tax income)
B3: Group | C3: Total taxes | D3: Personal taxes
B4: P25-50 | C4: 0.42 | D4: 0.1
B5: P50-60 | C5: 0.43 | D5: 0.13
B6: P60-70 | C6: 0.45 | D6: 0.14
B7: P70-80 | C7: 0.47 | D7: 0.14
B8: P80-90 | C8: 0.49 | D8: 0.15
B9: P90-99 | C9: 0.5 | D9: 0.2
B10: P99-99.9 | C10: 0.43 | D10: 0.25
B11: P99.9-100 | C11: 0.36 | D11: 0.15
B12: Berlusconi | C12: 0.18
B14: Source: Guzzardi et al. (2024) Figure 11, Tax rate by income percentiles, 2015 and Figure 12, Tax rate by top income percentiles, 2015. Values were eyeballed.
B15: The estimate for Berlusconi's tax rate is for year 2020.
B18: Distribution of pre-tax national income
B19: Income group | C19: Population | D19: Income threshold | E19: Average income | F19: Income share
B20: Full population | C20: 50699447 | E20: 26357 | F20: 1
B21: P 0–25 | C21: 12674862 | E21: 1814 | F21: 0.017
B22: P 25–50 | C22: 12674862 | D22: 6817 | E22: 13582 | F22: 0.146
B23: P 50–60 | C23: 5069945 | D23: 20006 | E23: 22592 | F23: 0.086
B24: P 60–70 | C24: 5069945 | D24: 25057 | E24: 27618 | F24: 0.105
B25: P 70–80 | C25: 5069945 | D25: 30433 | E25: 33938 | F25: 0.129
B26: P 80–90 | C26: 5069945 | D26: 37957 | E26: 43279 | F26: 0.164
B27: Top 10% | C27: 5069945 | D27: 50313 | E27: 97649 | F27: 0.37
B28: Top 5% | C28: 2534972 | D28: 68534 | E28: 137611 | F28: 0.261
B29: Top 1% | C29: 506994 | D29: 147733 | E29: 310672 | F29: 0.118
B30: Top 0.1% | C30: 50699 | D30: 507543 | E30: 1195681 | F30: 0.045 | G30: =E30/D30 -> 2.3558221 | H30: (Pareto coefficient used in the simulations for dissagregating the top 0,1%)
B32: Source: Guzzardi et al. (2024), Table 4, Pre-tax National Income thresholds, averages, and shares in 2015, 18 years or older.

Sheet WID
D2: Average pre-tax income within percentile group | O2: Annual nominal growth rate
B3: Country | C3: Percentile | D3: 2015 | E3: 2016 | F3: 2017 | G3: 2018 | H3: 2019 | I3: 2020 | J3: 2021 | K3: 2022 | L3: 2023 | M3: 2024
B5: France | C5: p99p99.9 | D5: 281665.81 | E5: 283728.64 | F5: 293012.29 | G5: 306547.68 | H5: 311439.8 | I5: 287122.09 | J5: 323189.62 | K5: 338549.96 | L5: 353306.3 | M5: 365008.61 | O5: =(M5/E5)^(1/8) - 1 -> 0.031988821
B6: France | C6: p99.9p99.99 | D6: 926532.28 | E6: 944375.37 | F6: 1010828.4 | G6: 1168007.4 | H6: 1159051.5 | I6: 1042575.9 | J6: 1340605 | K6: 1341070.5 | L6: 1367315.3 | M6: 1412604 | O6: =(M6/E6)^(1/8) - 1 -> 0.051621534
B7: France | C7: p99.99p99.999 | D7: 3253157.8 | E7: 3369797.6 | F7: 3710636 | G7: 4906499.6 | H7: 4777769.6 | I7: 4178577.9 | J7: 6183935.5 | K7: 5767540.9 | L7: 5489222.2 | M7: 5671037.8 | O7: =(M7/E7)^(1/8) - 1 -> 0.067228319
B8: France | C8: p99.999p100 | D8: 16944652 | E8: 17968758 | F8: 25213361 | G8: 33431961 | H8: 25645139 | I8: 25081436 | J8: 49235846 | K8: 32558968 | L8: 39605408 | M8: 40917220 | O8: =(M8/E8)^(1/8) - 1 -> 0.10834128
B10: USA | C10: p99p99.9 | D10: 726678.18 | E10: 729965.76 | F10: 774960.41 | G10: 819467.14 | H10: 847204.37 | I10: 780923.98 | J10: 905777.64 | K10: 1003521.7 | L10: 1057582.7 | M10: 1098008.4 | O10: =(M10/H10)^(1/5) - 1 -> 0.053230665
B11: USA | C11: p99.9p99.99 | D11: 3357210.2 | E11: 3345071.7 | F11: 3491827.4 | G11: 3729826.6 | H11: 3782305.8 | I11: 3503647 | J11: 4284199.5 | K11: 4841063.1 | L11: 5101857.3 | M11: 5296873.9 | O11: =(M11/H11)^(1/5) - 1 -> 0.069676856
B12: USA | C12: p99.99p99.999 | D12: 15710022 | E12: 15528099 | F12: 16145009 | G12: 17046168 | H12: 16863784 | I12: 15805341 | J12: 20176090 | K12: 23136751 | L12: 24383157 | M12: 25315194 | O12: =(M12/H12)^(1/5) - 1 -> 0.084639076
B13: USA | C13: p99.999p100 | D13: 1.2208418e+08 | E13: 1.2105442e+08 | F13: 1.3047656e+08 | G13: 1.2727335e+08 | H13: 1.2114337e+08 | I13: 1.1296727e+08 | J13: 1.5392984e+08 | K13: 1.8632193e+08 | L13: 1.9631099e+08 | M13: 2.0381492e+08 | O13: =(M13/H13)^(1/5) - 1 -> 0.10965318
B15: Netherlands | C15: p99p99.9 | D15: 253281.9 | E15: 258692.55 | F15: 273789.23 | G15: 283919.48 | H15: 283557.82 | I15: 271239.24 | J15: 320360.66 | K15: 342506.86 | L15: 371708.24 | M15: 389175.42 | O15: =(M15/E15)^(1/8) - 1 -> 0.052374181
B16: Netherlands | C16: p99.9p99.99 | D16: 587109.38 | E16: 610732.89 | F16: 639694.46 | G16: 662658.37 | H16: 662721.34 | I16: 633930.8 | J16: 745304.35 | K16: 759000.3 | L16: 825260.49 | M16: 864040.83 | O16: =(M16/E16)^(1/8) - 1 -> 0.044324266
B17: Netherlands | C17: p99.99p99.999 | D17: 1358600.2 | E17: 1439939.3 | F17: 1432915.6 | G17: 1508490.6 | H17: 1575321.2 | I17: 1506884.7 | J17: 1743050.5 | K17: 1785883.1 | L17: 1977897 | M17: 2070841.7 | O17: =(M17/E17)^(1/8) - 1 -> 0.046466517
B18: Netherlands | C18: p99.999p100 | D18: 3626819.1 | E18: 3977355.4 | F18: 3925792.4 | G18: 4133622.2 | H18: 4151640.8 | I18: 3971246.1 | J18: 4781816.1 | K18: 4898927.6 | L18: 5051333.8 | M18: 5288700.5 | O18: =(M18/E18)^(1/8) - 1 -> 0.036261402
B20: Brazil | C20: p99p99.9 | D20: 602409.77 | E20: 604569.49 | F20: 571812.96 | G20: 646331.37 | H20: 603628.42 | I20: 666459.53 | J20: 757766.61 | K20: 880343.72 | L20: 971757.3 | M20: 1031864.8 | O20: =(M20/H20)^(1/5) - 1 -> 0.1131934
B21: Brazil | C21: p99.9p99.99 | D21: 2047459.1 | E21: 2168428.2 | F21: 1497915.5 | G21: 2259899.9 | H21: 2938097.8 | I21: 2876598.8 | J21: 3390869.3 | K21: 3440354.2 | L21: 3917009.6 | M21: 4159294 | O21: =(M21/H21)^(1/5) - 1 -> 0.071989851
B22: Brazil | C22: p99.99p99.999 | D22: 6036333.5 | E22: 3509594.8 | F22: 4168112.7 | G22: 2983067.9 | H22: 4190556.1 | I22: 6550670.6 | J22: 7414119.3 | K22: 3688253.2 | L22: 5148814.7 | M22: 5467291.6 | O22: =(M22/H22)^(1/5) - 1 -> 0.054629983
B23: Brazil | C23: p99.999p100 | D23: 2.3173493e+08 | E23: 1.7892101e+08 | F23: 3.2588594e+08 | G23: 1.9281135e+08 | H23: 2.2789748e+08 | I23: 2.3797058e+08 | J23: 3.2164809e+08 | K23: 2.6631568e+08 | L23: 2.8105293e+08 | M23: 2.9843715e+08 | O23: =(M23/H23)^(1/5) - 1 -> 0.055413566
B25: Italy | C25: p99p99.9 | D25: 175054.99 | E25: 199024.75 | F25: 212661.45 | G25: 216139.16 | H25: 215809.26 | I25: 197155.43 | J25: 215348.03 | K25: 231710.16 | L25: 242256.99 | M25: 248145.29 | O25: =(M25/D25)^(1/9) - 1 -> 0.039529547
B26: Italy | C26: p99.9p99.99 | D26: 449014.54 | E26: 565947.16 | F26: 601140.28 | G26: 607169.54 | H26: 603732.24 | I26: 551547.65 | J26: 649086.7 | K26: 736275.27 | L26: 746578.13 | M26: 764724.49 | O26: =(M26/D26)^(1/9) - 1 -> 0.060947379
B27: Italy | C27: p99.99p99.999 | D27: 1183214 | E27: 1603516.9 | F27: 1712926.6 | G27: 1715913.9 | H27: 1667768.6 | I27: 1523612.3 | J27: 1825556.3 | K27: 2057239.7 | L27: 2094989.7 | M27: 2145910.6 | O27: =(M27/D27)^(1/9) - 1 -> 0.068384531
B28: Italy | C28: p99.999p100 | D28: 3677032.8 | E28: 5905331.1 | F28: 6119727.5 | G28: 6073085.2 | H28: 5928398.5 | I28: 5415985.6 | J28: 6403003.8 | K28: 7235545.2 | L28: 7248733.5 | M28: 7424933.9 | O28: =(M28/D28)^(1/9) - 1 -> 0.081211274
B30: Source: Downloaded from wid.world on 05-02-2026 at 11:06:23.
B31: Notes: Variable aptinc_992_j. Amounts are expressed in current local currency. The population is comprised of individuals over age 20. The base unit is the individual and resources are split equally within couples.
D33: Income thresholds for entering pre-tax income percentile groups | O33: Annual nominal growth rate
B34: Country | C34: Percentile | D34: 2015 | E34: 2016 | F34: 2017 | G34: 2018 | H34: 2019 | I34: 2020 | J34: 2021 | K34: 2022 | L34: 2023 | M34: 2024
B36: France | C36: p99p99.1 | D36: 172900.11 | E36: 188158.63 | F36: 191212.32 | G36: 193427.11 | H36: 182729.64 | I36: 169850.43 | J36: 180506.37 | K36: 191569.67 | L36: 204146.18 | M36: 226912.8 | O36: =(M36/E36)^(1/8) - 1 -> 0.023686218
B37: France | C37: p99.9p99.91 | D37: 545763.32 | E37: 550818.2 | F37: 635770.64 | G37: 635359.72 | H37: 640347.49 | I37: 581432.43 | J37: 759492.1 | K37: 711840.21 | L37: 732402.28 | M37: 833460.9 | O37: =(M37/E37)^(1/8) - 1 -> 0.053136389
B38: France | C38: p99.99p99.991 | D38: 1881298.7 | E38: 1924270.9 | F38: 2078009.8 | G38: 2656934.4 | H38: 2572756.6 | I38: 2298621 | J38: 3216909.5 | K38: 3362174 | L38: 3060872.6 | M38: 3162255 | O38: =(M38/E38)^(1/8) - 1 -> 0.064060531
B39: France | C39: p99.999p100 | D39: 11444661 | E39: 12069486 | F39: 8369288.1 | G39: 21370186 | H39: 11448524 | I39: 16316331 | J39: 30559350 | K39: 21850044 | L39: 24890667 | M39: 25715096 | O39: =(M39/E39)^(1/8) - 1 -> 0.099163812
B41: USA | C41: p99p99.1 | D41: 391226.1 | E41: 393832.65 | F41: 413672.94 | G41: 435602.18 | H41: 449540.95 | I41: 418398.24 | J41: 468632.51 | K41: 513112.32 | L41: 539951.55 | M41: 560591.1 | O41: =(M41/K41)^(1/2) - 1 -> 0.045242063
B42: USA | C42: p99.9p99.91 | D42: 1686992.2 | E42: 1688494.3 | F42: 1784690 | G42: 1898766.4 | H42: 1951092.8 | I42: 1799492.9 | J42: 2152815.6 | K42: 2410702.5 | L42: 2540558 | M42: 2637670.3 | O42: =(M42/K42)^(1/2) - 1 -> 0.046016289
B43: USA | C43: p99.99p99.991 | D43: 7950330.3 | E43: 7879606.4 | F43: 8186686.6 | G43: 8738745.5 | H43: 8754857.5 | I43: 8145419.1 | J43: 10202796 | K43: 11608408 | L43: 12251469 | M43: 12719778 | O43: =(M43/K43)^(1/2) - 1 -> 0.046775212
B44: USA | C44: p99.999p100 | D44: 76965371 | E44: 76268204 | F44: 81670256 | G44: 80781355 | H44: 77393670 | I44: 72181339 | J44: 97333116 | K44: 1.1682108e+08 | L44: 1.2312517e+08 | M44: 127831592 | O44: =(M44/K44)^(1/2) - 1 -> 0.046064574
B46: Netherlands | C46: p99p99.1 | D46: 177219.62 | E46: 180472.82 | F46: 191380.96 | G46: 198325.03 | H46: 198444.18 | I46: 189821.51 | J46: 221804.96 | K46: 239174.83 | L46: 259428.5 | M46: 271619.3 | O46: =(M46/E46)^(1/8) - 1 -> 0.052430928
B47: Netherlands | C47: p99.9p99.91 | D47: 413449.57 | E47: 425896.35 | F47: 447743.86 | G47: 464548.32 | H47: 464623.47 | I47: 444434.59 | J47: 520654.73 | K47: 533419.38 | L47: 578590.49 | M47: 605778.9 | O47: =(M47/E47)^(1/8) - 1 -> 0.045024033
B48: Netherlands | C48: p99.99p99.991 | D48: 954417.9 | E48: 1003016.5 | F48: 1034151.3 | G48: 1077644 | H48: 1078945.2 | I48: 1032063.4 | J48: 1220870.7 | K48: 1250515.8 | L48: 1356411.2 | M48: 1420150.5 | O48: =(M48/E48)^(1/8) - 1 -> 0.044427469
B49: Netherlands | C49: p99.999p100 | D49: 2824906 | E49: 3074477.9 | F49: 3058521.3 | G49: 3214350.2 | H49: 3226466.2 | I49: 3086271.7 | J49: 3707852.5 | K49: 3798387.1 | L49: 3988817.8 | M49: 4176256.3 | O49: =(M49/E49)^(1/8) - 1 -> 0.03902733
B51: Brazil | C51: p99p99.1 | D51: 367066.62 | E51: 385522.83 | F51: 383611.04 | G51: 423057.96 | H51: 403987.25 | I51: 417735.6 | J51: 476231.69 | K51: 661331.52 | L51: 615148.26 | M51: 653197.6 | O51: =(M51/H51)^(1/5) - 1 -> 0.10086835
B52: Brazil | C52: p99.9p99.91 | D52: 1249137.1 | E52: 1109605.1 | F52: 1126844.9 | G52: 1229558 | H52: 1710441.2 | I52: 1352214 | J52: 1620819.1 | K52: 2526784 | L52: 2601812.1 | M52: 2762744.3 | O52: =(M52/H52)^(1/5) - 1 -> 0.10064308
B53: Brazil | C53: p99.99p99.991 | D53: 2639875.7 | E53: 2576466.4 | F53: 3326709.2 | G53: 2444676.6 | H53: 3105491 | I53: 3894848 | J53: 4501120.4 | K53: 3450633.1 | L53: 3941852.5 | M53: 4185671.5 | O53: =(M53/H53)^(1/5) - 1 -> 0.061517047
B54: Brazil | C54: p99.999p100 | D54: 21126576 | E54: 92512569 | F54: 1.6617973e+08 | G54: 5458519.7 | H54: 1.1755707e+08 | I54: 1.2582406e+08 | J54: 1.6855823e+08 | K54: 1.3536696e+08 | L54: 1.4474971e+08 | M54: 153703040 | O54: =(M54/H54)^(1/5) - 1 -> 0.055083278
B56: Italy | C56: p99p99.1 | D56: 117972.46 | E56: 128968.5 | F56: 137074.83 | G56: 139689.09 | H56: 140164.55 | I56: 128048.77 | J56: 139365.45 | K56: 147911.92 | L56: 157335.72 | M56: 161160.1 | O56: =(M56/D56)^(1/9) - 1 -> 0.035268475
B57: Italy | C57: p99.9p99.91 | D57: 301400.22 | E57: 361115.58 | F57: 386113.96 | G57: 390467.74 | H57: 388726.27 | I57: 355127.37 | J57: 419846.47 | K57: 474436.31 | L57: 482035.92 | M57: 493752.9 | O57: =(M57/D57)^(1/9) - 1 -> 0.056375828
B58: Italy | C58: p99.99p99.991 | D58: 778485.33 | E58: 1032045.2 | F58: 1095442.5 | G58: 1100228.4 | H58: 1087554.8 | I58: 993553.15 | J58: 1174620.5 | K58: 1327348.9 | L58: 1347401.9 | M58: 1380154.3 | O58: =(M58/D58)^(1/9) - 1 -> 0.065689781
B59: Italy | C59: p99.999p100 | D59: 2758448.6 | E59: 4292058.5 | F59: 4466335.8 | G59: 4440865.3 | H59: 4343835.2 | I59: 3968381.1 | J59: 4691585.8 | K59: 5301602.4 | L59: 5321581.8 | M59: 5450937 | O59: =(M59/D59)^(1/9) - 1 -> 0.078617252
B61: Source: Downloaded from wid.world on 05-02-2026 at 11:39:59
B62: Notes: Variable tptinc_992_j. Amounts are expressed in current local currency. The population is comprised of individuals over age 20. The base unit is the individual and resources are split equally within couples.
D64: Adult population | O64: Population growth
B65: Country | D65: 2015 | E65: 2016 | F65: 2017 | G65: 2018 | H65: 2019 | I65: 2020 | J65: 2021 | K65: 2022 | L65: 2023 | M65: 2024
B66: France | D66: 50504620 | E66: 50702744 | F66: 50953892 | G66: 51285688 | H66: 51601820 | I66: 51873496 | J66: 52136424 | K66: 52410868 | L66: 52695128 | M66: 52956956 | O66: =(M66/E66)^(1/8) - 1 -> 0.0054522348
B67: USA | D67: 242288453 | E67: 244961813 | F67: 247625094 | G67: 250238203 | H67: 252854125 | I67: 254844656 | J67: 256216438 | K67: 258043797 | L67: 260434000 | M67: 262814969 | O67: =(M67/K67)^(1/2) - 1 -> 0.0092025446
B68: Netherlands | D68: 13234287 | E68: 13336380 | F68: 13449388 | G68: 13568205 | H68: 13703108 | I68: 13832343 | J68: 13954525 | K68: 14132256 | L68: 14327401 | M68: 14475086 | O68: =(M68/E68)^(1/8) - 1 -> 0.010294291
B69: Brazil | D69: 139571188 | E69: 141673438 | F69: 143759375 | G69: 145780906 | H69: 147756922 | I69: 149602453 | J69: 151145594 | K69: 152542422 | L69: 153980281 | M69: 155432016 | O69: =(M69/H69)^(1/5) - 1 -> 0.010179449
B70: Italy | D70: 49418188 | E70: 49409332 | F70: 49414824 | G70: 49419367 | H70: 49415379 | I70: 49356125 | J70: 49326875 | K70: 49349629 | L70: 49376355 | M70: 49380695 | O70: =(M70/D70)^(1/9) - 1 -> -8.4327136e-05
B72: Source: Downloaded from wid.world on 05-02-2026 at 12:05:44
B73: Notes: Variable npopul_992_i. The population is comprised of individuals over age 20.
